Workbook
Name _90346E10___AllReports: 'SLCA Raw'!$A$1:$G$166

Sheet Table of Contents
B2: TABLE OF CONTENTS
B4: =HYPERLINK("#'Main Page & Assumptions'!A1", "Main Page & Assumptions") -> Main Page & Assumptions
B5: =HYPERLINK("#'Summary'!A1", "Summary") -> Summary
B7: DCFs
B8: =HYPERLINK("#'Carveout DCFs'!A1", "Carveout DCFs") -> Carveout DCFs
B9: =HYPERLINK("#'Standalone DCFs'!A1", "Standalone DCFs") -> Standalone DCFs
B11: Supporting
B12: =HYPERLINK('Revenue Build'!A1,"Revenue Build") -> Revenue Build
B13: =HYPERLINK('ISP Carve Out Costs'!A1,"ISP Carve Out Costs") -> ISP Carve Out Costs
B14: =HYPERLINK('SLCA Financials (memo)'!A2,"SLCA Financials") -> SLCA Financials
B15: =HYPERLINK('Individual Cash Flow'!A1,"Individual Cash Flow") -> Individual Cash Flow
B16: =HYPERLINK('Public Comps'!A1,"Public Comps") -> Public Comps
B17: =HYPERLINK('Site By Site Assignments'!A1, "Site By Site Assignments") -> Site By Site Assignments

Sheet Main Page & Assumptions
A1: =HYPERLINK("#'Table of Contents'!A1","<--------") -> <--------
B2: Transaction Assumptions
B4: Transaction Toggle
B5: Scenario Toggle | D5: 2
B8: Operating Assumptions | E8: 1 | J8: 2 | O8: 3
E9: Downside | J9: Base | O9: Upside
E10: 2024 | F10: =E10+1 -> 2025 | G10: =F10+1 -> 2026 | H10: =G10+1 -> 2027 | I10: =H10+1 -> 2028 | J10: 2024 | K10: =J10+1 -> 2025 | L10: =K10+1 -> 2026 | M10: =L10+1 -> 2027 | N10: =M10+1 -> 2028 | O10: 2024 | P10: =O10+1 -> 2025 | Q10: =P10+1 -> 2026 | R10: =Q10+1 -> 2027 | S10: =R10+1 -> 2028
B11: OG Selling Price Growth | E11: -0.02 | F11: 0 | G11: 0.005 | H11: 0.007 | I11: 0.01 | J11: 0.01 | K11: 0.01 | L11: 0.01 | M11: 0.013 | N11: 0.015 | O11: 0.025 | P11: 0.025 | Q11: 0.03 | R11: 0.03 | S11: 0.03
B12: OG Sales Volume Gorwth | E12: -0.05 | F12: -0.02 | G12: 0 | H12: 0.01 | I12: 0.01 | J12: 0.02 | K12: 0.02 | L12: =K12 -> 0.02 | M12: =L12 -> 0.02 | N12: =M12 -> 0.02 | O12: 0.06 | P12: 0.05 | Q12: 0.04 | R12: 0.03 | S12: 0.025
B13: OG Segment Cost of Sales | E13: =52.5 -> 52.5 | F13: =E13*1.035 -> 54.3375 | G13: =F13*1.035 -> 56.239312 | H13: =G13*1.035 -> 58.207688 | I13: =H13*1.035 -> 60.244958 | J13: 50.4 | K13: =J13*1.03 -> 51.912 | L13: =K13*1.03 -> 53.46936 | M13: =L13*1.03 -> 55.073441 | N13: =M13*1.03 -> 56.725644 | O13: 49.3 | P13: =O13*1.025 -> 50.5325 | Q13: =P13*1.025 -> 51.795812 | R13: =Q13*1.025 -> 53.090708 | S13: =R13*1.025 -> 54.417976
B14: ISP Selling Price Growth | E14: 0 | F14: 0.01 | G14: 0.015 | H14: 0.015 | I14: 0.015 | J14: 0.02 | K14: 0.02 | L14: 0.02 | M14: 0.02 | N14: 0.02 | O14: 0.035 | P14: 0.035 | Q14: 0.03 | R14: 0.03 | S14: 0.025
B15: ISP Sales Volume Gorwth | E15: -0.02 | F15: 0 | G15: 0.005 | H15: 0.01 | I15: 0.01 | J15: 0.02 | K15: 0.018 | L15: 0.015 | M15: 0.013 | N15: 0.012 | O15: 0.04 | P15: 0.035 | Q15: 0.03 | R15: 0.025 | S15: 0.02
B16: ISP Segment Cost of Sales | E16: 91 | F16: =E16*1.03 -> 93.73 | G16: =F16*1.03 -> 96.5419 | H16: =G16*1.03 -> 99.438157 | I16: =H16*1.03 -> 102.4213 | J16: =86*1.03 -> 88.58 | K16: =J16*1.03 -> 91.2374 | L16: =K16*1.03 -> 93.974522 | M16: =L16*1.03 -> 96.793758 | N16: =M16*1.03 -> 99.69757 | O16: 87 | P16: =O16*1.02 -> 88.74 | Q16: =P16*1.02 -> 90.5148 | R16: =Q16*1.02 -> 92.325096 | S16: =R16*1.02 -> 94.171598
B17: CapEx % Revenue | E17: 0.055 | F17: =$E$17 -> 0.055 | G17: =$E$17 -> 0.055 | H17: =$E$17 -> 0.055 | I17: =$E$17 -> 0.055 | J17: 0.05 | K17: =$J$17 -> 0.05 | L17: =$J$17 -> 0.05 | M17: =$J$17 -> 0.05 | N17: =$J$17 -> 0.05 | O17: 0.045 | P17: =$O$17 -> 0.045 | Q17: =$O$17 -> 0.045 | R17: =$O$17 -> 0.045 | S17: =$O$17 -> 0.045
B18: Tax Rate | E18: 0.265 | F18: =$E$18 -> 0.265 | G18: =$E$18 -> 0.265 | H18: =$E$18 -> 0.265 | I18: =$E$18 -> 0.265 | J18: =$E$18 -> 0.265 | K18: =$E$18 -> 0.265 | L18: =$E$18 -> 0.265 | M18: =$E$18 -> 0.265 | ... S18: =$E$18 -> 0.265
B20: Carveout Assumptions
B21: See ISP Carve Out Costs
B22: Capex Split (O&G) | D22: 0.5
B24: DCF Assumptions
C25: ISP | D25: O&G
B26: WACC | C26: 0.11 | D26: 0.135
D27: Standalone SLCA
B28: WACC | D28: 0.125
B30: Multiple Assumptions
C31: ISP | D31: O&G
B32: Base | C32: 7.7 | D32: 3.3
B33: Low | C33: 7.3 | D33: 3
B34: High | C34: 8.3 | D34: 3.5
B35: Standalone SLCA
B36: Median | D36: 4.5
B37: Low | D37: 4.3
B38: High | D38: 4.8
B40: Transaction Assumptions
B42: Apollo Offer/Share | D42: 15.5
B43: Diluted Shares Outstanding | D43: 79
B44: Net Debt | D44: 622

Sheet Summary
A1: =HYPERLINK("#'Table of Contents'!A1","<--------") -> <--------
B2: Summary
B4: Sum-Of-Parts | C4: O&G | D4: ISP | E4: Total
B5: Equity Value | C5: ='Carveout DCFs'!C19 -> 481.72421 | D5: ='Carveout DCFs'!C39 -> 733.84829 | E5: =C5+D5 -> 1215.5725
B6: SLCA Standalone Shares | E6: ='Standalone DCF'!C35 -> 79
B7: Diluted Share Price | E7: =E5/E6 -> 15.386994
B10: Standalone | E10: Standalone Total
B11: Equity Value | E11: ='Standalone DCF'!C34 -> 1208.755
B12: SLCA Standalone Shares | E12: ='Standalone DCF'!C35 -> 79
B13: Diluted Share Price | E13: =E11/E12 -> 15.300697
B15: Conclusion: | C15: Value-Neutral

Sheet Revenue Build
A1: =HYPERLINK("#'Table of Contents'!A1","<--------") -> <--------
B2: (NOT in $mm ($000))
B3: U.S. Silica
B4: O&G and I&P Sales Build
C5: Actual | I5: Forecast
C6: 43465 | D6: =EDATE(C6,12) -> 43830 | E6: =EDATE(D6,12) -> 44196 | F6: =EDATE(E6,12) -> 44561 | G6: =EDATE(F6,12) -> 44926 | H6: =EDATE(G6,12) -> 45291 | I6: =EDATE(H6,12) -> 45657 | J6: =EDATE(I6,12) -> 46022 | K6: =EDATE(J6,12) -> 46387 | ... M6: =EDATE(L6,12) -> 47118
B7: Total Revenue | C7: ='SLCA Financials (memo)'!D35*1000 -> 1577298 | D7: ='SLCA Financials (memo)'!E35*1000 -> 1474477 | E7: ='SLCA Financials (memo)'!F35*1000 -> 845885 | F7: ='SLCA Financials (memo)'!G35*1000 -> 1103879 | G7: ='SLCA Financials (memo)'!H35*1000 -> 1525147 | H7: ='SLCA Financials (memo)'!I35*1000 -> 1552022 | I7: =I12+I34 -> 1604624.1 | J7: =J12+J34 -> 1657818.9 | K7: =K12+K34 -> 1710958 | L7: =L12+L34 -> 1767864.4 | M7: =M12+M34 -> 1828297.7
B8: YoY Growth | D8: =D7/C7-1 -> -0.065188062 | E8: =E7/D7-1 -> -0.42631523 | F8: =F7/E7-1 -> 0.30499891 | G8: =G7/F7-1 -> 0.38162516 | H8: =H7/G7-1 -> 0.017621252 | I8: =I7/H7-1 -> 0.033892621 | J8: =J7/I7-1 -> 0.03315092 | K8: =K7/J7-1 -> 0.032053624 | ... M8: =M7/L7-1 -> 0.034184327
B10: O&G
B12: Sales ($000) | C12: 1182991 | D12: 1010521 | E12: 414897 | F12: 615448 | G12: 961667 | H12: 994276 | I12: =I13*I14 -> 1024340.1 | J12: =J13*J14 -> 1055275.1 | K12: =K13*K14 -> 1087144.4 | L12: =L13*L14 -> 1123302.9 | M12: =M13*M14 -> 1162955.5
B13: Tons Sold (000s) | C13: 14242 | D13: 15054 | E13: 7496 | F13: 11610 | G13: 13654 | H13: 13368 | I13: =H13*(1+I24) -> 13635.36 | J13: =I13*(1+J24) -> 13908.067 | K13: =J13*(1+K24) -> 14186.229 | L13: =K13*(1+L24) -> 14469.953 | M13: =L13*(1+M24) -> 14759.352
B14: Average Selling Price ($/ton) | C14: 83.06 | D14: 67.13 | E14: 55.35 | F14: 53.01 | G14: 70.43 | H14: 74.38 | I14: =H14*(1+I23) -> 75.1238 | J14: =I14*(1+J23) -> 75.875038 | K14: =J14*(1+K23) -> 76.633788 | L14: =K14*(1+L23) -> 77.630028 | M14: =L14*(1+M23) -> 78.794478
B15: Segment Contribution Margin ($000) | C15: 357846 | D15: 248594 | E15: 142041 | F15: 160052 | G15: 301837 | H15: 361998 | I15: =I12-(I27*I13) -> 337117.91 | J15: =J12-(J27*J13) -> 333279.54 | K15: =K12-(K27*K13) -> 328615.88 | L15: =L12-(L27*L13) -> 326392.75 | M15: =M12-(M27*M13) -> 325721.69
B17: calculated metrics/ drivers
B19: Contribution Margin % | C19: =C15/C12 -> 0.30249258 | D19: =D15/D12 -> 0.24600577 | E19: =E15/E12 -> 0.34235244 | F19: =F15/F12 -> 0.26005771 | G19: =G15/G12 -> 0.31386852 | H19: =H15/H12 -> 0.36408201 | I19: =I15/I12 -> 0.32910742 | J19: =J15/J12 -> 0.31582242 | ... M19: =M15/M12 -> 0.28008097
B20: % Total Revenue | C20: =C$12/C$7 -> 0.75001109 | D20: =D$12/D$7 -> 0.68534199 | E20: =E$12/E$7 -> 0.49048866 | F20: =F$12/F$7 -> 0.55753212 | G20: =G$12/G$7 -> 0.63054053 | H20: =H$12/H$7 -> 0.64063267 | I20: =I$12/I$7 -> 0.63836762 | J20: =J$12/J$7 -> 0.63654429 | ... M20: =M$12/M$7 -> 0.63608649
B22: Segment Revenue Growth | D22: =D12/C12 -1 -> -0.14579147 | E22: =E12/D12 -1 -> -0.58942268 | F22: =F12/E12 -1 -> 0.48337539 | G22: =G12/F12 -1 -> 0.56254793 | H22: =H12/G12 -1 -> 0.033908827 | I22: =I12/H12-1 -> 0.030237135 | J22: =J12/I12-1 -> 0.0302 | K22: =K12/J12-1 -> 0.0302 | L22: =L12/K12-1 -> 0.03326 | M22: =M12/L12-1 -> 0.0353
B23: Selling Price Growth | D23: =D14/C14 -1 -> -0.19178907 | E23: =E14/D14 -1 -> -0.17548041 | F23: =F14/E14 -1 -> -0.042276423 | G23: =G14/F14 -1 -> 0.32861724 | H23: =H14/G14 -1 -> 0.056084055 | I23: =CHOOSE('Main Page & Assumptions'!$D$5,'Main Page & Assumptions'!E11,'Main Page & Assumptions'!J11,'Main Page & Assumptions'!O11) -> 0.01 | J23: =CHOOSE('Main Page & Assumptions'!$D$5,'Main Page & Assumptions'!F11,'Main Page & Assumptions'!K11,'Main Page & Assumptions'!P11) -> 0.01 | K23: =CHOOSE('Main Page & Assumptions'!$D$5,'Main Page & Assumptions'!G11,'Main Page & Assumptions'!L11,'Main Page & Assumptions'!Q11) -> 0.01 | L23: =CHOOSE('Main Page & Assumptions'!$D$5,'Main Page & Assumptions'!H11,'Main Page & Assumptions'!M11,'Main Page & Assumptions'!R11) -> 0.013 | M23: =CHOOSE('Main Page & Assumptions'!$D$5,'Main Page & Assumptions'!I11,'Main Page & Assumptions'!N11,'Main Page & Assumptions'!S11) -> 0.015
B24: Sales Volume Growth | D24: =D13/C13-1 -> 0.057014464 | E24: =E13/D13-1 -> -0.50205925 | F24: =F13/E13-1 -> 0.54882604 | G24: =G13/F13-1 -> 0.17605512 | H24: =H13/G13-1 -> -0.020946243 | I24: =CHOOSE('Main Page & Assumptions'!$D$5,'Main Page & Assumptions'!E12,'Main Page & Assumptions'!J12,'Main Page & Assumptions'!O12) -> 0.02 | J24: =CHOOSE('Main Page & Assumptions'!$D$5,'Main Page & Assumptions'!F12,'Main Page & Assumptions'!K12,'Main Page & Assumptions'!P12) -> 0.02 | K24: =CHOOSE('Main Page & Assumptions'!$D$5,'Main Page & Assumptions'!G12,'Main Page & Assumptions'!L12,'Main Page & Assumptions'!Q12) -> 0.02 | L24: =CHOOSE('Main Page & Assumptions'!$D$5,'Main Page & Assumptions'!H12,'Main Page & Assumptions'!M12,'Main Page & Assumptions'!R12) -> 0.02 | M24: =CHOOSE('Main Page & Assumptions'!$D$5,'Main Page & Assumptions'!I12,'Main Page & Assumptions'!N12,'Main Page & Assumptions'!S12) -> 0.02
B26: Segment Cost of Sales ($000) | C26: =C12-C15 -> 825145 | D26: =D12-D15 -> 761927 | E26: =E12-E15 -> 272856 | F26: =F12-F15 -> 455396 | G26: =G12-G15 -> 659830 | H26: =H12-H15 -> 632278 | I26: =I12-I15 -> 687222.14 | J26: =J12-J15 -> 721995.58 | ... M26: =M12-M15 -> 837233.76
B27: Segment Cost of Sales / Ton ($/ton) | C27: =C26/C13 -> 57.937439 | D27: =D26/D13 -> 50.612927 | E27: =E26/E13 -> 36.400213 | F27: =F26/F13 -> 39.224462 | G27: =G26/G13 -> 48.325033 | H27: =H26/H13 -> 47.297876 | I27: =CHOOSE('Main Page & Assumptions'!$D$5,'Main Page & Assumptions'!E13,'Main Page & Assumptions'!J13,'Main Page & Assumptions'!O13) -> 50.4 | J27: =CHOOSE('Main Page & Assumptions'!$D$5,'Main Page & Assumptions'!F13,'Main Page & Assumptions'!K13,'Main Page & Assumptions'!P13) -> 51.912 | K27: =CHOOSE('Main Page & Assumptions'!$D$5,'Main Page & Assumptions'!G13,'Main Page & Assumptions'!L13,'Main Page & Assumptions'!Q13) -> 53.46936 | L27: =CHOOSE('Main Page & Assumptions'!$D$5,'Main Page & Assumptions'!H13,'Main Page & Assumptions'!M13,'Main Page & Assumptions'!R13) -> 55.073441 | M27: =CHOOSE('Main Page & Assumptions'!$D$5,'Main Page & Assumptions'!I13,'Main Page & Assumptions'!N13,'Main Page & Assumptions'!S13) -> 56.725644
B28: Contribution Margin / Ton ($/ton) | C28: =C$15/C$13 -> 25.126106 | D28: =D$15/D$13 -> 16.513485 | E28: =E$15/E$13 -> 18.948906 | F28: =F$15/F$13 -> 13.785702 | G28: =G$15/G$13 -> 22.106123 | H28: =H$15/H$13 -> 27.079443 | I28: =I$15/I$13 -> 24.7238 | J28: =J$15/J$13 -> 23.963038 | ... M28: =M$15/M$13 -> 22.068834
B32: ISP
B34: Sales ($000) | C34: 394307 | D34: 463956 | E34: 430988 | F34: 488431 | G34: 563480 | H34: 557746 | I34: =I35*I36 -> 580284.04 | J34: =J35*J36 -> 602543.73 | K34: =K35*K36 -> 623813.53 | L34: =L35*L36 -> 644561.56 | M34: =M35*M36 -> 665342.23
B35: Tons Sold (000s) | C35: 3817 | D35: 3734 | E35: 3634 | F35: 4227 | G35: 4362 | H35: 4010 | I35: =H35*(1+I46) -> 4090.2 | J35: =I35*(1+J46) -> 4163.8236 | K35: =J35*(1+K46) -> 4226.281 | L35: =K35*(1+L46) -> 4281.2226 | M35: =L35*(1+M46) -> 4332.5973
B36: Average Selling Price ($/ton) | C36: 103.3 | D36: 124.25 | E36: 118.6 | F36: 115.55 | G36: 129.18 | H36: 139.09 | I36: =H36*(1+I45) -> 141.8718 | J36: =I36*(1+J45) -> 144.70924 | K36: =J36*(1+K45) -> 147.60342 | L36: =K36*(1+L45) -> 150.55549 | M36: =L36*(1+M45) -> 153.5666
B37: Segment Contribution Margin ($000) | C37: 155084 | D37: 178215 | E37: 159176 | F37: 168499 | G37: 170280 | H37: 187665 | I37: =I34-(I49*I35) -> 217974.12 | J37: =J34-(J49*J35) -> 222647.29 | K37: =K34-(K49*K35) -> 226650.79 | L37: =L34-(L49*L35) -> 230165.94 | M37: =M34-(M49*M35) -> 233392.81
B39: calculated metrics / drivers
B41: Contribution Margin % | C41: =C37/C34 -> 0.39330775 | D41: =D37/D34 -> 0.38412048 | E41: =E37/E34 -> 0.36932815 | F41: =F37/F34 -> 0.34498015 | G41: =G37/G34 -> 0.30219351 | H41: =H37/H34 -> 0.33647036 | I41: =I37/I34 -> 0.37563349 | J41: =J37/J34 -> 0.36951225 | ... M41: =M37/M34 -> 0.3507861
B42: % Total Revenue | C42: =C$34/C$7 -> 0.24998891 | D42: =D$34/D$7 -> 0.31465801 | E42: =E$34/E$7 -> 0.50951134 | F42: =F$34/F$7 -> 0.44246788 | G42: =G$34/G$7 -> 0.36945947 | H42: =H$34/H$7 -> 0.35936733 | I42: =I$34/I$7 -> 0.36163238 | J42: =J$34/J$7 -> 0.36345571 | ... M42: =M$34/M$7 -> 0.36391351
B44: Segment Revenue Growth | D44: =D34/C34 -1 -> 0.17663648 | E44: =E34/D34 -1 -> -0.071058462 | F44: =F34/E34 -1 -> 0.13328213 | G44: =G34/F34 -1 -> 0.15365323 | H44: =H34/G34 -1 -> -0.010176049 | I44: =I34/H34-1 -> 0.04040914 | J44: =J34/I34-1 -> 0.03836 | K44: =K34/J34-1 -> 0.0353 | L44: =L34/K34-1 -> 0.03326 | M44: =M34/L34-1 -> 0.03224
B45: Selling Price Growth | D45: =D36/C36 -1 -> 0.20280736 | E45: =E36/D36 -1 -> -0.045472837 | F45: =F36/E36 -1 -> -0.025716695 | G45: =G36/F36 -1 -> 0.11795759 | H45: =H36/G36 -1 -> 0.076714662 | I45: =CHOOSE('Main Page & Assumptions'!$D$5,'Main Page & Assumptions'!E14,'Main Page & Assumptions'!J14,'Main Page & Assumptions'!O14) -> 0.02 | J45: =CHOOSE('Main Page & Assumptions'!$D$5,'Main Page & Assumptions'!F14,'Main Page & Assumptions'!K14,'Main Page & Assumptions'!P14) -> 0.02 | K45: =CHOOSE('Main Page & Assumptions'!$D$5,'Main Page & Assumptions'!G14,'Main Page & Assumptions'!L14,'Main Page & Assumptions'!Q14) -> 0.02 | L45: =CHOOSE('Main Page & Assumptions'!$D$5,'Main Page & Assumptions'!H14,'Main Page & Assumptions'!M14,'Main Page & Assumptions'!R14) -> 0.02 | M45: =CHOOSE('Main Page & Assumptions'!$D$5,'Main Page & Assumptions'!I14,'Main Page & Assumptions'!N14,'Main Page & Assumptions'!S14) -> 0.02
B46: Sales Volume Growth | D46: =D35/C35-1 -> -0.021744826 | E46: =E35/D35-1 -> -0.026780932 | F46: =F35/E35-1 -> 0.16318107 | G46: =G35/F35-1 -> 0.031937544 | H46: =H35/G35-1 -> -0.080696928 | I46: =CHOOSE('Main Page & Assumptions'!$D$5,'Main Page & Assumptions'!E15,'Main Page & Assumptions'!J15,'Main Page & Assumptions'!O15) -> 0.02 | J46: =CHOOSE('Main Page & Assumptions'!$D$5,'Main Page & Assumptions'!F15,'Main Page & Assumptions'!K15,'Main Page & Assumptions'!P15) -> 0.018 | K46: =CHOOSE('Main Page & Assumptions'!$D$5,'Main Page & Assumptions'!G15,'Main Page & Assumptions'!L15,'Main Page & Assumptions'!Q15) -> 0.015 | L46: =CHOOSE('Main Page & Assumptions'!$D$5,'Main Page & Assumptions'!H15,'Main Page & Assumptions'!M15,'Main Page & Assumptions'!R15) -> 0.013 | M46: =CHOOSE('Main Page & Assumptions'!$D$5,'Main Page & Assumptions'!I15,'Main Page & Assumptions'!N15,'Main Page & Assumptions'!S15) -> 0.012
B48: Segment Cost of Sales ($000) | C48: =C34-C37 -> 239223 | D48: =D34-D37 -> 285741 | E48: =E34-E37 -> 271812 | F48: =F34-F37 -> 319932 | G48: =G34-G37 -> 393200 | H48: =H34-H37 -> 370081 | I48: =I34-I37 -> 362309.92 | J48: =J34-J37 -> 379896.44 | ... M48: =M34-M37 -> 431949.42
B49: Segment Cost of Sales / Ton ($/ton) | C49: =C48/C35 -> 62.673042 | D49: =D48/D35 -> 76.524103 | E49: =E48/E35 -> 74.796918 | F49: =F48/F35 -> 75.687722 | G49: =G48/G35 -> 90.142137 | H49: =H48/H35 -> 92.289526 | I49: =CHOOSE('Main Page & Assumptions'!$D$5,'Main Page & Assumptions'!E16,'Main Page & Assumptions'!J16,'Main Page & Assumptions'!O16) -> 88.58 | J49: =CHOOSE('Main Page & Assumptions'!$D$5,'Main Page & Assumptions'!F16,'Main Page & Assumptions'!K16,'Main Page & Assumptions'!P16) -> 91.2374 | K49: =CHOOSE('Main Page & Assumptions'!$D$5,'Main Page & Assumptions'!G16,'Main Page & Assumptions'!L16,'Main Page & Assumptions'!Q16) -> 93.974522 | L49: =CHOOSE('Main Page & Assumptions'!$D$5,'Main Page & Assumptions'!H16,'Main Page & Assumptions'!M16,'Main Page & Assumptions'!R16) -> 96.793758 | M49: =CHOOSE('Main Page & Assumptions'!$D$5,'Main Page & Assumptions'!I16,'Main Page & Assumptions'!N16,'Main Page & Assumptions'!S16) -> 99.69757
B50: Contribution Margin / Ton ($/ton) | C50: =C37/C35 -> 40.629814 | D50: =D37/D35 -> 47.727638 | E50: =E37/E35 -> 43.801871 | F50: =F37/F35 -> 39.86255 | G50: =G37/G35 -> 39.037139 | H50: =H37/H35 -> 46.799252 | I50: =I37/I35 -> 53.2918 | J50: =J37/J35 -> 53.471836 | ... M50: =M37/M35 -> 53.869029
B55: segment contribution check | C55: =C42+C20 -> 1 | D55: =D42+D20 -> 1 | E55: =E42+E20 -> 1 | F55: =F42+F20 -> 1 | G55: =G42+G20 -> 1 | H55: =H42+H20 -> 1 | I55: =I42+I20 -> 1 | J55: =J42+J20 -> 1 | ... M55: =M42+M20 -> 1
D76: =122.289/D7 * 1000 -> 0.082937204 | H76: =65.47/'Revenue Build'!H7*1000 -> 0.04218368

Sheet ISP Carve Out Costs
A1: =HYPERLINK("#'Table of Contents'!A1","<--------") -> <--------
B2: Carve Out Adjustments (ISP)
B3: ($mm)
C4: Predicted
B5: FYE December | C5: 2024 | D5: =C5+1 -> 2025 | E5: =D5+1 -> 2026 | F5: =E5+1 -> 2027 | G5: =F5+1 -> 2028
B6: 1. PROJECTED SEGMENT EBITDA
B7: Reported EBITDA | C7: ='Individual Cash Flow'!I37 -> 143.86485 | D7: ='Individual Cash Flow'!J37 -> 148.87549 | E7: ='Individual Cash Flow'!K37 -> 151.33485 | F7: ='Individual Cash Flow'!L37 -> 152.36827 | G7: ='Individual Cash Flow'!M37 -> 153.10951
B9: 2. LESS RUN-RATE ADJUSTMENTS
B10: Corporate Functions to be Replaced | C10: =SUM(C11:C16) -> 5 | D10: =SUM(D11:D16) -> 5 | E10: =SUM(E11:E16) -> 5 | F10: =SUM(F11:F16) -> 5 | G10: =SUM(G11:G16) -> 5
B11: Finance/Accounting | C11: 1.2 | D11: 1.2 | E11: 1.2 | F11: 1.2 | G11: 1.2
B12: HR / Payroll | C12: 0.7 | D12: 0.7 | E12: 0.7 | F12: 0.7 | G12: 0.7
B13: IT / Systems | C13: 1.5 | D13: 1.5 | E13: 1.5 | F13: 1.5 | G13: 1.5
B14: Legal / Compliance | C14: 0.6 | D14: 0.6 | E14: 0.6 | F14: 0.6 | G14: 0.6
B15: Treasury | C15: 1 | D15: 1 | E15: 1 | F15: 1 | G15: 1
B16: other | C16: 0 | D16: 0 | E16: 0 | F16: 0 | G16: 0
B17: Total Run-Rate Adjustments | C17: =C10 -> 5 | D17: =D10 -> 5 | E17: =E10 -> 5 | F17: =F10 -> 5 | G17: =G10 -> 5
B19: 3. STANDALONE ADJUSTED EBITDA
B20: Adjusted Ebitda | C20: =C7+C17 -> 148.86485 | D20: =D7+D17 -> 153.87549 | E20: =E7+E17 -> 156.33485 | F20: =F7+F17 -> 157.36827 | G20: =G7+G17 -> 158.10951
B21: EBITDA Margin | C21: =C20/'[1]H.B. Fuller BAS Operating'!F7 -> 0.16644103 | D21: =D20/'[1]H.B. Fuller BAS Operating'!G7 -> 0.16542621 | E21: =E20/'[1]H.B. Fuller BAS Operating'!H7 -> 0.16238665 | F21: =F20/'[1]H.B. Fuller BAS Operating'!I7 -> 0.15793244 | G21: =G20/'[1]H.B. Fuller BAS Operating'!J7 -> 0.1540547
B23: 4. ONE TIME SEPERATION COSTS
B24: IT / Systems | C24: 8 | D24: 4 | E24: 0 | F24: 0 | G24: 0
B25: Legal | C25: 4 | D25: 1 | E25: 0 | F25: 0 | G25: 0
B26: People / HR | C26: 2 | D26: 1 | E26: 0 | F26: 0 | G26: 0
B27: Facilities | C27: 1 | D27: 0 | E27: 0 | F27: 0 | G27: 0
B28: Branding / Rebrand | C28: 0 | D28: 0 | E28: 0 | F28: 0 | G28: 0
B29: Other | C29: 2 | D29: 1 | E29: 0 | F29: 0 | G29: 0
B30: Total One-Time Seperation Costs | C30: =SUM(C24:C29) -> 17 | D30: =SUM(D24:D29) -> 7 | E30: =SUM(E24:E29) -> 0 | F30: =SUM(F24:F29) -> 0 | G30: =SUM(G24:G29) -> 0

Sheet SLCA Financials (memo)
B1: =HYPERLINK("#'Table of Contents'!A1", "<---------") -> <---------
C2: SLCA (memo)
C3: Consolidated Financials($mm)
J4: Forecast
C5: FYE December | D5: ='SLCA Raw'!B3 -> 43465 | E5: =EDATE(D5,12) -> 43830 | F5: =EDATE(E5,12) -> 44196 | G5: =EDATE(F5,12) -> 44561 | H5: =EDATE(G5,12) -> 44926 | I5: =EDATE(H5,12) -> 45291 | J5: =EDATE(I5,12) -> 45657 | K5: =EDATE(J5,12) -> 46022 | L5: =EDATE(K5,12) -> 46387 | ... N5: =EDATE(M5,12) -> 47118
D6: USD | E6: USD | F6: USD | G6: USD | H6: USD | I6: USD | J6: USD | K6: USD | L6: USD | M6: USD | N6: USD
C7: Revenue Drivers
A8: Revenue Growth | C8: Revenue Growth | E8: =E35/D35 - 1 -> -0.065188062 | F8: =F35/E35 - 1 -> -0.42631523 | G8: =G35/F35 - 1 -> 0.30499891 | H8: =H35/G35 - 1 -> 0.38162516 | I8: =I35/H35 - 1 -> 0.017621252 | J8: =J35/I35-1 -> 0.033892621 | K8: =K35/J35-1 -> 0.03315092 | L8: =L35/K35-1 -> 0.032053624 | M8: =M35/L35-1 -> 0.03326 | N8: =N35/M35-1 -> 0.034184327
A9: Gross Margin | C9: Gross Margin | D9: =D38/D35 -> 0.26258133 | E9: =E38/E35 -> 0.23139323 | F9: =F38/F35 -> 0.35154069 | G9: =G38/G35 -> 0.30988994 | H9: =H38/H35 -> 0.32359766 | I9: =I38/I35 -> 0.36664622 | J9: =AVERAGE(G9:I9) -> 0.33337794 | K9: =AVERAGE(H9:J9) -> 0.34120727 | L9: =AVERAGE(I9:K9) -> 0.34707714 | M9: =AVERAGE(J9:L9) -> 0.34055412 | N9: =AVERAGE(K9:M9) -> 0.34294618
A10: SG&A % Revenue | C10: SG&A % Revenue | D10: =D39/D35 -> 0.093178968 | E10: =E39/E35 -> 0.10230611 | F10: =F39/F35 -> 0.17817907 | G10: =G39/G35 -> 0.13843274 | H10: =H39/H35 -> 0.11960421 | I10: =I39/I35 -> 0.10080076 | J10: =AVERAGE($G$10:$I$10) -> 0.11961257 | K10: =J10 -> 0.11961257 | L10: =K10 -> 0.11961257 | M10: =L10 -> 0.11961257 | N10: =M10 -> 0.11961257
A11: R&D % Revenue | C11: R&D % Revenue | D11: =D40/D35 -> 0 | E11: =E40/E35 -> 0 | F11: =F40/F35 -> 0 | G11: =G40/G35 -> 0 | H11: =H40/H35 -> 0 | I11: =I40/I35 -> 0 | J11: =I11 -> 0 | K11: =J11 -> 0 | L11: =K11 -> 0 | M11: =L11 -> 0 | N11: =M11 -> 0
A12: Other Operating Expenses % Revenue | C12: Other Operating Expenses % Revenue | D12: =D$43/D$35 -> 0 | E12: =E$43/E$35 -> 0 | F12: =F$43/F$35 -> 0 | G12: =G$43/G$35 -> 0 | H12: =H$43/H$35 -> 0 | I12: =I$43/I$35 -> 0 | J12: =I12 -> 0 | K12: 0 | L12: 0 | M12: 0 | N12: 0
A13: Gain (Loss) on Asset Sales | C13: Gain (Loss) on Asset Sales | D13: =D$48 -> 0 | E13: =E$48 -> 0 | F13: =F$48 -> 0.3 | G13: =G$48 -> 0 | H13: =H$48 -> 0 | I13: =I$48 -> 16.8 | J13: 0 | K13: 0 | L13: 0 | M13: 0 | N13: 0
A15: Days Inventory (DOH) | C15: Working Capital Drivers
A16: Days Receivable (DSO) | C16: DSO | D16: =IFERROR( INDEX('SLCA Raw'!$B$120:$K$163, MATCH($A16,'SLCA Raw'!$A$120:$A$163,0), MATCH(D$33,'SLCA Raw'!$B$116:$K$116,0) ),"") -> 0 | E16: =IFERROR( INDEX('SLCA Raw'!$B$120:$K$163, MATCH($A16,'SLCA Raw'!$A$120:$A$163,0), MATCH(E$33,'SLCA Raw'!$B$116:$K$116,0) ),"") -> 0 | F16: =IFERROR( INDEX('SLCA Raw'!$B$120:$K$163, MATCH($A16,'SLCA Raw'!$A$120:$A$163,0), MATCH(F$33,'SLCA Raw'!$B$116:$K$116,0) ),"") -> 0 | G16: =IFERROR( INDEX('SLCA Raw'!$B$120:$K$163, MATCH($A16,'SLCA Raw'!$A$120:$A$163,0), MATCH(G$33,'SLCA Raw'!$B$116:$K$116,0) ),"") -> 0 | H16: =IFERROR( INDEX('SLCA Raw'!$B$120:$K$163, MATCH($A16,'SLCA Raw'!$A$120:$A$163,0), MATCH(H$33,'SLCA Raw'!$B$116:$K$116,0) ),"") -> 0 | I16: =IFERROR( INDEX('SLCA Raw'!$B$120:$K$163, MATCH($A16,'SLCA Raw'!$A$120:$A$163,0), MATCH(I$33,'SLCA Raw'!$B$116:$K$116,0) ),"") -> 0 | J16: 49 | K16: =J16 -> 49 | L16: =K16 -> 49 | M16: =L16 -> 49 | N16: =M16 -> 49
A17: Days Inventory (DOH) | C17: DOH | D17: =IFERROR( INDEX('SLCA Raw'!$B$120:$K$163, MATCH($A17,'SLCA Raw'!$A$120:$A$163,0), MATCH(D$33,'SLCA Raw'!$B$116:$K$116,0) ),"") -> 51 | E17: =IFERROR( INDEX('SLCA Raw'!$B$120:$K$163, MATCH($A17,'SLCA Raw'!$A$120:$A$163,0), MATCH(E$33,'SLCA Raw'!$B$116:$K$116,0) ),"") -> 40 | F17: =IFERROR( INDEX('SLCA Raw'!$B$120:$K$163, MATCH($A17,'SLCA Raw'!$A$120:$A$163,0), MATCH(F$33,'SLCA Raw'!$B$116:$K$116,0) ),"") -> 68 | G17: =IFERROR( INDEX('SLCA Raw'!$B$120:$K$163, MATCH($A17,'SLCA Raw'!$A$120:$A$163,0), MATCH(G$33,'SLCA Raw'!$B$116:$K$116,0) ),"") -> 55 | H17: =IFERROR( INDEX('SLCA Raw'!$B$120:$K$163, MATCH($A17,'SLCA Raw'!$A$120:$A$163,0), MATCH(H$33,'SLCA Raw'!$B$116:$K$116,0) ),"") -> 52 | I17: =IFERROR( INDEX('SLCA Raw'!$B$120:$K$163, MATCH($A17,'SLCA Raw'!$A$120:$A$163,0), MATCH(I$33,'SLCA Raw'!$B$116:$K$116,0) ),"") -> 55 | J17: =AVERAGE(G$17:I$17) -> 54 | K17: =J17 -> 54 | L17: =K17 -> 54 | M17: =L17 -> 54 | N17: =M17 -> 54
A18: Days Payable (DP) | C18: DPO | D18: =IFERROR( INDEX('SLCA Raw'!$B$120:$K$163, MATCH($A18,'SLCA Raw'!$A$120:$A$163,0), MATCH(D$33,'SLCA Raw'!$B$116:$K$116,0) ),"") -> 56 | E18: =IFERROR( INDEX('SLCA Raw'!$B$120:$K$163, MATCH($A18,'SLCA Raw'!$A$120:$A$163,0), MATCH(E$33,'SLCA Raw'!$B$116:$K$116,0) ),"") -> 58 | F18: =IFERROR( INDEX('SLCA Raw'!$B$120:$K$163, MATCH($A18,'SLCA Raw'!$A$120:$A$163,0), MATCH(F$33,'SLCA Raw'!$B$116:$K$116,0) ),"") -> 59 | G18: =IFERROR( INDEX('SLCA Raw'!$B$120:$K$163, MATCH($A18,'SLCA Raw'!$A$120:$A$163,0), MATCH(G$33,'SLCA Raw'!$B$116:$K$116,0) ),"") -> 64 | H18: =IFERROR( INDEX('SLCA Raw'!$B$120:$K$163, MATCH($A18,'SLCA Raw'!$A$120:$A$163,0), MATCH(H$33,'SLCA Raw'!$B$116:$K$116,0) ),"") -> 65 | I18: =IFERROR( INDEX('SLCA Raw'!$B$120:$K$163, MATCH($A18,'SLCA Raw'!$A$120:$A$163,0), MATCH(I$33,'SLCA Raw'!$B$116:$K$116,0) ),"") -> 46 | J18: =AVERAGE(G$18:I$18) -> 58.333333 | K18: =J18 -> 58.333333 | L18: =K18 -> 58.333333 | M18: =L18 -> 58.333333 | N18: =M18 -> 58.333333
A19: Other Balance Sheet Drivers | C19: Prepaids % Revenue | D19: =D$67/D$35 -> 0.011411921 | E19: =E$67/E$35 -> 0.010986947 | F19: =F$67/F$35 -> 0.027308677 | G19: =G$67/G$35 -> 0.016306135 | H19: =H$67/H$35 -> 0.013244625 | I19: =I$67/I$35 -> 0.012693119 | J19: =AVERAGE(G$19:I$19) -> 0.014081293 | K19: =J19 -> 0.014081293 | L19: =K19 -> 0.014081293 | M19: =L19 -> 0.014081293 | N19: =M19 -> 0.014081293
A20: Prepaids % Revenue | C20: Other Current Assets % Revenue | D20: =D$68/D$35 -> 0 | E20: =E$68/E$35 -> 0 | F20: =F$68/F$35 -> 0 | G20: =G$68/G$35 -> 0 | H20: =H$68/H$35 -> 0 | I20: =I$68/I$35 -> 0 | J20: =I20 -> 0 | K20: =J20 -> 0 | L20: =K20 -> 0 | M20: =L20 -> 0 | N20: =M20 -> 0
A21: Other Current Assets % Revenue | C21: Accrued Expenses % Revenue | D21: =D$82/D$35 -> 0.023838235 | E21: =E$82/E$35 -> 0.06388706 | F21: =F$82/F$35 -> 0.052016527 | G21: =G$82/G$35 -> 0.043120668 | H21: =H$82/H$35 -> 0.033504967 | I21: =I$82/I$35 -> 0.026159423 | J21: =AVERAGE(G$21:I$21) -> 0.034261686 | K21: =J21 -> 0.034261686 | L21: =K21 -> 0.034261686 | M21: =L21 -> 0.034261686 | N21: =M21 -> 0.034261686
A22: Accrued Expenses % Revenue | C22: Other Current Liabilities % Revenue | D22: =D$85/D$35 -> 0.020034261 | E22: =E$85/E$35 -> 0.010240919 | F22: =F$85/F$35 -> 0.015959616 | G22: =G$85/G$35 -> 0.0048918405 | H22: =H$85/H$35 -> 0.012261113 | I22: =I$85/I$35 -> 0.0034149 | J22: =AVERAGE(G$22:I$22) -> 0.0068559512 | K22: =J22 -> 0.0068559512 | L22: =K22 -> 0.0068559512 | M22: =L22 -> 0.0068559512 | N22: =M22 -> 0.0068559512
A24: Other Current Liabilities % Revenue | C24: Other Balance Sheet Drivers
A25: Other Long-Term Assets % Revenue | C25: Other Long-Term Assets % Revenue | D25: =D$77/D$35 -> 0.01160212 | E25: =E$77/E$35 -> 0.010986947 | F25: =F$77/F$35 -> 0.011585499 | G25: =G$77/G$35 -> 0.0064318644 | H25: =H$77/H$35 -> 0.0062944752 | I25: =I$77/I$35 -> 0.0080540095 | J25: =AVERAGE($G$25:$I$25) -> 0.006926783 | K25: =J25 -> 0.006926783 | L25: =K25 -> 0.006926783 | M25: =L25 -> 0.006926783 | N25: =M25 -> 0.006926783
A26: Other Long-Term Liabilities % Revenue | C26: Other Long-Term Liabilities % Revenue | D26: =D$92/D$35 -> 0.12901811 | E26: =E$92/E$35 -> 0.16866998 | F26: =F$92/F$35 -> 0.21066693 | G26: =G$92/G$35 -> 0.14648345 | H26: =H$92/H$35 -> 0.089040597 | I26: =I$92/I$35 -> 0.084470452 | J26: =AVERAGE(G$26:I$26) -> 0.10666483 | K26: =J26 -> 0.10666483 | L26: =K26 -> 0.10666483 | M26: =L26 -> 0.10666483 | N26: =M26 -> 0.10666483
A28: Tax Rate | C28: Tax Rate | D28: =CHOOSE('Main Page & Assumptions'!D5,'Main Page & Assumptions'!E18,'Main Page & Assumptions'!J18,'Main Page & Assumptions'!O18) -> 0.265 | E28: =$D$28 -> 0.265 | F28: =$D$28 -> 0.265 | G28: =$D$28 -> 0.265 | H28: =$D$28 -> 0.265 | I28: =$D$28 -> 0.265 | J28: =$D$28 -> 0.265 | K28: =$D$28 -> 0.265 | L28: =$D$28 -> 0.265 | ... N28: =$D$28 -> 0.265
C31: Income Statement
J32: Forecast
C33: FYE December | D33: =$D$5 -> 43465 | E33: =EDATE(D33,12) -> 43830 | F33: =EDATE(E33,12) -> 44196 | G33: =EDATE(F33,12) -> 44561 | H33: =EDATE(G33,12) -> 44926 | I33: =EDATE(H33,12) -> 45291 | J33: =EDATE(I33,12) -> 45657 | K33: =EDATE(J33,12) -> 46022 | L33: =EDATE(K33,12) -> 46387 | ... N33: =EDATE(M33,12) -> 47118
D34: USD | E34: USD | F34: USD | G34: USD | H34: USD | I34: USD | J34: USD | K34: USD | L34: USD | M34: USD | N34: USD
A35: Total Revenue | C35: Revenue | D35: =IFERROR( INDEX('SLCA Raw'!$B$6:$K$33, MATCH(TRIM($A35),'SLCA Raw'!$M$6:$M$33,0), MATCH(D$33,'SLCA Raw'!$B$3:$K$3,0) ),"") -> 1577.298 | E35: =IFERROR( INDEX('SLCA Raw'!$B$6:$K$33, MATCH(TRIM($A35),'SLCA Raw'!$M$6:$M$33,0), MATCH(E$33,'SLCA Raw'!$B$3:$K$3,0) ),"") -> 1474.477 | F35: =IFERROR( INDEX('SLCA Raw'!$B$6:$K$33, MATCH(TRIM($A35),'SLCA Raw'!$M$6:$M$33,0), MATCH(F$33,'SLCA Raw'!$B$3:$K$3,0) ),"") -> 845.885 | G35: =IFERROR( INDEX('SLCA Raw'!$B$6:$K$33, MATCH(TRIM($A35),'SLCA Raw'!$M$6:$M$33,0), MATCH(G$33,'SLCA Raw'!$B$3:$K$3,0) ),"") -> 1103.879 | H35: =IFERROR( INDEX('SLCA Raw'!$B$6:$K$33, MATCH(TRIM($A35),'SLCA Raw'!$M$6:$M$33,0), MATCH(H$33,'SLCA Raw'!$B$3:$K$3,0) ),"") -> 1525.147 | I35: =IFERROR( INDEX('SLCA Raw'!$B$6:$K$33, MATCH(TRIM($A35),'SLCA Raw'!$M$6:$M$33,0), MATCH(I$33,'SLCA Raw'!$B$3:$K$3,0) ),"") -> 1552.022 | J35: ='Revenue Build'!I7/1000 -> 1604.6241 | K35: ='Revenue Build'!J7/1000 -> 1657.8189 | L35: ='Revenue Build'!K7/1000 -> 1710.958 | M35: ='Revenue Build'!L7/1000 -> 1767.8644 | N35: ='Revenue Build'!M7/1000 -> 1828.2977
A37: Cost of Revenue, Total | C37: Cost of Revenue | D37: =IFERROR( INDEX('SLCA Raw'!$B$6:$K$33, MATCH(TRIM($A37),'SLCA Raw'!$M$6:$M$33,0), MATCH(D$33,'SLCA Raw'!$B$3:$K$3,0) ),"") -> 1163.129 | E37: =IFERROR( INDEX('SLCA Raw'!$B$6:$K$33, MATCH(TRIM($A37),'SLCA Raw'!$M$6:$M$33,0), MATCH(E$33,'SLCA Raw'!$B$3:$K$3,0) ),"") -> 1133.293 | F37: =IFERROR( INDEX('SLCA Raw'!$B$6:$K$33, MATCH(TRIM($A37),'SLCA Raw'!$M$6:$M$33,0), MATCH(F$33,'SLCA Raw'!$B$3:$K$3,0) ),"") -> 548.522 | G37: =IFERROR( INDEX('SLCA Raw'!$B$6:$K$33, MATCH(TRIM($A37),'SLCA Raw'!$M$6:$M$33,0), MATCH(G$33,'SLCA Raw'!$B$3:$K$3,0) ),"") -> 761.798 | H37: =IFERROR( INDEX('SLCA Raw'!$B$6:$K$33, MATCH(TRIM($A37),'SLCA Raw'!$M$6:$M$33,0), MATCH(H$33,'SLCA Raw'!$B$3:$K$3,0) ),"") -> 1031.613 | I37: =IFERROR( INDEX('SLCA Raw'!$B$6:$K$33, MATCH(TRIM($A37),'SLCA Raw'!$M$6:$M$33,0), MATCH(I$33,'SLCA Raw'!$B$3:$K$3,0) ),"") -> 982.979 | J37: =J35*(1-J$9) -> 1069.6778 | K37: =K35*(1-K$9) -> 1092.159 | L37: =L35*(1-L$9) -> 1117.1236 | M37: =M35*(1-M$9) -> 1165.8109 | N37: =N35*(1-N$9) -> 1201.29
A38: Gross Profit | C38: Gross Profit | D38: =IFERROR( INDEX('SLCA Raw'!$B$6:$K$33, MATCH(TRIM($A38),'SLCA Raw'!$M$6:$M$33,0), MATCH(D$33,'SLCA Raw'!$B$3:$K$3,0) ),"") -> 414.169 | E38: =IFERROR( INDEX('SLCA Raw'!$B$6:$K$33, MATCH(TRIM($A38),'SLCA Raw'!$M$6:$M$33,0), MATCH(E$33,'SLCA Raw'!$B$3:$K$3,0) ),"") -> 341.184 | F38: =IFERROR( INDEX('SLCA Raw'!$B$6:$K$33, MATCH(TRIM($A38),'SLCA Raw'!$M$6:$M$33,0), MATCH(F$33,'SLCA Raw'!$B$3:$K$3,0) ),"") -> 297.363 | G38: =IFERROR( INDEX('SLCA Raw'!$B$6:$K$33, MATCH(TRIM($A38),'SLCA Raw'!$M$6:$M$33,0), MATCH(G$33,'SLCA Raw'!$B$3:$K$3,0) ),"") -> 342.081 | H38: =IFERROR( INDEX('SLCA Raw'!$B$6:$K$33, MATCH(TRIM($A38),'SLCA Raw'!$M$6:$M$33,0), MATCH(H$33,'SLCA Raw'!$B$3:$K$3,0) ),"") -> 493.534 | I38: =IFERROR( INDEX('SLCA Raw'!$B$6:$K$33, MATCH(TRIM($A38),'SLCA Raw'!$M$6:$M$33,0), MATCH(I$33,'SLCA Raw'!$B$3:$K$3,0) ),"") -> 569.043 | J38: =J$35-J$37 -> 534.94628 | K38: =K$35-K$37 -> 565.65985 | L38: =L$35-L$37 -> 593.8344 | M38: =M$35-M$37 -> 602.05351 | N38: =N$35-N$37 -> 627.0077
A39: Selling/General/Admin. Expenses, Total | C39: SG&A | D39: =IFERROR( INDEX('SLCA Raw'!$B$6:$K$33, MATCH(TRIM($A39),'SLCA Raw'!$M$6:$M$33,0), MATCH(D$33,'SLCA Raw'!$B$3:$K$3,0) ),"") -> 146.971 | E39: =IFERROR( INDEX('SLCA Raw'!$B$6:$K$33, MATCH(TRIM($A39),'SLCA Raw'!$M$6:$M$33,0), MATCH(E$33,'SLCA Raw'!$B$3:$K$3,0) ),"") -> 150.848 | F39: =IFERROR( INDEX('SLCA Raw'!$B$6:$K$33, MATCH(TRIM($A39),'SLCA Raw'!$M$6:$M$33,0), MATCH(F$33,'SLCA Raw'!$B$3:$K$3,0) ),"") -> 150.719 | G39: =IFERROR( INDEX('SLCA Raw'!$B$6:$K$33, MATCH(TRIM($A39),'SLCA Raw'!$M$6:$M$33,0), MATCH(G$33,'SLCA Raw'!$B$3:$K$3,0) ),"") -> 152.813 | H39: =IFERROR( INDEX('SLCA Raw'!$B$6:$K$33, MATCH(TRIM($A39),'SLCA Raw'!$M$6:$M$33,0), MATCH(H$33,'SLCA Raw'!$B$3:$K$3,0) ),"") -> 182.414 | I39: =IFERROR( INDEX('SLCA Raw'!$B$6:$K$33, MATCH(TRIM($A39),'SLCA Raw'!$M$6:$M$33,0), MATCH(I$33,'SLCA Raw'!$B$3:$K$3,0) ),"") -> 156.445 | J39: =J$35*J$10 -> 191.93321 | K39: =K$35*K$10 -> 198.29598 | L39: =L$35*L$10 -> 204.65208 | M39: =M$35*M$10 -> 211.45881 | N39: =N$35*N$10 -> 218.68739
A40: Research & Development | C40: R&D | D40: =IFERROR( INDEX('SLCA Raw'!$B$6:$K$33, MATCH(TRIM($A40),'SLCA Raw'!$M$6:$M$33,0), MATCH(D$33,'SLCA Raw'!$B$3:$K$3,0) ),"") -> 0 | E40: =IFERROR( INDEX('SLCA Raw'!$B$6:$K$33, MATCH(TRIM($A40),'SLCA Raw'!$M$6:$M$33,0), MATCH(E$33,'SLCA Raw'!$B$3:$K$3,0) ),"") -> 0 | F40: =IFERROR( INDEX('SLCA Raw'!$B$6:$K$33, MATCH(TRIM($A40),'SLCA Raw'!$M$6:$M$33,0), MATCH(F$33,'SLCA Raw'!$B$3:$K$3,0) ),"") -> 0 | G40: =IFERROR( INDEX('SLCA Raw'!$B$6:$K$33, MATCH(TRIM($A40),'SLCA Raw'!$M$6:$M$33,0), MATCH(G$33,'SLCA Raw'!$B$3:$K$3,0) ),"") -> 0 | H40: =IFERROR( INDEX('SLCA Raw'!$B$6:$K$33, MATCH(TRIM($A40),'SLCA Raw'!$M$6:$M$33,0), MATCH(H$33,'SLCA Raw'!$B$3:$K$3,0) ),"") -> 0 | I40: =IFERROR( INDEX('SLCA Raw'!$B$6:$K$33, MATCH(TRIM($A40),'SLCA Raw'!$M$6:$M$33,0), MATCH(I$33,'SLCA Raw'!$B$3:$K$3,0) ),"") -> 0 | J40: =J$35*J$11 -> 0 | K40: =K$35*K$11 -> 0 | L40: =L$35*L$11 -> 0 | M40: =M$35*M$11 -> 0 | N40: =N$35*N$11 -> 0
A41: Depreciation/Amortization | C41: D&A | D41: =IFERROR( INDEX('SLCA Raw'!$B$6:$K$33, MATCH(TRIM($A41),'SLCA Raw'!$M$6:$M$33,0), MATCH(D$33,'SLCA Raw'!$B$3:$K$3,0) ),"") -> 148.8 | E41: =IFERROR( INDEX('SLCA Raw'!$B$6:$K$33, MATCH(TRIM($A41),'SLCA Raw'!$M$6:$M$33,0), MATCH(E$33,'SLCA Raw'!$B$3:$K$3,0) ),"") -> 179.4 | F41: =IFERROR( INDEX('SLCA Raw'!$B$6:$K$33, MATCH(TRIM($A41),'SLCA Raw'!$M$6:$M$33,0), MATCH(F$33,'SLCA Raw'!$B$3:$K$3,0) ),"") -> 155.6 | G41: =IFERROR( INDEX('SLCA Raw'!$B$6:$K$33, MATCH(TRIM($A41),'SLCA Raw'!$M$6:$M$33,0), MATCH(G$33,'SLCA Raw'!$B$3:$K$3,0) ),"") -> 161.1 | H41: =IFERROR( INDEX('SLCA Raw'!$B$6:$K$33, MATCH(TRIM($A41),'SLCA Raw'!$M$6:$M$33,0), MATCH(H$33,'SLCA Raw'!$B$3:$K$3,0) ),"") -> 140.2 | I41: =IFERROR( INDEX('SLCA Raw'!$B$6:$K$33, MATCH(TRIM($A41),'SLCA Raw'!$M$6:$M$33,0), MATCH(I$33,'SLCA Raw'!$B$3:$K$3,0) ),"") -> 137.3 | J41: =SUM('Individual Cash Flow'!I13+'Individual Cash Flow'!I39) -> 146.23333 | K41: =SUM('Individual Cash Flow'!J13+'Individual Cash Flow'!J39) -> 146.23333 | L41: =SUM('Individual Cash Flow'!K13+'Individual Cash Flow'!K39) -> 146.23333 | M41: =SUM('Individual Cash Flow'!L13+'Individual Cash Flow'!L39) -> 146.23333 | N41: =SUM('Individual Cash Flow'!M13+'Individual Cash Flow'!M39) -> 146.23333
A42: Unusual Expense (Income) | C42: Unusual Expense (Income) | D42: =IFERROR( INDEX('SLCA Raw'!$B$6:$K$33, MATCH(TRIM($A42),'SLCA Raw'!$M$6:$M$33,0), MATCH(D$33,'SLCA Raw'!$B$3:$K$3,0) ),"") -> 281.9 | E42: =IFERROR( INDEX('SLCA Raw'!$B$6:$K$33, MATCH(TRIM($A42),'SLCA Raw'!$M$6:$M$33,0), MATCH(E$33,'SLCA Raw'!$B$3:$K$3,0) ),"") -> 363.8 | F42: =IFERROR( INDEX('SLCA Raw'!$B$6:$K$33, MATCH(TRIM($A42),'SLCA Raw'!$M$6:$M$33,0), MATCH(F$33,'SLCA Raw'!$B$3:$K$3,0) ),"") -> 110.7 | G42: =IFERROR( INDEX('SLCA Raw'!$B$6:$K$33, MATCH(TRIM($A42),'SLCA Raw'!$M$6:$M$33,0), MATCH(G$33,'SLCA Raw'!$B$3:$K$3,0) ),"") -> 0.2 | H42: =IFERROR( INDEX('SLCA Raw'!$B$6:$K$33, MATCH(TRIM($A42),'SLCA Raw'!$M$6:$M$33,0), MATCH(H$33,'SLCA Raw'!$B$3:$K$3,0) ),"") -> 0 | I42: =IFERROR( INDEX('SLCA Raw'!$B$6:$K$33, MATCH(TRIM($A42),'SLCA Raw'!$M$6:$M$33,0), MATCH(I$33,'SLCA Raw'!$B$3:$K$3,0) ),"") -> 8.5 | J42: 0 | K42: 0 | L42: 0 | M42: 0 | N42: 0
A43: Other Operating Expenses, Total | C43: Other Operating Expenses | D43: =IFERROR( INDEX('SLCA Raw'!$B$6:$K$33, MATCH(TRIM($A43),'SLCA Raw'!$M$6:$M$33,0), MATCH(D$33,'SLCA Raw'!$B$3:$K$3,0) ),"") -> 0 | E43: =IFERROR( INDEX('SLCA Raw'!$B$6:$K$33, MATCH(TRIM($A43),'SLCA Raw'!$M$6:$M$33,0), MATCH(E$33,'SLCA Raw'!$B$3:$K$3,0) ),"") -> 0 | F43: =IFERROR( INDEX('SLCA Raw'!$B$6:$K$33, MATCH(TRIM($A43),'SLCA Raw'!$M$6:$M$33,0), MATCH(F$33,'SLCA Raw'!$B$3:$K$3,0) ),"") -> 0 | G43: =IFERROR( INDEX('SLCA Raw'!$B$6:$K$33, MATCH(TRIM($A43),'SLCA Raw'!$M$6:$M$33,0), MATCH(G$33,'SLCA Raw'!$B$3:$K$3,0) ),"") -> 0 | H43: =IFERROR( INDEX('SLCA Raw'!$B$6:$K$33, MATCH(TRIM($A43),'SLCA Raw'!$M$6:$M$33,0), MATCH(H$33,'SLCA Raw'!$B$3:$K$3,0) ),"") -> 0 | I43: =IFERROR( INDEX('SLCA Raw'!$B$6:$K$33, MATCH(TRIM($A43),'SLCA Raw'!$M$6:$M$33,0), MATCH(I$33,'SLCA Raw'!$B$3:$K$3,0) ),"") -> 0 | J43: =J$12*J$35 -> 0 | K43: =K$12*K$35 -> 0 | L43: =L$12*L$35 -> 0 | M43: =M$12*M$35 -> 0 | N43: =N$12*N$35 -> 0
A44: Total Operating Expense | C44: Total Operating Costs & Expenses | D44: =IFERROR( INDEX('SLCA Raw'!$B$6:$K$33, MATCH(TRIM($A44),'SLCA Raw'!$M$6:$M$33,0), MATCH(D$33,'SLCA Raw'!$B$3:$K$3,0) ),"") -> 1740.8 | E44: =IFERROR( INDEX('SLCA Raw'!$B$6:$K$33, MATCH(TRIM($A44),'SLCA Raw'!$M$6:$M$33,0), MATCH(E$33,'SLCA Raw'!$B$3:$K$3,0) ),"") -> 1827.4 | F44: =IFERROR( INDEX('SLCA Raw'!$B$6:$K$33, MATCH(TRIM($A44),'SLCA Raw'!$M$6:$M$33,0), MATCH(F$33,'SLCA Raw'!$B$3:$K$3,0) ),"") -> 965.5 | G44: =IFERROR( INDEX('SLCA Raw'!$B$6:$K$33, MATCH(TRIM($A44),'SLCA Raw'!$M$6:$M$33,0), MATCH(G$33,'SLCA Raw'!$B$3:$K$3,0) ),"") -> 1075.9 | H44: =IFERROR( INDEX('SLCA Raw'!$B$6:$K$33, MATCH(TRIM($A44),'SLCA Raw'!$M$6:$M$33,0), MATCH(H$33,'SLCA Raw'!$B$3:$K$3,0) ),"") -> 1354.2 | I44: =IFERROR( INDEX('SLCA Raw'!$B$6:$K$33, MATCH(TRIM($A44),'SLCA Raw'!$M$6:$M$33,0), MATCH(I$33,'SLCA Raw'!$B$3:$K$3,0) ),"") -> 1285.2 | J44: =SUM(J$39:J$43)+J37 -> 1407.8444 | K44: =SUM(K$39:K$43)+K37 -> 1436.6883 | L44: =SUM(L$39:L$43)+L37 -> 1468.009 | M44: =SUM(M$39:M$43)+M37 -> 1523.5031 | N44: =SUM(N$39:N$43)+N37 -> 1566.2107
A45: Operating Income | C45: Operating Income | D45: =IFERROR( INDEX('SLCA Raw'!$B$6:$K$33, MATCH(TRIM($A45),'SLCA Raw'!$M$6:$M$33,0), MATCH(D$33,'SLCA Raw'!$B$3:$K$3,0) ),"") -> -163.533 | E45: =IFERROR( INDEX('SLCA Raw'!$B$6:$K$33, MATCH(TRIM($A45),'SLCA Raw'!$M$6:$M$33,0), MATCH(E$33,'SLCA Raw'!$B$3:$K$3,0) ),"") -> -352.955 | F45: =IFERROR( INDEX('SLCA Raw'!$B$6:$K$33, MATCH(TRIM($A45),'SLCA Raw'!$M$6:$M$33,0), MATCH(F$33,'SLCA Raw'!$B$3:$K$3,0) ),"") -> -119.612 | G45: =IFERROR( INDEX('SLCA Raw'!$B$6:$K$33, MATCH(TRIM($A45),'SLCA Raw'!$M$6:$M$33,0), MATCH(G$33,'SLCA Raw'!$B$3:$K$3,0) ),"") -> 27.935 | H45: =IFERROR( INDEX('SLCA Raw'!$B$6:$K$33, MATCH(TRIM($A45),'SLCA Raw'!$M$6:$M$33,0), MATCH(H$33,'SLCA Raw'!$B$3:$K$3,0) ),"") -> 170.954 | I45: =IFERROR( INDEX('SLCA Raw'!$B$6:$K$33, MATCH(TRIM($A45),'SLCA Raw'!$M$6:$M$33,0), MATCH(I$33,'SLCA Raw'!$B$3:$K$3,0) ),"") -> 266.839 | J45: =J$35-J$44 -> 196.77973 | K45: =K$35-K$44 -> 221.13054 | L45: =L$35-L$44 -> 242.94899 | M45: =M$35-M$44 -> 244.36137 | N45: =N$35-N$44 -> 262.08698
A47: Interest Inc.(Exp.),Net-Non-Op., Total | C47: Interest Expense, Net | D47: =IFERROR( INDEX('SLCA Raw'!$B$6:$K$33, MATCH(TRIM($A47),'SLCA Raw'!$M$6:$M$33,0), MATCH(D$33,'SLCA Raw'!$B$3:$K$3,0) ),"") -> -70.6 | E47: =IFERROR( INDEX('SLCA Raw'!$B$6:$K$33, MATCH(TRIM($A47),'SLCA Raw'!$M$6:$M$33,0), MATCH(E$33,'SLCA Raw'!$B$3:$K$3,0) ),"") -> -95.5 | F47: =IFERROR( INDEX('SLCA Raw'!$B$6:$K$33, MATCH(TRIM($A47),'SLCA Raw'!$M$6:$M$33,0), MATCH(F$33,'SLCA Raw'!$B$3:$K$3,0) ),"") -> -79.9 | G47: =IFERROR( INDEX('SLCA Raw'!$B$6:$K$33, MATCH(TRIM($A47),'SLCA Raw'!$M$6:$M$33,0), MATCH(G$33,'SLCA Raw'!$B$3:$K$3,0) ),"") -> -71.2 | H47: =IFERROR( INDEX('SLCA Raw'!$B$6:$K$33, MATCH(TRIM($A47),'SLCA Raw'!$M$6:$M$33,0), MATCH(H$33,'SLCA Raw'!$B$3:$K$3,0) ),"") -> -77.6 | I47: =IFERROR( INDEX('SLCA Raw'!$B$6:$K$33, MATCH(TRIM($A47),'SLCA Raw'!$M$6:$M$33,0), MATCH(I$33,'SLCA Raw'!$B$3:$K$3,0) ),"") -> -101.7
A48: Gain (Loss) on Sale of Assets | C48: Gain (Loss) on Asset Sales | D48: =IFERROR( INDEX('SLCA Raw'!$B$6:$K$33, MATCH(TRIM($A48),'SLCA Raw'!$M$6:$M$33,0), MATCH(D$33,'SLCA Raw'!$B$3:$K$3,0) ),"") -> 0 | E48: =IFERROR( INDEX('SLCA Raw'!$B$6:$K$33, MATCH(TRIM($A48),'SLCA Raw'!$M$6:$M$33,0), MATCH(E$33,'SLCA Raw'!$B$3:$K$3,0) ),"") -> 0 | F48: =IFERROR( INDEX('SLCA Raw'!$B$6:$K$33, MATCH(TRIM($A48),'SLCA Raw'!$M$6:$M$33,0), MATCH(F$33,'SLCA Raw'!$B$3:$K$3,0) ),"") -> 0.3 | G48: =IFERROR( INDEX('SLCA Raw'!$B$6:$K$33, MATCH(TRIM($A48),'SLCA Raw'!$M$6:$M$33,0), MATCH(G$33,'SLCA Raw'!$B$3:$K$3,0) ),"") -> 0 | H48: =IFERROR( INDEX('SLCA Raw'!$B$6:$K$33, MATCH(TRIM($A48),'SLCA Raw'!$M$6:$M$33,0), MATCH(H$33,'SLCA Raw'!$B$3:$K$3,0) ),"") -> 0 | I48: =IFERROR( INDEX('SLCA Raw'!$B$6:$K$33, MATCH(TRIM($A48),'SLCA Raw'!$M$6:$M$33,0), MATCH(I$33,'SLCA Raw'!$B$3:$K$3,0) ),"") -> 16.8 | J48: =J13 -> 0 | K48: =K13 -> 0 | L48: =L13 -> 0 | M48: =M13 -> 0 | N48: =N13 -> 0
A49: Other, Net | C49: Other Non-Operating Income (Expense) | D49: =IFERROR( INDEX('SLCA Raw'!$B$6:$K$33, MATCH(TRIM($A49),'SLCA Raw'!$M$6:$M$33,0), MATCH(D$33,'SLCA Raw'!$B$3:$K$3,0) ),"") -> 4.1 | E49: =IFERROR( INDEX('SLCA Raw'!$B$6:$K$33, MATCH(TRIM($A49),'SLCA Raw'!$M$6:$M$33,0), MATCH(E$33,'SLCA Raw'!$B$3:$K$3,0) ),"") -> 19.5 | F49: =IFERROR( INDEX('SLCA Raw'!$B$6:$K$33, MATCH(TRIM($A49),'SLCA Raw'!$M$6:$M$33,0), MATCH(F$33,'SLCA Raw'!$B$3:$K$3,0) ),"") -> 24 | G49: =IFERROR( INDEX('SLCA Raw'!$B$6:$K$33, MATCH(TRIM($A49),'SLCA Raw'!$M$6:$M$33,0), MATCH(G$33,'SLCA Raw'!$B$3:$K$3,0) ),"") -> 6.1 | H49: =IFERROR( INDEX('SLCA Raw'!$B$6:$K$33, MATCH(TRIM($A49),'SLCA Raw'!$M$6:$M$33,0), MATCH(H$33,'SLCA Raw'!$B$3:$K$3,0) ),"") -> 10.6 | I49: =IFERROR( INDEX('SLCA Raw'!$B$6:$K$33, MATCH(TRIM($A49),'SLCA Raw'!$M$6:$M$33,0), MATCH(I$33,'SLCA Raw'!$B$3:$K$3,0) ),"") -> 13.6 | J49: =AVERAGE($I$49:$I$49) -> 13.6 | K49: =AVERAGE($I$49:$I$49) -> 13.6 | L49: =AVERAGE($I$49:$I$49) -> 13.6 | M49: =AVERAGE($I$49:$I$49) -> 13.6 | N49: =AVERAGE($I$49:$I$49) -> 13.6
A50: Net Income Before Taxes | C50: Pre-Tax Income | D50: =IFERROR( INDEX('SLCA Raw'!$B$6:$K$33, MATCH(TRIM($A50),'SLCA Raw'!$M$6:$M$33,0), MATCH(D$33,'SLCA Raw'!$B$3:$K$3,0) ),"") -> -229.953 | E50: =IFERROR( INDEX('SLCA Raw'!$B$6:$K$33, MATCH(TRIM($A50),'SLCA Raw'!$M$6:$M$33,0), MATCH(E$33,'SLCA Raw'!$B$3:$K$3,0) ),"") -> -428.908 | F50: =IFERROR( INDEX('SLCA Raw'!$B$6:$K$33, MATCH(TRIM($A50),'SLCA Raw'!$M$6:$M$33,0), MATCH(F$33,'SLCA Raw'!$B$3:$K$3,0) ),"") -> -175.147 | G50: =IFERROR( INDEX('SLCA Raw'!$B$6:$K$33, MATCH(TRIM($A50),'SLCA Raw'!$M$6:$M$33,0), MATCH(G$33,'SLCA Raw'!$B$3:$K$3,0) ),"") -> -37.076 | H50: =IFERROR( INDEX('SLCA Raw'!$B$6:$K$33, MATCH(TRIM($A50),'SLCA Raw'!$M$6:$M$33,0), MATCH(H$33,'SLCA Raw'!$B$3:$K$3,0) ),"") -> 103.999 | I50: =IFERROR( INDEX('SLCA Raw'!$B$6:$K$33, MATCH(TRIM($A50),'SLCA Raw'!$M$6:$M$33,0), MATCH(I$33,'SLCA Raw'!$B$3:$K$3,0) ),"") -> 195.569 | J50: =J$45+J$47+J$48+J$49 -> 210.37973 | K50: =K$45+K$47+K$48+K$49 -> 234.73054 | L50: =L$45+L$47+L$48+L$49 -> 256.54899 | M50: =M$45+M$47+M$48+M$49 -> 257.96137 | N50: =N$45+N$47+N$48+N$49 -> 275.68698
A51: Provision for Income Taxes | C51: Income Taxes | D51: =IFERROR( INDEX('SLCA Raw'!$B$6:$K$33, MATCH(TRIM($A51),'SLCA Raw'!$M$6:$M$33,0), MATCH(D$33,'SLCA Raw'!$B$3:$K$3,0) ),"") -> -29.132 | E51: =IFERROR( INDEX('SLCA Raw'!$B$6:$K$33, MATCH(TRIM($A51),'SLCA Raw'!$M$6:$M$33,0), MATCH(E$33,'SLCA Raw'!$B$3:$K$3,0) ),"") -> -99.151 | F51: =IFERROR( INDEX('SLCA Raw'!$B$6:$K$33, MATCH(TRIM($A51),'SLCA Raw'!$M$6:$M$33,0), MATCH(F$33,'SLCA Raw'!$B$3:$K$3,0) ),"") -> -37.707 | G51: =IFERROR( INDEX('SLCA Raw'!$B$6:$K$33, MATCH(TRIM($A51),'SLCA Raw'!$M$6:$M$33,0), MATCH(G$33,'SLCA Raw'!$B$3:$K$3,0) ),"") -> -2.755 | H51: =IFERROR( INDEX('SLCA Raw'!$B$6:$K$33, MATCH(TRIM($A51),'SLCA Raw'!$M$6:$M$33,0), MATCH(H$33,'SLCA Raw'!$B$3:$K$3,0) ),"") -> 26.159 | I51: =IFERROR( INDEX('SLCA Raw'!$B$6:$K$33, MATCH(TRIM($A51),'SLCA Raw'!$M$6:$M$33,0), MATCH(I$33,'SLCA Raw'!$B$3:$K$3,0) ),"") -> 49.08 | J51: =J$50*J$28 -> 55.750628 | K51: =K$50*K$28 -> 62.203594 | L51: =L$50*L$28 -> 67.985482 | M51: =M$50*M$28 -> 68.359763 | N51: =N$50*N$28 -> 73.057051
A52: Net Income | C52: Net Income | D52: =IFERROR( INDEX('SLCA Raw'!$B$6:$K$33, MATCH(TRIM($A52),'SLCA Raw'!$M$6:$M$33,0), MATCH(D$33,'SLCA Raw'!$B$3:$K$3,0) ),"") -> -200.808 | E52: =IFERROR( INDEX('SLCA Raw'!$B$6:$K$33, MATCH(TRIM($A52),'SLCA Raw'!$M$6:$M$33,0), MATCH(E$33,'SLCA Raw'!$B$3:$K$3,0) ),"") -> -329.082 | F52: =IFERROR( INDEX('SLCA Raw'!$B$6:$K$33, MATCH(TRIM($A52),'SLCA Raw'!$M$6:$M$33,0), MATCH(F$33,'SLCA Raw'!$B$3:$K$3,0) ),"") -> -114.094 | G52: =IFERROR( INDEX('SLCA Raw'!$B$6:$K$33, MATCH(TRIM($A52),'SLCA Raw'!$M$6:$M$33,0), MATCH(G$33,'SLCA Raw'!$B$3:$K$3,0) ),"") -> -33.761 | H52: =IFERROR( INDEX('SLCA Raw'!$B$6:$K$33, MATCH(TRIM($A52),'SLCA Raw'!$M$6:$M$33,0), MATCH(H$33,'SLCA Raw'!$B$3:$K$3,0) ),"") -> 78.176 | I52: =IFERROR( INDEX('SLCA Raw'!$B$6:$K$33, MATCH(TRIM($A52),'SLCA Raw'!$M$6:$M$33,0), MATCH(I$33,'SLCA Raw'!$B$3:$K$3,0) ),"") -> 146.925 | J52: =J50-J51 -> 154.6291 | K52: =K50-K51 -> 172.52695 | L52: =L50-L51 -> 188.56351 | M52: =M50-M51 -> 189.60161 | N52: =N50-N51 -> 202.62993
C53: Net Income Attributable to NCI | D53: =D$52-D$113 -> 0.013 | E53: =E$52-E$113 -> 0.675 | F53: =F$52-F$113 -> 1.028 | G53: =G$52-G$113 -> 0.56 | H53: =H$52-H$113 -> 0.336 | I53: =I$52-I$113 -> 0.436 | J53: 0 | K53: =$J$53 -> 0 | L53: =$J$53 -> 0 | M53: =$J$53 -> 0 | N53: =$J$53 -> 0
A55: Basic Weighted Average Shares | C55: Basic Weighted Average Shares | D55: =IFERROR( INDEX('SLCA Raw'!$B$6:$K$33, MATCH(TRIM($A55),'SLCA Raw'!$M$6:$M$33,0), MATCH(D$33,'SLCA Raw'!$B$3:$K$3,0) ),"") -> 76 | E55: =IFERROR( INDEX('SLCA Raw'!$B$6:$K$33, MATCH(TRIM($A55),'SLCA Raw'!$M$6:$M$33,0), MATCH(E$33,'SLCA Raw'!$B$3:$K$3,0) ),"") -> 73 | F55: =IFERROR( INDEX('SLCA Raw'!$B$6:$K$33, MATCH(TRIM($A55),'SLCA Raw'!$M$6:$M$33,0), MATCH(F$33,'SLCA Raw'!$B$3:$K$3,0) ),"") -> 74 | G55: =IFERROR( INDEX('SLCA Raw'!$B$6:$K$33, MATCH(TRIM($A55),'SLCA Raw'!$M$6:$M$33,0), MATCH(G$33,'SLCA Raw'!$B$3:$K$3,0) ),"") -> 74 | H55: =IFERROR( INDEX('SLCA Raw'!$B$6:$K$33, MATCH(TRIM($A55),'SLCA Raw'!$M$6:$M$33,0), MATCH(H$33,'SLCA Raw'!$B$3:$K$3,0) ),"") -> 76 | I55: =IFERROR( INDEX('SLCA Raw'!$B$6:$K$33, MATCH(TRIM($A55),'SLCA Raw'!$M$6:$M$33,0), MATCH(I$33,'SLCA Raw'!$B$3:$K$3,0) ),"") -> 77 | J55: ='[2]Olin Equity Schedule'!M$19 -> 114 | K55: ='[2]Olin Equity Schedule'!N$19 -> 114 | L55: ='[2]Olin Equity Schedule'!O$19 -> 114 | M55: ='[2]Olin Equity Schedule'!P$19 -> 114 | N55: ='[2]Olin Equity Schedule'!Q$19 -> 114
A56: Diluted Weighted Average Shares | C56: Diluted Shares | D56: =IFERROR( INDEX('SLCA Raw'!$B$6:$K$33, MATCH(TRIM($A56),'SLCA Raw'!$M$6:$M$33,0), MATCH(D$33,'SLCA Raw'!$B$3:$K$3,0) ),"") -> 76 | E56: =IFERROR( INDEX('SLCA Raw'!$B$6:$K$33, MATCH(TRIM($A56),'SLCA Raw'!$M$6:$M$33,0), MATCH(E$33,'SLCA Raw'!$B$3:$K$3,0) ),"") -> 73 | F56: =IFERROR( INDEX('SLCA Raw'!$B$6:$K$33, MATCH(TRIM($A56),'SLCA Raw'!$M$6:$M$33,0), MATCH(F$33,'SLCA Raw'!$B$3:$K$3,0) ),"") -> 74 | G56: =IFERROR( INDEX('SLCA Raw'!$B$6:$K$33, MATCH(TRIM($A56),'SLCA Raw'!$M$6:$M$33,0), MATCH(G$33,'SLCA Raw'!$B$3:$K$3,0) ),"") -> 74 | H56: =IFERROR( INDEX('SLCA Raw'!$B$6:$K$33, MATCH(TRIM($A56),'SLCA Raw'!$M$6:$M$33,0), MATCH(H$33,'SLCA Raw'!$B$3:$K$3,0) ),"") -> 78 | I56: =IFERROR( INDEX('SLCA Raw'!$B$6:$K$33, MATCH(TRIM($A56),'SLCA Raw'!$M$6:$M$33,0), MATCH(I$33,'SLCA Raw'!$B$3:$K$3,0) ),"") -> 79 | J56: =$I$56 -> 79 | K56: =$I$56 -> 79 | L56: =$I$56 -> 79 | M56: =$I$56 -> 79 | N56: =$I$56 -> 79
A57: Diluted EPS Excluding ExtraOrd Items | C57: Diluted EPS | D57: =IFERROR( INDEX('SLCA Raw'!$B$6:$K$33, MATCH(TRIM($A57),'SLCA Raw'!$M$6:$M$33,0), MATCH(D$33,'SLCA Raw'!$B$3:$K$3,0) ),"") -> -2.63 | E57: =IFERROR( INDEX('SLCA Raw'!$B$6:$K$33, MATCH(TRIM($A57),'SLCA Raw'!$M$6:$M$33,0), MATCH(E$33,'SLCA Raw'!$B$3:$K$3,0) ),"") -> -4.49 | F57: =IFERROR( INDEX('SLCA Raw'!$B$6:$K$33, MATCH(TRIM($A57),'SLCA Raw'!$M$6:$M$33,0), MATCH(F$33,'SLCA Raw'!$B$3:$K$3,0) ),"") -> -1.85 | G57: =IFERROR( INDEX('SLCA Raw'!$B$6:$K$33, MATCH(TRIM($A57),'SLCA Raw'!$M$6:$M$33,0), MATCH(G$33,'SLCA Raw'!$B$3:$K$3,0) ),"") -> -0.45 | H57: =IFERROR( INDEX('SLCA Raw'!$B$6:$K$33, MATCH(TRIM($A57),'SLCA Raw'!$M$6:$M$33,0), MATCH(H$33,'SLCA Raw'!$B$3:$K$3,0) ),"") -> 1.01 | I57: =IFERROR( INDEX('SLCA Raw'!$B$6:$K$33, MATCH(TRIM($A57),'SLCA Raw'!$M$6:$M$33,0), MATCH(I$33,'SLCA Raw'!$B$3:$K$3,0) ),"") -> 1.87 | J57: =J52/J56 -> 1.9573304 | K57: =K52/K56 -> 2.1838854 | L57: =L52/L56 -> 2.3868798 | M57: =M52/M56 -> 2.4000203 | N57: =N52/N56 -> 2.5649359
A58: Dividends Per Share | C58: Dividends Per Share | D58: =IFERROR( INDEX('SLCA Raw'!$B$6:$K$33, MATCH(TRIM($A58),'SLCA Raw'!$M$6:$M$33,0), MATCH(D$33,'SLCA Raw'!$B$3:$K$3,0) ),"") -> 0.25 | E58: =IFERROR( INDEX('SLCA Raw'!$B$6:$K$33, MATCH(TRIM($A58),'SLCA Raw'!$M$6:$M$33,0), MATCH(E$33,'SLCA Raw'!$B$3:$K$3,0) ),"") -> 0.25 | F58: =IFERROR( INDEX('SLCA Raw'!$B$6:$K$33, MATCH(TRIM($A58),'SLCA Raw'!$M$6:$M$33,0), MATCH(F$33,'SLCA Raw'!$B$3:$K$3,0) ),"") -> 0 | G58: =IFERROR( INDEX('SLCA Raw'!$B$6:$K$33, MATCH(TRIM($A58),'SLCA Raw'!$M$6:$M$33,0), MATCH(G$33,'SLCA Raw'!$B$3:$K$3,0) ),"") -> 0 | H58: =IFERROR( INDEX('SLCA Raw'!$B$6:$K$33, MATCH(TRIM($A58),'SLCA Raw'!$M$6:$M$33,0), MATCH(H$33,'SLCA Raw'!$B$3:$K$3,0) ),"") -> 0 | I58: =IFERROR( INDEX('SLCA Raw'!$B$6:$K$33, MATCH(TRIM($A58),'SLCA Raw'!$M$6:$M$33,0), MATCH(I$33,'SLCA Raw'!$B$3:$K$3,0) ),"") -> 0 | J58: 0 | K58: =J58 -> 0 | L58: =K58 -> 0 | M58: =L58 -> 0 | N58: =M58 -> 0
A60: Balance Sheet | C60: Balance Sheet
J61: Forecast
C62: FYE December | D62: =$D$5 -> 43465 | E62: =EDATE(D62,12) -> 43830 | F62: =EDATE(E62,12) -> 44196 | G62: =EDATE(F62,12) -> 44561 | H62: =EDATE(G62,12) -> 44926 | I62: =EDATE(H62,12) -> 45291 | J62: =EDATE(I62,12) -> 45657 | K62: =EDATE(J62,12) -> 46022 | L62: =EDATE(K62,12) -> 46387 | ... N62: =EDATE(M62,12) -> 47118
D63: USD | E63: USD | F63: USD | G63: USD | H63: USD | I63: USD | J63: USD | K63: USD | L63: USD | M63: USD | N63: USD
A64: Cash & Equivalents | C64: Cash and Cash Equivalents | D64: =IFERROR( INDEX('SLCA Raw'!$B$41:$K$100, MATCH(TRIM($A64),'SLCA Raw'!$M$41:$M$100,0), MATCH(D$33,'SLCA Raw'!$B$38:$K$38,0) ),"") -> 202.498 | E64: =IFERROR( INDEX('SLCA Raw'!$B$41:$K$100, MATCH(TRIM($A64),'SLCA Raw'!$M$41:$M$100,0), MATCH(E$33,'SLCA Raw'!$B$38:$K$38,0) ),"") -> 185.74 | F64: =IFERROR( INDEX('SLCA Raw'!$B$41:$K$100, MATCH(TRIM($A64),'SLCA Raw'!$M$41:$M$100,0), MATCH(F$33,'SLCA Raw'!$B$38:$K$38,0) ),"") -> 150.92 | G64: =IFERROR( INDEX('SLCA Raw'!$B$41:$K$100, MATCH(TRIM($A64),'SLCA Raw'!$M$41:$M$100,0), MATCH(G$33,'SLCA Raw'!$B$38:$K$38,0) ),"") -> 239.425 | H64: =IFERROR( INDEX('SLCA Raw'!$B$41:$K$100, MATCH(TRIM($A64),'SLCA Raw'!$M$41:$M$100,0), MATCH(H$33,'SLCA Raw'!$B$38:$K$38,0) ),"") -> 280.845 | I64: =IFERROR( INDEX('SLCA Raw'!$B$41:$K$100, MATCH(TRIM($A64),'SLCA Raw'!$M$41:$M$100,0), MATCH(I$33,'SLCA Raw'!$B$38:$K$38,0) ),"") -> 245.716 | J64: =J137 -> 533.93556 | K64: =K137 -> 767.85177 | L64: =L137 -> 1018.8226 | M64: =M137 -> 1266.4171 | N64: =N137 -> 1523.8351 | O64: (potentially change) | R64: possibly circular
A65: Total Receivables, Net | C65: Accounts Receivable | D65: =IFERROR( INDEX('SLCA Raw'!$B$41:$K$100, MATCH(TRIM($A65),'SLCA Raw'!$M$41:$M$100,0), MATCH(D$33,'SLCA Raw'!$B$38:$K$38,0) ),"") -> 217.686 | E65: =IFERROR( INDEX('SLCA Raw'!$B$41:$K$100, MATCH(TRIM($A65),'SLCA Raw'!$M$41:$M$100,0), MATCH(E$33,'SLCA Raw'!$B$38:$K$38,0) ),"") -> 182.713 | F65: =IFERROR( INDEX('SLCA Raw'!$B$41:$K$100, MATCH(TRIM($A65),'SLCA Raw'!$M$41:$M$100,0), MATCH(F$33,'SLCA Raw'!$B$38:$K$38,0) ),"") -> 207.562 | G65: =IFERROR( INDEX('SLCA Raw'!$B$41:$K$100, MATCH(TRIM($A65),'SLCA Raw'!$M$41:$M$100,0), MATCH(G$33,'SLCA Raw'!$B$38:$K$38,0) ),"") -> 202.759 | H65: =IFERROR( INDEX('SLCA Raw'!$B$41:$K$100, MATCH(TRIM($A65),'SLCA Raw'!$M$41:$M$100,0), MATCH(H$33,'SLCA Raw'!$B$38:$K$38,0) ),"") -> 208.631 | I65: =IFERROR( INDEX('SLCA Raw'!$B$41:$K$100, MATCH(TRIM($A65),'SLCA Raw'!$M$41:$M$100,0), MATCH(I$33,'SLCA Raw'!$B$38:$K$38,0) ),"") -> 185.917 | J65: =J$35*J$16 / 365 -> 215.41529 | K65: =K$35*K$16 / 365 -> 222.5565 | L65: =L$35*L$16 / 365 -> 229.69025 | M65: =M$35*M$16 / 365 -> 237.32974 | N65: =N$35*N$16 / 365 -> 245.4427
A66: Total Inventory | C66: Inventory | D66: =IFERROR( INDEX('SLCA Raw'!$B$41:$K$100, MATCH(TRIM($A66),'SLCA Raw'!$M$41:$M$100,0), MATCH(D$33,'SLCA Raw'!$B$38:$K$38,0) ),"") -> 162.087 | E66: =IFERROR( INDEX('SLCA Raw'!$B$41:$K$100, MATCH(TRIM($A66),'SLCA Raw'!$M$41:$M$100,0), MATCH(E$33,'SLCA Raw'!$B$38:$K$38,0) ),"") -> 124.432 | F66: =IFERROR( INDEX('SLCA Raw'!$B$41:$K$100, MATCH(TRIM($A66),'SLCA Raw'!$M$41:$M$100,0), MATCH(F$33,'SLCA Raw'!$B$38:$K$38,0) ),"") -> 104.684 | G66: =IFERROR( INDEX('SLCA Raw'!$B$41:$K$100, MATCH(TRIM($A66),'SLCA Raw'!$M$41:$M$100,0), MATCH(G$33,'SLCA Raw'!$B$38:$K$38,0) ),"") -> 115.713 | H66: =IFERROR( INDEX('SLCA Raw'!$B$41:$K$100, MATCH(TRIM($A66),'SLCA Raw'!$M$41:$M$100,0), MATCH(H$33,'SLCA Raw'!$B$38:$K$38,0) ),"") -> 147.626 | I66: =IFERROR( INDEX('SLCA Raw'!$B$41:$K$100, MATCH(TRIM($A66),'SLCA Raw'!$M$41:$M$100,0), MATCH(I$33,'SLCA Raw'!$B$38:$K$38,0) ),"") -> 149.429 | J66: =J$37*J$17 / 365 -> 158.2537 | K66: =K$37*K$17 / 365 -> 161.57969 | L66: =L$37*L$17 / 365 -> 165.27307 | M66: =M$37*M$17 / 365 -> 172.47613 | N66: =N$37*N$17 / 365 -> 177.72509
A67: Prepaid Expenses | C67: Prepaid Expenses | D67: =IFERROR( INDEX('SLCA Raw'!$B$41:$K$100, MATCH(TRIM($A67),'SLCA Raw'!$M$41:$M$100,0), MATCH(D$33,'SLCA Raw'!$B$38:$K$38,0) ),"") -> 18 | E67: =IFERROR( INDEX('SLCA Raw'!$B$41:$K$100, MATCH(TRIM($A67),'SLCA Raw'!$M$41:$M$100,0), MATCH(E$33,'SLCA Raw'!$B$38:$K$38,0) ),"") -> 16.2 | F67: =IFERROR( INDEX('SLCA Raw'!$B$41:$K$100, MATCH(TRIM($A67),'SLCA Raw'!$M$41:$M$100,0), MATCH(F$33,'SLCA Raw'!$B$38:$K$38,0) ),"") -> 23.1 | G67: =IFERROR( INDEX('SLCA Raw'!$B$41:$K$100, MATCH(TRIM($A67),'SLCA Raw'!$M$41:$M$100,0), MATCH(G$33,'SLCA Raw'!$B$38:$K$38,0) ),"") -> 18 | H67: =IFERROR( INDEX('SLCA Raw'!$B$41:$K$100, MATCH(TRIM($A67),'SLCA Raw'!$M$41:$M$100,0), MATCH(H$33,'SLCA Raw'!$B$38:$K$38,0) ),"") -> 20.2 | I67: =IFERROR( INDEX('SLCA Raw'!$B$41:$K$100, MATCH(TRIM($A67),'SLCA Raw'!$M$41:$M$100,0), MATCH(I$33,'SLCA Raw'!$B$38:$K$38,0) ),"") -> 19.7 | J67: =J$35*J$19 -> 22.595182 | K67: =K$35*K$19 -> 23.344233 | L67: =L$35*L$19 -> 24.0925 | M67: =M$35*M$19 -> 24.893817 | N67: =N$35*N$19 -> 25.744795
A68: Other Current Assets, Total | C68: Other Current Assets | D68: =IFERROR( INDEX('SLCA Raw'!$B$41:$K$100, MATCH(TRIM($A68),'SLCA Raw'!$M$41:$M$100,0), MATCH(D$33,'SLCA Raw'!$B$38:$K$38,0) ),"") -> 0 | E68: =IFERROR( INDEX('SLCA Raw'!$B$41:$K$100, MATCH(TRIM($A68),'SLCA Raw'!$M$41:$M$100,0), MATCH(E$33,'SLCA Raw'!$B$38:$K$38,0) ),"") -> 0 | F68: =IFERROR( INDEX('SLCA Raw'!$B$41:$K$100, MATCH(TRIM($A68),'SLCA Raw'!$M$41:$M$100,0), MATCH(F$33,'SLCA Raw'!$B$38:$K$38,0) ),"") -> 0 | G68: =IFERROR( INDEX('SLCA Raw'!$B$41:$K$100, MATCH(TRIM($A68),'SLCA Raw'!$M$41:$M$100,0), MATCH(G$33,'SLCA Raw'!$B$38:$K$38,0) ),"") -> 0 | H68: =IFERROR( INDEX('SLCA Raw'!$B$41:$K$100, MATCH(TRIM($A68),'SLCA Raw'!$M$41:$M$100,0), MATCH(H$33,'SLCA Raw'!$B$38:$K$38,0) ),"") -> 0 | I68: =IFERROR( INDEX('SLCA Raw'!$B$41:$K$100, MATCH(TRIM($A68),'SLCA Raw'!$M$41:$M$100,0), MATCH(I$33,'SLCA Raw'!$B$38:$K$38,0) ),"") -> 0 | J68: =J$35*J$20 -> 0 | K68: =K$35*K$20 -> 0 | L68: =L$35*L$20 -> 0 | M68: =M$35*M$20 -> 0 | N68: =N$35*N$20 -> 0
A69: Total Current Assets | C69: Total Current Assets | D69: =IFERROR( INDEX('SLCA Raw'!$B$41:$K$100, MATCH(TRIM($A69),'SLCA Raw'!$M$41:$M$100,0), MATCH(D$33,'SLCA Raw'!$B$38:$K$38,0) ),"") -> 600.237 | E69: =IFERROR( INDEX('SLCA Raw'!$B$41:$K$100, MATCH(TRIM($A69),'SLCA Raw'!$M$41:$M$100,0), MATCH(E$33,'SLCA Raw'!$B$38:$K$38,0) ),"") -> 509.04 | F69: =IFERROR( INDEX('SLCA Raw'!$B$41:$K$100, MATCH(TRIM($A69),'SLCA Raw'!$M$41:$M$100,0), MATCH(F$33,'SLCA Raw'!$B$38:$K$38,0) ),"") -> 486.313 | G69: =IFERROR( INDEX('SLCA Raw'!$B$41:$K$100, MATCH(TRIM($A69),'SLCA Raw'!$M$41:$M$100,0), MATCH(G$33,'SLCA Raw'!$B$38:$K$38,0) ),"") -> 575.915 | H69: =IFERROR( INDEX('SLCA Raw'!$B$41:$K$100, MATCH(TRIM($A69),'SLCA Raw'!$M$41:$M$100,0), MATCH(H$33,'SLCA Raw'!$B$38:$K$38,0) ),"") -> 657.284 | I69: =IFERROR( INDEX('SLCA Raw'!$B$41:$K$100, MATCH(TRIM($A69),'SLCA Raw'!$M$41:$M$100,0), MATCH(I$33,'SLCA Raw'!$B$38:$K$38,0) ),"") -> 600.744 | J69: =SUM(J$64:J$68) -> 930.19973 | K69: =SUM(K$64:K$68) -> 1175.3322 | L69: =SUM(L$64:L$68) -> 1437.8784 | M69: =SUM(M$64:M$68) -> 1701.1168 | N69: =SUM(N$64:N$68) -> 1972.7477
A71: Property/Plant/Equipment, Total - Gross | C71: Gross PP&E | D71: =IFERROR( INDEX('SLCA Raw'!$B$41:$K$100, MATCH(TRIM($A71),'SLCA Raw'!$M$41:$M$100,0), MATCH(D$33,'SLCA Raw'!$B$38:$K$38,0) ),"") -> 2326.1 | E71: =IFERROR( INDEX('SLCA Raw'!$B$41:$K$100, MATCH(TRIM($A71),'SLCA Raw'!$M$41:$M$100,0), MATCH(E$33,'SLCA Raw'!$B$38:$K$38,0) ),"") -> 2277.3 | F71: =IFERROR( INDEX('SLCA Raw'!$B$41:$K$100, MATCH(TRIM($A71),'SLCA Raw'!$M$41:$M$100,0), MATCH(F$33,'SLCA Raw'!$B$38:$K$38,0) ),"") -> 2245 | G71: =IFERROR( INDEX('SLCA Raw'!$B$41:$K$100, MATCH(TRIM($A71),'SLCA Raw'!$M$41:$M$100,0), MATCH(G$33,'SLCA Raw'!$B$38:$K$38,0) ),"") -> 2286.2 | H71: =IFERROR( INDEX('SLCA Raw'!$B$41:$K$100, MATCH(TRIM($A71),'SLCA Raw'!$M$41:$M$100,0), MATCH(H$33,'SLCA Raw'!$B$38:$K$38,0) ),"") -> 2321.1 | I71: =IFERROR( INDEX('SLCA Raw'!$B$41:$K$100, MATCH(TRIM($A71),'SLCA Raw'!$M$41:$M$100,0), MATCH(I$33,'SLCA Raw'!$B$38:$K$38,0) ),"") -> 2377.6 | J71: =I71-J121 -> 2457.8312 | K71: =J71-K121 -> 2540.7221 | L71: =K71-L121 -> 2626.27 | M71: =L71-M121 -> 2714.6633 | N71: =M71-N121 -> 2806.0782
A72: Accumulated Depreciation, Total | C72: Accumulated Depreciation | D72: =IFERROR( INDEX('SLCA Raw'!$B$41:$K$100, MATCH(TRIM($A72),'SLCA Raw'!$M$41:$M$100,0), MATCH(D$33,'SLCA Raw'!$B$38:$K$38,0) ),"") -> -499.823 | E72: =IFERROR( INDEX('SLCA Raw'!$B$41:$K$100, MATCH(TRIM($A72),'SLCA Raw'!$M$41:$M$100,0), MATCH(E$33,'SLCA Raw'!$B$38:$K$38,0) ),"") -> -706.61 | F72: =IFERROR( INDEX('SLCA Raw'!$B$41:$K$100, MATCH(TRIM($A72),'SLCA Raw'!$M$41:$M$100,0), MATCH(F$33,'SLCA Raw'!$B$38:$K$38,0) ),"") -> -839.402 | G72: =IFERROR( INDEX('SLCA Raw'!$B$41:$K$100, MATCH(TRIM($A72),'SLCA Raw'!$M$41:$M$100,0), MATCH(G$33,'SLCA Raw'!$B$38:$K$38,0) ),"") -> -985.295 | H72: =IFERROR( INDEX('SLCA Raw'!$B$41:$K$100, MATCH(TRIM($A72),'SLCA Raw'!$M$41:$M$100,0), MATCH(H$33,'SLCA Raw'!$B$38:$K$38,0) ),"") -> -1099.922 | I72: =IFERROR( INDEX('SLCA Raw'!$B$41:$K$100, MATCH(TRIM($A72),'SLCA Raw'!$M$41:$M$100,0), MATCH(I$33,'SLCA Raw'!$B$38:$K$38,0) ),"") -> -1211.26 | J72: =I72-J41 -> -1357.4933 | K72: =J72-K41 -> -1503.7267 | L72: =K72-L41 -> -1649.96 | M72: =L72-M41 -> -1796.1933 | N72: =M72-N41 -> -1942.4267
A73: Property/Plant/Equipment, Total - Net | C73: Net PP&E | D73: =IFERROR( INDEX('SLCA Raw'!$B$41:$K$100, MATCH(TRIM($A73),'SLCA Raw'!$M$41:$M$100,0), MATCH(D$33,'SLCA Raw'!$B$38:$K$38,0) ),"") -> 1826.3 | E73: =IFERROR( INDEX('SLCA Raw'!$B$41:$K$100, MATCH(TRIM($A73),'SLCA Raw'!$M$41:$M$100,0), MATCH(E$33,'SLCA Raw'!$B$38:$K$38,0) ),"") -> 1570.7 | F73: =IFERROR( INDEX('SLCA Raw'!$B$41:$K$100, MATCH(TRIM($A73),'SLCA Raw'!$M$41:$M$100,0), MATCH(F$33,'SLCA Raw'!$B$38:$K$38,0) ),"") -> 1405.6 | G73: =IFERROR( INDEX('SLCA Raw'!$B$41:$K$100, MATCH(TRIM($A73),'SLCA Raw'!$M$41:$M$100,0), MATCH(G$33,'SLCA Raw'!$B$38:$K$38,0) ),"") -> 1300.9 | H73: =IFERROR( INDEX('SLCA Raw'!$B$41:$K$100, MATCH(TRIM($A73),'SLCA Raw'!$M$41:$M$100,0), MATCH(H$33,'SLCA Raw'!$B$38:$K$38,0) ),"") -> 1221.2 | I73: =IFERROR( INDEX('SLCA Raw'!$B$41:$K$100, MATCH(TRIM($A73),'SLCA Raw'!$M$41:$M$100,0), MATCH(I$33,'SLCA Raw'!$B$38:$K$38,0) ),"") -> 1166.3 | J73: =J71+J72 -> 1100.3379 | K73: =K71+K72 -> 1036.9955 | L73: =L71+L72 -> 976.31005 | M73: =M71+M72 -> 918.46993 | N73: =N71+N72 -> 863.65148
A74: Goodwill, Net | C74: Goodwill | D74: =IFERROR( INDEX('SLCA Raw'!$B$41:$K$100, MATCH(TRIM($A74),'SLCA Raw'!$M$41:$M$100,0), MATCH(D$33,'SLCA Raw'!$B$38:$K$38,0) ),"") -> 261.34 | E74: =IFERROR( INDEX('SLCA Raw'!$B$41:$K$100, MATCH(TRIM($A74),'SLCA Raw'!$M$41:$M$100,0), MATCH(E$33,'SLCA Raw'!$B$38:$K$38,0) ),"") -> 273.524 | F74: =IFERROR( INDEX('SLCA Raw'!$B$41:$K$100, MATCH(TRIM($A74),'SLCA Raw'!$M$41:$M$100,0), MATCH(F$33,'SLCA Raw'!$B$38:$K$38,0) ),"") -> 185.649 | G74: =IFERROR( INDEX('SLCA Raw'!$B$41:$K$100, MATCH(TRIM($A74),'SLCA Raw'!$M$41:$M$100,0), MATCH(G$33,'SLCA Raw'!$B$38:$K$38,0) ),"") -> 185.649 | H74: =IFERROR( INDEX('SLCA Raw'!$B$41:$K$100, MATCH(TRIM($A74),'SLCA Raw'!$M$41:$M$100,0), MATCH(H$33,'SLCA Raw'!$B$38:$K$38,0) ),"") -> 185.649 | I74: =IFERROR( INDEX('SLCA Raw'!$B$41:$K$100, MATCH(TRIM($A74),'SLCA Raw'!$M$41:$M$100,0), MATCH(I$33,'SLCA Raw'!$B$38:$K$38,0) ),"") -> 185.649 | J74: =I74 -> 185.649 | K74: =J74 -> 185.649 | L74: =K74 -> 185.649 | M74: =L74 -> 185.649 | N74: =M74 -> 185.649
A75: Intangibles, Net | C75: Intangible Assets | D75: =IFERROR( INDEX('SLCA Raw'!$B$41:$K$100, MATCH(TRIM($A75),'SLCA Raw'!$M$41:$M$100,0), MATCH(D$33,'SLCA Raw'!$B$38:$K$38,0) ),"") -> 194.626 | E75: =IFERROR( INDEX('SLCA Raw'!$B$41:$K$100, MATCH(TRIM($A75),'SLCA Raw'!$M$41:$M$100,0), MATCH(E$33,'SLCA Raw'!$B$38:$K$38,0) ),"") -> 183.815 | F75: =IFERROR( INDEX('SLCA Raw'!$B$41:$K$100, MATCH(TRIM($A75),'SLCA Raw'!$M$41:$M$100,0), MATCH(F$33,'SLCA Raw'!$B$38:$K$38,0) ),"") -> 159.582 | G75: =IFERROR( INDEX('SLCA Raw'!$B$41:$K$100, MATCH(TRIM($A75),'SLCA Raw'!$M$41:$M$100,0), MATCH(G$33,'SLCA Raw'!$B$38:$K$38,0) ),"") -> 150.054 | H75: =IFERROR( INDEX('SLCA Raw'!$B$41:$K$100, MATCH(TRIM($A75),'SLCA Raw'!$M$41:$M$100,0), MATCH(H$33,'SLCA Raw'!$B$38:$K$38,0) ),"") -> 140.809 | I75: =IFERROR( INDEX('SLCA Raw'!$B$41:$K$100, MATCH(TRIM($A75),'SLCA Raw'!$M$41:$M$100,0), MATCH(I$33,'SLCA Raw'!$B$38:$K$38,0) ),"") -> 131.384 | J75: =I$75 -> 131.384 | K75: =J$75 -> 131.384 | L75: =K$75 -> 131.384 | M75: =L$75 -> 131.384 | N75: =M$75 -> 131.384
A76: Long Term Investments | C76: Long-Term Investments | D76: =IFERROR( INDEX('SLCA Raw'!$B$41:$K$100, MATCH(TRIM($A76),'SLCA Raw'!$M$41:$M$100,0), MATCH(D$33,'SLCA Raw'!$B$38:$K$38,0) ),"") -> 0 | E76: =IFERROR( INDEX('SLCA Raw'!$B$41:$K$100, MATCH(TRIM($A76),'SLCA Raw'!$M$41:$M$100,0), MATCH(E$33,'SLCA Raw'!$B$38:$K$38,0) ),"") -> 0 | F76: =IFERROR( INDEX('SLCA Raw'!$B$41:$K$100, MATCH(TRIM($A76),'SLCA Raw'!$M$41:$M$100,0), MATCH(F$33,'SLCA Raw'!$B$38:$K$38,0) ),"") -> 0 | G76: =IFERROR( INDEX('SLCA Raw'!$B$41:$K$100, MATCH(TRIM($A76),'SLCA Raw'!$M$41:$M$100,0), MATCH(G$33,'SLCA Raw'!$B$38:$K$38,0) ),"") -> 0 | H76: =IFERROR( INDEX('SLCA Raw'!$B$41:$K$100, MATCH(TRIM($A76),'SLCA Raw'!$M$41:$M$100,0), MATCH(H$33,'SLCA Raw'!$B$38:$K$38,0) ),"") -> 0 | I76: =IFERROR( INDEX('SLCA Raw'!$B$41:$K$100, MATCH(TRIM($A76),'SLCA Raw'!$M$41:$M$100,0), MATCH(I$33,'SLCA Raw'!$B$38:$K$38,0) ),"") -> 0 | J76: =I76 -> 0 | K76: =J76 -> 0 | L76: =K76 -> 0 | M76: =L76 -> 0 | N76: =M76 -> 0
A77: Other Long Term Assets, Total | C77: Other Long-Term Assets | D77: =IFERROR( INDEX('SLCA Raw'!$B$41:$K$100, MATCH(TRIM($A77),'SLCA Raw'!$M$41:$M$100,0), MATCH(D$33,'SLCA Raw'!$B$38:$K$38,0) ),"") -> 18.3 | E77: =IFERROR( INDEX('SLCA Raw'!$B$41:$K$100, MATCH(TRIM($A77),'SLCA Raw'!$M$41:$M$100,0), MATCH(E$33,'SLCA Raw'!$B$38:$K$38,0) ),"") -> 16.2 | F77: =IFERROR( INDEX('SLCA Raw'!$B$41:$K$100, MATCH(TRIM($A77),'SLCA Raw'!$M$41:$M$100,0), MATCH(F$33,'SLCA Raw'!$B$38:$K$38,0) ),"") -> 9.8 | G77: =IFERROR( INDEX('SLCA Raw'!$B$41:$K$100, MATCH(TRIM($A77),'SLCA Raw'!$M$41:$M$100,0), MATCH(G$33,'SLCA Raw'!$B$38:$K$38,0) ),"") -> 7.1 | H77: =IFERROR( INDEX('SLCA Raw'!$B$41:$K$100, MATCH(TRIM($A77),'SLCA Raw'!$M$41:$M$100,0), MATCH(H$33,'SLCA Raw'!$B$38:$K$38,0) ),"") -> 9.6 | I77: =IFERROR( INDEX('SLCA Raw'!$B$41:$K$100, MATCH(TRIM($A77),'SLCA Raw'!$M$41:$M$100,0), MATCH(I$33,'SLCA Raw'!$B$38:$K$38,0) ),"") -> 12.5 | J77: =J$35*J$25 -> 11.114883 | K77: =K$35*K$25 -> 11.483352 | L77: =L$35*L$25 -> 11.851435 | M77: =M$35*M$25 -> 12.245613 | N77: =N$35*N$25 -> 12.664221
A78: Other Assets, Total | C78: Other Assets | D78: =IFERROR( INDEX('SLCA Raw'!$B$41:$K$100, MATCH(TRIM($A78),'SLCA Raw'!$M$41:$M$100,0), MATCH(D$33,'SLCA Raw'!$B$38:$K$38,0) ),"") -> 0 | E78: =IFERROR( INDEX('SLCA Raw'!$B$41:$K$100, MATCH(TRIM($A78),'SLCA Raw'!$M$41:$M$100,0), MATCH(E$33,'SLCA Raw'!$B$38:$K$38,0) ),"") -> 0 | F78: =IFERROR( INDEX('SLCA Raw'!$B$41:$K$100, MATCH(TRIM($A78),'SLCA Raw'!$M$41:$M$100,0), MATCH(F$33,'SLCA Raw'!$B$38:$K$38,0) ),"") -> 0 | G78: =IFERROR( INDEX('SLCA Raw'!$B$41:$K$100, MATCH(TRIM($A78),'SLCA Raw'!$M$41:$M$100,0), MATCH(G$33,'SLCA Raw'!$B$38:$K$38,0) ),"") -> 0 | H78: =IFERROR( INDEX('SLCA Raw'!$B$41:$K$100, MATCH(TRIM($A78),'SLCA Raw'!$M$41:$M$100,0), MATCH(H$33,'SLCA Raw'!$B$38:$K$38,0) ),"") -> 0 | I78: =IFERROR( INDEX('SLCA Raw'!$B$41:$K$100, MATCH(TRIM($A78),'SLCA Raw'!$M$41:$M$100,0), MATCH(I$33,'SLCA Raw'!$B$38:$K$38,0) ),"") -> 0 | J78: =AVERAGE($D$78:$I$78) -> 0 | K78: =AVERAGE($D$78:$I$78) -> 0 | L78: =AVERAGE($D$78:$I$78) -> 0 | M78: =AVERAGE($D$78:$I$78) -> 0 | N78: =AVERAGE($D$78:$I$78) -> 0
A79: Total Assets | C79: Total Assets | D79: =IFERROR( INDEX('SLCA Raw'!$B$41:$K$100, MATCH(TRIM($A79),'SLCA Raw'!$M$41:$M$100,0), MATCH(D$33,'SLCA Raw'!$B$38:$K$38,0) ),"") -> 2900.84 | E79: =IFERROR( INDEX('SLCA Raw'!$B$41:$K$100, MATCH(TRIM($A79),'SLCA Raw'!$M$41:$M$100,0), MATCH(E$33,'SLCA Raw'!$B$38:$K$38,0) ),"") -> 2553.234 | F79: =IFERROR( INDEX('SLCA Raw'!$B$41:$K$100, MATCH(TRIM($A79),'SLCA Raw'!$M$41:$M$100,0), MATCH(F$33,'SLCA Raw'!$B$38:$K$38,0) ),"") -> 2246.947 | G79: =IFERROR( INDEX('SLCA Raw'!$B$41:$K$100, MATCH(TRIM($A79),'SLCA Raw'!$M$41:$M$100,0), MATCH(G$33,'SLCA Raw'!$B$38:$K$38,0) ),"") -> 2219.6 | H79: =IFERROR( INDEX('SLCA Raw'!$B$41:$K$100, MATCH(TRIM($A79),'SLCA Raw'!$M$41:$M$100,0), MATCH(H$33,'SLCA Raw'!$B$38:$K$38,0) ),"") -> 2214.58 | I79: =IFERROR( INDEX('SLCA Raw'!$B$41:$K$100, MATCH(TRIM($A79),'SLCA Raw'!$M$41:$M$100,0), MATCH(I$33,'SLCA Raw'!$B$38:$K$38,0) ),"") -> 2096.593 | J79: =J$69+J$73+J$74+J$75+J$76+J$77 -> 2358.6855 | K79: =K$69+K$73+K$74+K$75+K$76+K$77 -> 2540.844 | L79: =L$69+L$73+L$74+L$75+L$76+L$77 -> 2743.0729 | M79: =M$69+M$73+M$74+M$75+M$76+M$77 -> 2948.8653 | N79: =N$69+N$73+N$74+N$75+N$76+N$77 -> 3166.0964
A81: Accounts Payable | C81: Accounts Payable | D81: =IFERROR( INDEX('SLCA Raw'!$B$41:$K$100, MATCH(TRIM($A81),'SLCA Raw'!$M$41:$M$100,0), MATCH(D$33,'SLCA Raw'!$B$38:$K$38,0) ),"") -> 178.804 | E81: =IFERROR( INDEX('SLCA Raw'!$B$41:$K$100, MATCH(TRIM($A81),'SLCA Raw'!$M$41:$M$100,0), MATCH(E$33,'SLCA Raw'!$B$38:$K$38,0) ),"") -> 181.029 | F81: =IFERROR( INDEX('SLCA Raw'!$B$41:$K$100, MATCH(TRIM($A81),'SLCA Raw'!$M$41:$M$100,0), MATCH(F$33,'SLCA Raw'!$B$38:$K$38,0) ),"") -> 90.564 | G81: =IFERROR( INDEX('SLCA Raw'!$B$41:$K$100, MATCH(TRIM($A81),'SLCA Raw'!$M$41:$M$100,0), MATCH(G$33,'SLCA Raw'!$B$38:$K$38,0) ),"") -> 134.494 | H81: =IFERROR( INDEX('SLCA Raw'!$B$41:$K$100, MATCH(TRIM($A81),'SLCA Raw'!$M$41:$M$100,0), MATCH(H$33,'SLCA Raw'!$B$38:$K$38,0) ),"") -> 182.555 | I81: =IFERROR( INDEX('SLCA Raw'!$B$41:$K$100, MATCH(TRIM($A81),'SLCA Raw'!$M$41:$M$100,0), MATCH(I$33,'SLCA Raw'!$B$38:$K$38,0) ),"") -> 123.667 | J81: =J$37*J$18 / 365 -> 170.95308 | K81: =K$37*K$18 / 365 -> 174.54596 | L81: =L$37*L$18 / 365 -> 178.53573 | M81: =M$37*M$18 / 365 -> 186.31681 | N81: =N$37*N$18 / 365 -> 191.98698
A82: Accrued Expenses | C82: Accrued Expenses | D82: =IFERROR( INDEX('SLCA Raw'!$B$41:$K$100, MATCH(TRIM($A82),'SLCA Raw'!$M$41:$M$100,0), MATCH(D$33,'SLCA Raw'!$B$38:$K$38,0) ),"") -> 37.6 | E82: =IFERROR( INDEX('SLCA Raw'!$B$41:$K$100, MATCH(TRIM($A82),'SLCA Raw'!$M$41:$M$100,0), MATCH(E$33,'SLCA Raw'!$B$38:$K$38,0) ),"") -> 94.2 | F82: =IFERROR( INDEX('SLCA Raw'!$B$41:$K$100, MATCH(TRIM($A82),'SLCA Raw'!$M$41:$M$100,0), MATCH(F$33,'SLCA Raw'!$B$38:$K$38,0) ),"") -> 44 | G82: =IFERROR( INDEX('SLCA Raw'!$B$41:$K$100, MATCH(TRIM($A82),'SLCA Raw'!$M$41:$M$100,0), MATCH(G$33,'SLCA Raw'!$B$38:$K$38,0) ),"") -> 47.6 | H82: =IFERROR( INDEX('SLCA Raw'!$B$41:$K$100, MATCH(TRIM($A82),'SLCA Raw'!$M$41:$M$100,0), MATCH(H$33,'SLCA Raw'!$B$38:$K$38,0) ),"") -> 51.1 | I82: =IFERROR( INDEX('SLCA Raw'!$B$41:$K$100, MATCH(TRIM($A82),'SLCA Raw'!$M$41:$M$100,0), MATCH(I$33,'SLCA Raw'!$B$38:$K$38,0) ),"") -> 40.6 | J82: =J$35*J$21 -> 54.977127 | K82: =J82 -> 54.977127 | L82: =L$35*L$21 -> 58.620305 | M82: =M$35*M$21 -> 60.570016 | N82: =N$35*N$21 -> 62.640561
A83: Current Port. of LT Debt/Capital Leases | C83: Current Portion of Debt | D83: =IFERROR( INDEX('SLCA Raw'!$B$41:$K$100, MATCH(TRIM($A83),'SLCA Raw'!$M$41:$M$100,0), MATCH(D$33,'SLCA Raw'!$B$38:$K$38,0) ),"") -> 13.3 | E83: =IFERROR( INDEX('SLCA Raw'!$B$41:$K$100, MATCH(TRIM($A83),'SLCA Raw'!$M$41:$M$100,0), MATCH(E$33,'SLCA Raw'!$B$38:$K$38,0) ),"") -> 18.5 | F83: =IFERROR( INDEX('SLCA Raw'!$B$41:$K$100, MATCH(TRIM($A83),'SLCA Raw'!$M$41:$M$100,0), MATCH(F$33,'SLCA Raw'!$B$38:$K$38,0) ),"") -> 42 | G83: =IFERROR( INDEX('SLCA Raw'!$B$41:$K$100, MATCH(TRIM($A83),'SLCA Raw'!$M$41:$M$100,0), MATCH(G$33,'SLCA Raw'!$B$38:$K$38,0) ),"") -> 18.3 | H83: =IFERROR( INDEX('SLCA Raw'!$B$41:$K$100, MATCH(TRIM($A83),'SLCA Raw'!$M$41:$M$100,0), MATCH(H$33,'SLCA Raw'!$B$38:$K$38,0) ),"") -> 19.5 | I83: =IFERROR( INDEX('SLCA Raw'!$B$41:$K$100, MATCH(TRIM($A83),'SLCA Raw'!$M$41:$M$100,0), MATCH(I$33,'SLCA Raw'!$B$38:$K$38,0) ),"") -> 16.4 | J83: =$I$83 -> 16.4 | K83: =$I$83 -> 16.4 | L83: =$I$83 -> 16.4 | M83: =$I$83 -> 16.4 | N83: =$I$83 -> 16.4
A84: Notes Payable/Short Term Debt | C84: Other Short-Term Debt | D84: =IFERROR( INDEX('SLCA Raw'!$B$41:$K$100, MATCH(TRIM($A84),'SLCA Raw'!$M$41:$M$100,0), MATCH(D$33,'SLCA Raw'!$B$38:$K$38,0) ),"") -> 0 | E84: =IFERROR( INDEX('SLCA Raw'!$B$41:$K$100, MATCH(TRIM($A84),'SLCA Raw'!$M$41:$M$100,0), MATCH(E$33,'SLCA Raw'!$B$38:$K$38,0) ),"") -> 0 | F84: =IFERROR( INDEX('SLCA Raw'!$B$41:$K$100, MATCH(TRIM($A84),'SLCA Raw'!$M$41:$M$100,0), MATCH(F$33,'SLCA Raw'!$B$38:$K$38,0) ),"") -> 0 | G84: =IFERROR( INDEX('SLCA Raw'!$B$41:$K$100, MATCH(TRIM($A84),'SLCA Raw'!$M$41:$M$100,0), MATCH(G$33,'SLCA Raw'!$B$38:$K$38,0) ),"") -> 0 | H84: =IFERROR( INDEX('SLCA Raw'!$B$41:$K$100, MATCH(TRIM($A84),'SLCA Raw'!$M$41:$M$100,0), MATCH(H$33,'SLCA Raw'!$B$38:$K$38,0) ),"") -> 0 | I84: =IFERROR( INDEX('SLCA Raw'!$B$41:$K$100, MATCH(TRIM($A84),'SLCA Raw'!$M$41:$M$100,0), MATCH(I$33,'SLCA Raw'!$B$38:$K$38,0) ),"") -> 0 | J84: 0 | K84: =$J$84 -> 0 | L84: =$J$84 -> 0 | M84: =$J$84 -> 0 | N84: =$J$84 -> 0
A85: Other Current Liabilities, Total | C85: Other Current Liabilities | D85: =IFERROR( INDEX('SLCA Raw'!$B$41:$K$100, MATCH(TRIM($A85),'SLCA Raw'!$M$41:$M$100,0), MATCH(D$33,'SLCA Raw'!$B$38:$K$38,0) ),"") -> 31.6 | E85: =IFERROR( INDEX('SLCA Raw'!$B$41:$K$100, MATCH(TRIM($A85),'SLCA Raw'!$M$41:$M$100,0), MATCH(E$33,'SLCA Raw'!$B$38:$K$38,0) ),"") -> 15.1 | F85: =IFERROR( INDEX('SLCA Raw'!$B$41:$K$100, MATCH(TRIM($A85),'SLCA Raw'!$M$41:$M$100,0), MATCH(F$33,'SLCA Raw'!$B$38:$K$38,0) ),"") -> 13.5 | G85: =IFERROR( INDEX('SLCA Raw'!$B$41:$K$100, MATCH(TRIM($A85),'SLCA Raw'!$M$41:$M$100,0), MATCH(G$33,'SLCA Raw'!$B$38:$K$38,0) ),"") -> 5.4 | H85: =IFERROR( INDEX('SLCA Raw'!$B$41:$K$100, MATCH(TRIM($A85),'SLCA Raw'!$M$41:$M$100,0), MATCH(H$33,'SLCA Raw'!$B$38:$K$38,0) ),"") -> 18.7 | I85: =IFERROR( INDEX('SLCA Raw'!$B$41:$K$100, MATCH(TRIM($A85),'SLCA Raw'!$M$41:$M$100,0), MATCH(I$33,'SLCA Raw'!$B$38:$K$38,0) ),"") -> 5.3 | J85: =J$35*J$22 -> 11.001225 | K85: =K$35*K$22 -> 11.365925 | L85: =L$35*L$22 -> 11.730244 | M85: =M$35*M$22 -> 12.120392 | N85: =N$35*N$22 -> 12.53472
A86: Total Current Liabilities | C86: Total Current Liabilities | D86: =IFERROR( INDEX('SLCA Raw'!$B$41:$K$100, MATCH(TRIM($A86),'SLCA Raw'!$M$41:$M$100,0), MATCH(D$33,'SLCA Raw'!$B$38:$K$38,0) ),"") -> 261.339 | E86: =IFERROR( INDEX('SLCA Raw'!$B$41:$K$100, MATCH(TRIM($A86),'SLCA Raw'!$M$41:$M$100,0), MATCH(E$33,'SLCA Raw'!$B$38:$K$38,0) ),"") -> 335.398 | F86: =IFERROR( INDEX('SLCA Raw'!$B$41:$K$100, MATCH(TRIM($A86),'SLCA Raw'!$M$41:$M$100,0), MATCH(F$33,'SLCA Raw'!$B$38:$K$38,0) ),"") -> 194.895 | G86: =IFERROR( INDEX('SLCA Raw'!$B$41:$K$100, MATCH(TRIM($A86),'SLCA Raw'!$M$41:$M$100,0), MATCH(G$33,'SLCA Raw'!$B$38:$K$38,0) ),"") -> 205.871 | H86: =IFERROR( INDEX('SLCA Raw'!$B$41:$K$100, MATCH(TRIM($A86),'SLCA Raw'!$M$41:$M$100,0), MATCH(H$33,'SLCA Raw'!$B$38:$K$38,0) ),"") -> 271.95 | I86: =IFERROR( INDEX('SLCA Raw'!$B$41:$K$100, MATCH(TRIM($A86),'SLCA Raw'!$M$41:$M$100,0), MATCH(I$33,'SLCA Raw'!$B$38:$K$38,0) ),"") -> 185.85 | J86: =SUM(J81:J85) -> 253.33143 | K86: =SUM(K81:K85) -> 257.28901 | L86: =SUM(L81:L85) -> 265.28628 | M86: =SUM(M81:M85) -> 275.40722 | N86: =SUM(N81:N85) -> 283.56226
A88: Long Term Debt | C88: Long-Term Debt | D88: =IFERROR( INDEX('SLCA Raw'!$B$41:$K$100, MATCH(TRIM($A88),'SLCA Raw'!$M$41:$M$100,0), MATCH(D$33,'SLCA Raw'!$B$38:$K$38,0) ),"") -> 1246.4 | E88: =IFERROR( INDEX('SLCA Raw'!$B$41:$K$100, MATCH(TRIM($A88),'SLCA Raw'!$M$41:$M$100,0), MATCH(E$33,'SLCA Raw'!$B$38:$K$38,0) ),"") -> 1214 | F88: =IFERROR( INDEX('SLCA Raw'!$B$41:$K$100, MATCH(TRIM($A88),'SLCA Raw'!$M$41:$M$100,0), MATCH(F$33,'SLCA Raw'!$B$38:$K$38,0) ),"") -> 1197.4 | G88: =IFERROR( INDEX('SLCA Raw'!$B$41:$K$100, MATCH(TRIM($A88),'SLCA Raw'!$M$41:$M$100,0), MATCH(G$33,'SLCA Raw'!$B$38:$K$38,0) ),"") -> 1190.6 | H88: =IFERROR( INDEX('SLCA Raw'!$B$41:$K$100, MATCH(TRIM($A88),'SLCA Raw'!$M$41:$M$100,0), MATCH(H$33,'SLCA Raw'!$B$38:$K$38,0) ),"") -> 1035.3 | I88: =IFERROR( INDEX('SLCA Raw'!$B$41:$K$100, MATCH(TRIM($A88),'SLCA Raw'!$M$41:$M$100,0), MATCH(I$33,'SLCA Raw'!$B$38:$K$38,0) ),"") -> 821.7 | J88: =I88 -> 821.7 | K88: =J88 -> 821.7 | L88: =K88 -> 821.7 | M88: =L88 -> 821.7 | N88: =M88 -> 821.7
A89: Capital Lease Obligations | C89: Lease Obligations | D89: =IFERROR( INDEX('SLCA Raw'!$B$41:$K$100, MATCH(TRIM($A89),'SLCA Raw'!$M$41:$M$100,0), MATCH(D$33,'SLCA Raw'!$B$38:$K$38,0) ),"") -> 0 | E89: =IFERROR( INDEX('SLCA Raw'!$B$41:$K$100, MATCH(TRIM($A89),'SLCA Raw'!$M$41:$M$100,0), MATCH(E$33,'SLCA Raw'!$B$38:$K$38,0) ),"") -> 0 | F89: =IFERROR( INDEX('SLCA Raw'!$B$41:$K$100, MATCH(TRIM($A89),'SLCA Raw'!$M$41:$M$100,0), MATCH(F$33,'SLCA Raw'!$B$38:$K$38,0) ),"") -> 0.3 | G89: =IFERROR( INDEX('SLCA Raw'!$B$41:$K$100, MATCH(TRIM($A89),'SLCA Raw'!$M$41:$M$100,0), MATCH(G$33,'SLCA Raw'!$B$38:$K$38,0) ),"") -> 2.5 | H89: =IFERROR( INDEX('SLCA Raw'!$B$41:$K$100, MATCH(TRIM($A89),'SLCA Raw'!$M$41:$M$100,0), MATCH(H$33,'SLCA Raw'!$B$38:$K$38,0) ),"") -> 2.2 | I89: =IFERROR( INDEX('SLCA Raw'!$B$41:$K$100, MATCH(TRIM($A89),'SLCA Raw'!$M$41:$M$100,0), MATCH(I$33,'SLCA Raw'!$B$38:$K$38,0) ),"") -> 2 | J89: 0 | K89: =$J$89 -> 0 | L89: =$J$89 -> 0 | M89: =$J$89 -> 0 | N89: =$J$89 -> 0
A90: Total Long Term Debt | C90: Total Long-Term Debt | D90: =IFERROR( INDEX('SLCA Raw'!$B$41:$K$100, MATCH(TRIM($A90),'SLCA Raw'!$M$41:$M$100,0), MATCH(D$33,'SLCA Raw'!$B$38:$K$38,0) ),"") -> 1246.428 | E90: =IFERROR( INDEX('SLCA Raw'!$B$41:$K$100, MATCH(TRIM($A90),'SLCA Raw'!$M$41:$M$100,0), MATCH(E$33,'SLCA Raw'!$B$38:$K$38,0) ),"") -> 1213.985 | F90: =IFERROR( INDEX('SLCA Raw'!$B$41:$K$100, MATCH(TRIM($A90),'SLCA Raw'!$M$41:$M$100,0), MATCH(F$33,'SLCA Raw'!$B$38:$K$38,0) ),"") -> 1197.66 | G90: =IFERROR( INDEX('SLCA Raw'!$B$41:$K$100, MATCH(TRIM($A90),'SLCA Raw'!$M$41:$M$100,0), MATCH(G$33,'SLCA Raw'!$B$38:$K$38,0) ),"") -> 1193.135 | H90: =IFERROR( INDEX('SLCA Raw'!$B$41:$K$100, MATCH(TRIM($A90),'SLCA Raw'!$M$41:$M$100,0), MATCH(H$33,'SLCA Raw'!$B$38:$K$38,0) ),"") -> 1037.458 | I90: =IFERROR( INDEX('SLCA Raw'!$B$41:$K$100, MATCH(TRIM($A90),'SLCA Raw'!$M$41:$M$100,0), MATCH(I$33,'SLCA Raw'!$B$38:$K$38,0) ),"") -> 823.67 | J90: =$I$90 -> 823.67 | K90: =$I$90 -> 823.67 | L90: =$I$90 -> 823.67 | M90: =$I$90 -> 823.67 | N90: =$I$90 -> 823.67
A91: Deferred Income Tax | C91: Deferred Taxes | D91: =IFERROR( INDEX('SLCA Raw'!$B$41:$K$100, MATCH(TRIM($A91),'SLCA Raw'!$M$41:$M$100,0), MATCH(D$33,'SLCA Raw'!$B$38:$K$38,0) ),"") -> 137.239 | E91: =IFERROR( INDEX('SLCA Raw'!$B$41:$K$100, MATCH(TRIM($A91),'SLCA Raw'!$M$41:$M$100,0), MATCH(E$33,'SLCA Raw'!$B$38:$K$38,0) ),"") -> 38.585 | F91: =IFERROR( INDEX('SLCA Raw'!$B$41:$K$100, MATCH(TRIM($A91),'SLCA Raw'!$M$41:$M$100,0), MATCH(F$33,'SLCA Raw'!$B$38:$K$38,0) ),"") -> 49.386 | G91: =IFERROR( INDEX('SLCA Raw'!$B$41:$K$100, MATCH(TRIM($A91),'SLCA Raw'!$M$41:$M$100,0), MATCH(G$33,'SLCA Raw'!$B$38:$K$38,0) ),"") -> 44.774 | H91: =IFERROR( INDEX('SLCA Raw'!$B$41:$K$100, MATCH(TRIM($A91),'SLCA Raw'!$M$41:$M$100,0), MATCH(H$33,'SLCA Raw'!$B$38:$K$38,0) ),"") -> 64.636 | I91: =IFERROR( INDEX('SLCA Raw'!$B$41:$K$100, MATCH(TRIM($A91),'SLCA Raw'!$M$41:$M$100,0), MATCH(I$33,'SLCA Raw'!$B$38:$K$38,0) ),"") -> 100.458 | J91: 100 | K91: 100 | L91: 100 | M91: 100 | N91: 100
A92: Other Liabilities, Total | C92: Other Long-Term Liabilities | D92: =IFERROR( INDEX('SLCA Raw'!$B$41:$K$100, MATCH(TRIM($A92),'SLCA Raw'!$M$41:$M$100,0), MATCH(D$33,'SLCA Raw'!$B$38:$K$38,0) ),"") -> 203.5 | E92: =IFERROR( INDEX('SLCA Raw'!$B$41:$K$100, MATCH(TRIM($A92),'SLCA Raw'!$M$41:$M$100,0), MATCH(E$33,'SLCA Raw'!$B$38:$K$38,0) ),"") -> 248.7 | F92: =IFERROR( INDEX('SLCA Raw'!$B$41:$K$100, MATCH(TRIM($A92),'SLCA Raw'!$M$41:$M$100,0), MATCH(F$33,'SLCA Raw'!$B$38:$K$38,0) ),"") -> 178.2 | G92: =IFERROR( INDEX('SLCA Raw'!$B$41:$K$100, MATCH(TRIM($A92),'SLCA Raw'!$M$41:$M$100,0), MATCH(G$33,'SLCA Raw'!$B$38:$K$38,0) ),"") -> 161.7 | H92: =IFERROR( INDEX('SLCA Raw'!$B$41:$K$100, MATCH(TRIM($A92),'SLCA Raw'!$M$41:$M$100,0), MATCH(H$33,'SLCA Raw'!$B$38:$K$38,0) ),"") -> 135.8 | I92: =IFERROR( INDEX('SLCA Raw'!$B$41:$K$100, MATCH(TRIM($A92),'SLCA Raw'!$M$41:$M$100,0), MATCH(I$33,'SLCA Raw'!$B$38:$K$38,0) ),"") -> 131.1 | J92: =J$35*J$26 -> 171.15696 | K92: =K$35*K$26 -> 176.83097 | L92: =L$35*L$26 -> 182.49904 | M92: =M$35*M$26 -> 188.56896 | N92: =N$35*N$26 -> 195.01506
A93: Minority Interest | C93: Noncontrolling Interest | D93: =IFERROR( INDEX('SLCA Raw'!$B$41:$K$100, MATCH(TRIM($A93),'SLCA Raw'!$M$41:$M$100,0), MATCH(D$33,'SLCA Raw'!$B$38:$K$38,0) ),"") -> 7.484 | E93: =IFERROR( INDEX('SLCA Raw'!$B$41:$K$100, MATCH(TRIM($A93),'SLCA Raw'!$M$41:$M$100,0), MATCH(E$33,'SLCA Raw'!$B$38:$K$38,0) ),"") -> 11.363 | F93: =IFERROR( INDEX('SLCA Raw'!$B$41:$K$100, MATCH(TRIM($A93),'SLCA Raw'!$M$41:$M$100,0), MATCH(F$33,'SLCA Raw'!$B$38:$K$38,0) ),"") -> 11.531 | G93: =IFERROR( INDEX('SLCA Raw'!$B$41:$K$100, MATCH(TRIM($A93),'SLCA Raw'!$M$41:$M$100,0), MATCH(G$33,'SLCA Raw'!$B$38:$K$38,0) ),"") -> 9.868 | H93: =IFERROR( INDEX('SLCA Raw'!$B$41:$K$100, MATCH(TRIM($A93),'SLCA Raw'!$M$41:$M$100,0), MATCH(H$33,'SLCA Raw'!$B$38:$K$38,0) ),"") -> 8.009 | I93: =IFERROR( INDEX('SLCA Raw'!$B$41:$K$100, MATCH(TRIM($A93),'SLCA Raw'!$M$41:$M$100,0), MATCH(I$33,'SLCA Raw'!$B$38:$K$38,0) ),"") -> 6.219 | J93: =I93 -> 6.219 | K93: =J93 -> 6.219 | L93: =K93 -> 6.219 | M93: =L93 -> 6.219 | N93: =M93 -> 6.219
A94: Total Liabilities | C94: Total Liabilities | D94: =IFERROR( INDEX('SLCA Raw'!$B$41:$K$100, MATCH(TRIM($A94),'SLCA Raw'!$M$41:$M$100,0), MATCH(D$33,'SLCA Raw'!$B$38:$K$38,0) ),"") -> 1856.02 | E94: =IFERROR( INDEX('SLCA Raw'!$B$41:$K$100, MATCH(TRIM($A94),'SLCA Raw'!$M$41:$M$100,0), MATCH(E$33,'SLCA Raw'!$B$38:$K$38,0) ),"") -> 1848.017 | F94: =IFERROR( INDEX('SLCA Raw'!$B$41:$K$100, MATCH(TRIM($A94),'SLCA Raw'!$M$41:$M$100,0), MATCH(F$33,'SLCA Raw'!$B$38:$K$38,0) ),"") -> 1631.687 | G94: =IFERROR( INDEX('SLCA Raw'!$B$41:$K$100, MATCH(TRIM($A94),'SLCA Raw'!$M$41:$M$100,0), MATCH(G$33,'SLCA Raw'!$B$38:$K$38,0) ),"") -> 1615.385 | H94: =IFERROR( INDEX('SLCA Raw'!$B$41:$K$100, MATCH(TRIM($A94),'SLCA Raw'!$M$41:$M$100,0), MATCH(H$33,'SLCA Raw'!$B$38:$K$38,0) ),"") -> 1517.895 | I94: =IFERROR( INDEX('SLCA Raw'!$B$41:$K$100, MATCH(TRIM($A94),'SLCA Raw'!$M$41:$M$100,0), MATCH(I$33,'SLCA Raw'!$B$38:$K$38,0) ),"") -> 1247.285 | J94: =J86+J90+J91+J92+J93 -> 1354.3774 | K94: =K86+K90+K91+K92+K93 -> 1364.009 | L94: =L86+L90+L91+L92+L93 -> 1377.6743 | M94: =M86+M90+M91+M92+M93 -> 1393.8652 | N94: =N86+N90+N91+N92+N93 -> 1408.4663
A96: Common Stock | C96: Common Stock | D96: =IFERROR( INDEX('SLCA Raw'!$B$41:$K$100, MATCH(TRIM($A96),'SLCA Raw'!$M$41:$M$100,0), MATCH(D$33,'SLCA Raw'!$B$38:$K$38,0) ),"") -> 0.8 | E96: =IFERROR( INDEX('SLCA Raw'!$B$41:$K$100, MATCH(TRIM($A96),'SLCA Raw'!$M$41:$M$100,0), MATCH(E$33,'SLCA Raw'!$B$38:$K$38,0) ),"") -> 0.8 | F96: =IFERROR( INDEX('SLCA Raw'!$B$41:$K$100, MATCH(TRIM($A96),'SLCA Raw'!$M$41:$M$100,0), MATCH(F$33,'SLCA Raw'!$B$38:$K$38,0) ),"") -> 0.8 | G96: =IFERROR( INDEX('SLCA Raw'!$B$41:$K$100, MATCH(TRIM($A96),'SLCA Raw'!$M$41:$M$100,0), MATCH(G$33,'SLCA Raw'!$B$38:$K$38,0) ),"") -> 0.8 | H96: =IFERROR( INDEX('SLCA Raw'!$B$41:$K$100, MATCH(TRIM($A96),'SLCA Raw'!$M$41:$M$100,0), MATCH(H$33,'SLCA Raw'!$B$38:$K$38,0) ),"") -> 0.9 | I96: =IFERROR( INDEX('SLCA Raw'!$B$41:$K$100, MATCH(TRIM($A96),'SLCA Raw'!$M$41:$M$100,0), MATCH(I$33,'SLCA Raw'!$B$38:$K$38,0) ),"") -> 0.9 | J96: 1 | K96: 1 | L96: 1 | M96: 1 | N96: 1
A97: Additional Paid-In Capital | C97: Additional Paid-In Capital | D97: =IFERROR( INDEX('SLCA Raw'!$B$41:$K$100, MATCH(TRIM($A97),'SLCA Raw'!$M$41:$M$100,0), MATCH(D$33,'SLCA Raw'!$B$38:$K$38,0) ),"") -> 1169.383 | E97: =IFERROR( INDEX('SLCA Raw'!$B$41:$K$100, MATCH(TRIM($A97),'SLCA Raw'!$M$41:$M$100,0), MATCH(E$33,'SLCA Raw'!$B$38:$K$38,0) ),"") -> 1185.116 | F97: =IFERROR( INDEX('SLCA Raw'!$B$41:$K$100, MATCH(TRIM($A97),'SLCA Raw'!$M$41:$M$100,0), MATCH(F$33,'SLCA Raw'!$B$38:$K$38,0) ),"") -> 1200.023 | G97: =IFERROR( INDEX('SLCA Raw'!$B$41:$K$100, MATCH(TRIM($A97),'SLCA Raw'!$M$41:$M$100,0), MATCH(G$33,'SLCA Raw'!$B$38:$K$38,0) ),"") -> 1218.575 | H97: =IFERROR( INDEX('SLCA Raw'!$B$41:$K$100, MATCH(TRIM($A97),'SLCA Raw'!$M$41:$M$100,0), MATCH(H$33,'SLCA Raw'!$B$38:$K$38,0) ),"") -> 1234.834 | I97: =IFERROR( INDEX('SLCA Raw'!$B$41:$K$100, MATCH(TRIM($A97),'SLCA Raw'!$M$41:$M$100,0), MATCH(I$33,'SLCA Raw'!$B$38:$K$38,0) ),"") -> 1249.46 | J97: =I97 -> 1249.46 | K97: =J97 -> 1249.46 | L97: =K97 -> 1249.46 | M97: =L97 -> 1249.46 | N97: =M97 -> 1249.46
A98: Retained Earnings (Accumulated Deficit) | C98: Retained Earnings | D98: =IFERROR( INDEX('SLCA Raw'!$B$41:$K$100, MATCH(TRIM($A98),'SLCA Raw'!$M$41:$M$100,0), MATCH(D$33,'SLCA Raw'!$B$38:$K$38,0) ),"") -> 67.854 | E98: =IFERROR( INDEX('SLCA Raw'!$B$41:$K$100, MATCH(TRIM($A98),'SLCA Raw'!$M$41:$M$100,0), MATCH(E$33,'SLCA Raw'!$B$38:$K$38,0) ),"") -> -279.956 | F98: =IFERROR( INDEX('SLCA Raw'!$B$41:$K$100, MATCH(TRIM($A98),'SLCA Raw'!$M$41:$M$100,0), MATCH(F$33,'SLCA Raw'!$B$38:$K$38,0) ),"") -> -395.496 | G98: =IFERROR( INDEX('SLCA Raw'!$B$41:$K$100, MATCH(TRIM($A98),'SLCA Raw'!$M$41:$M$100,0), MATCH(G$33,'SLCA Raw'!$B$38:$K$38,0) ),"") -> -429.26 | H98: =IFERROR( INDEX('SLCA Raw'!$B$41:$K$100, MATCH(TRIM($A98),'SLCA Raw'!$M$41:$M$100,0), MATCH(H$33,'SLCA Raw'!$B$38:$K$38,0) ),"") -> -351.084 | I98: =IFERROR( INDEX('SLCA Raw'!$B$41:$K$100, MATCH(TRIM($A98),'SLCA Raw'!$M$41:$M$100,0), MATCH(I$33,'SLCA Raw'!$B$38:$K$38,0) ),"") -> -204.159 | J98: =I98+J52 -> -49.5299 | K98: =J98+K52 -> 122.99705 | L98: =K98+L52 -> 311.56056 | M98: =L98+M52 -> 501.16216 | N98: =M98+N52 -> 703.7921
A99: Treasury Stock - Common | C99: Treasury Stock | D99: =IFERROR( INDEX('SLCA Raw'!$B$41:$K$100, MATCH(TRIM($A99),'SLCA Raw'!$M$41:$M$100,0), MATCH(D$33,'SLCA Raw'!$B$38:$K$38,0) ),"") -> -178.215 | E99: =IFERROR( INDEX('SLCA Raw'!$B$41:$K$100, MATCH(TRIM($A99),'SLCA Raw'!$M$41:$M$100,0), MATCH(E$33,'SLCA Raw'!$B$38:$K$38,0) ),"") -> -180.912 | F99: =IFERROR( INDEX('SLCA Raw'!$B$41:$K$100, MATCH(TRIM($A99),'SLCA Raw'!$M$41:$M$100,0), MATCH(F$33,'SLCA Raw'!$B$38:$K$38,0) ),"") -> -181.615 | G99: =IFERROR( INDEX('SLCA Raw'!$B$41:$K$100, MATCH(TRIM($A99),'SLCA Raw'!$M$41:$M$100,0), MATCH(G$33,'SLCA Raw'!$B$38:$K$38,0) ),"") -> -186.294 | H99: =IFERROR( INDEX('SLCA Raw'!$B$41:$K$100, MATCH(TRIM($A99),'SLCA Raw'!$M$41:$M$100,0), MATCH(H$33,'SLCA Raw'!$B$38:$K$38,0) ),"") -> -186.196 | I99: =IFERROR( INDEX('SLCA Raw'!$B$41:$K$100, MATCH(TRIM($A99),'SLCA Raw'!$M$41:$M$100,0), MATCH(I$33,'SLCA Raw'!$B$38:$K$38,0) ),"") -> -196.745 | J99: =I99 -> -196.745 | K99: =J99 -> -196.745 | L99: =K99 -> -196.745 | M99: =L99 -> -196.745 | N99: =M99 -> -196.745
A100: Other Equity, Total | C100: Other Equity | D100: =IFERROR( INDEX('SLCA Raw'!$B$41:$K$100, MATCH(TRIM($A100),'SLCA Raw'!$M$41:$M$100,0), MATCH(D$33,'SLCA Raw'!$B$38:$K$38,0) ),"") -> -15.02 | E100: =IFERROR( INDEX('SLCA Raw'!$B$41:$K$100, MATCH(TRIM($A100),'SLCA Raw'!$M$41:$M$100,0), MATCH(E$33,'SLCA Raw'!$B$38:$K$38,0) ),"") -> -19.854 | F100: =IFERROR( INDEX('SLCA Raw'!$B$41:$K$100, MATCH(TRIM($A100),'SLCA Raw'!$M$41:$M$100,0), MATCH(F$33,'SLCA Raw'!$B$38:$K$38,0) ),"") -> -8.479 | G100: =IFERROR( INDEX('SLCA Raw'!$B$41:$K$100, MATCH(TRIM($A100),'SLCA Raw'!$M$41:$M$100,0), MATCH(G$33,'SLCA Raw'!$B$38:$K$38,0) ),"") -> 0.349 | H100: =IFERROR( INDEX('SLCA Raw'!$B$41:$K$100, MATCH(TRIM($A100),'SLCA Raw'!$M$41:$M$100,0), MATCH(H$33,'SLCA Raw'!$B$38:$K$38,0) ),"") -> -1.723 | I100: =IFERROR( INDEX('SLCA Raw'!$B$41:$K$100, MATCH(TRIM($A100),'SLCA Raw'!$M$41:$M$100,0), MATCH(I$33,'SLCA Raw'!$B$38:$K$38,0) ),"") -> -0.125 | J100: 0 | K100: 0 | L100: 0 | M100: 0 | N100: 0
A101: Total Equity | C101: Total Equity | D101: =IFERROR( INDEX('SLCA Raw'!$B$41:$K$100, MATCH(TRIM($A101),'SLCA Raw'!$M$41:$M$100,0), MATCH(D$33,'SLCA Raw'!$B$38:$K$38,0) ),"") -> 1044.82 | E101: =IFERROR( INDEX('SLCA Raw'!$B$41:$K$100, MATCH(TRIM($A101),'SLCA Raw'!$M$41:$M$100,0), MATCH(E$33,'SLCA Raw'!$B$38:$K$38,0) ),"") -> 705.217 | F101: =IFERROR( INDEX('SLCA Raw'!$B$41:$K$100, MATCH(TRIM($A101),'SLCA Raw'!$M$41:$M$100,0), MATCH(F$33,'SLCA Raw'!$B$38:$K$38,0) ),"") -> 615.26 | G101: =IFERROR( INDEX('SLCA Raw'!$B$41:$K$100, MATCH(TRIM($A101),'SLCA Raw'!$M$41:$M$100,0), MATCH(G$33,'SLCA Raw'!$B$38:$K$38,0) ),"") -> 604.215 | H101: =IFERROR( INDEX('SLCA Raw'!$B$41:$K$100, MATCH(TRIM($A101),'SLCA Raw'!$M$41:$M$100,0), MATCH(H$33,'SLCA Raw'!$B$38:$K$38,0) ),"") -> 696.685 | I101: =IFERROR( INDEX('SLCA Raw'!$B$41:$K$100, MATCH(TRIM($A101),'SLCA Raw'!$M$41:$M$100,0), MATCH(I$33,'SLCA Raw'!$B$38:$K$38,0) ),"") -> 849.308 | J101: =SUM(J96:J100) -> 1004.1851 | K101: =SUM(K96:K100) -> 1176.712 | L101: =SUM(L96:L100) -> 1365.2756 | M101: =SUM(M96:M100) -> 1554.8772 | N101: =SUM(N96:N100) -> 1757.5071
A103: Total Liabilities & Shareholders' Equity | C103: Total Liabilities and Equity | D103: =IFERROR( INDEX('SLCA Raw'!$B$41:$K$100, MATCH(TRIM($A103),'SLCA Raw'!$M$41:$M$100,0), MATCH(D$33,'SLCA Raw'!$B$38:$K$38,0) ),"") -> 2900.84 | E103: =IFERROR( INDEX('SLCA Raw'!$B$41:$K$100, MATCH(TRIM($A103),'SLCA Raw'!$M$41:$M$100,0), MATCH(E$33,'SLCA Raw'!$B$38:$K$38,0) ),"") -> 2553.234 | F103: =IFERROR( INDEX('SLCA Raw'!$B$41:$K$100, MATCH(TRIM($A103),'SLCA Raw'!$M$41:$M$100,0), MATCH(F$33,'SLCA Raw'!$B$38:$K$38,0) ),"") -> 2246.947 | G103: =IFERROR( INDEX('SLCA Raw'!$B$41:$K$100, MATCH(TRIM($A103),'SLCA Raw'!$M$41:$M$100,0), MATCH(G$33,'SLCA Raw'!$B$38:$K$38,0) ),"") -> 2219.6 | H103: =IFERROR( INDEX('SLCA Raw'!$B$41:$K$100, MATCH(TRIM($A103),'SLCA Raw'!$M$41:$M$100,0), MATCH(H$33,'SLCA Raw'!$B$38:$K$38,0) ),"") -> 2214.58 | I103: =IFERROR( INDEX('SLCA Raw'!$B$41:$K$100, MATCH(TRIM($A103),'SLCA Raw'!$M$41:$M$100,0), MATCH(I$33,'SLCA Raw'!$B$38:$K$38,0) ),"") -> 2096.593 | J103: =J$101+J$94 -> 2358.5625 | K103: =K$101+K$94 -> 2540.721 | L103: =L$101+L$94 -> 2742.9499 | M103: =M$101+M$94 -> 2948.7423 | N103: =N$101+N$94 -> 3165.9734
C105: Assets = Liabilities + Equity Check | D105: =D103-D79 -> 0 | E105: =E103-E79 -> 0 | F105: =F103-F79 -> 0 | G105: =G103-G79 -> 0 | H105: =H103-H79 -> 0 | I105: =I103-I79 -> 0 | J105: =J79-J103 -> 0.123 | K105: =K79-K103 -> 0.123 | L105: =L79-L103 -> 0.123 | M105: =M79-M103 -> 0.123 | N105: =N79-N103 -> 0.123
A107: Total Common Shares Outstanding | C107: Common Shares Outstanding | D107: =IFERROR( INDEX('SLCA Raw'!$B$41:$K$100, MATCH(TRIM($A107),'SLCA Raw'!$M$41:$M$100,0), MATCH(D$33,'SLCA Raw'!$B$38:$K$38,0) ),"") -> 73 | E107: =IFERROR( INDEX('SLCA Raw'!$B$41:$K$100, MATCH(TRIM($A107),'SLCA Raw'!$M$41:$M$100,0), MATCH(E$33,'SLCA Raw'!$B$38:$K$38,0) ),"") -> 74 | F107: =IFERROR( INDEX('SLCA Raw'!$B$41:$K$100, MATCH(TRIM($A107),'SLCA Raw'!$M$41:$M$100,0), MATCH(F$33,'SLCA Raw'!$B$38:$K$38,0) ),"") -> 74 | G107: =IFERROR( INDEX('SLCA Raw'!$B$41:$K$100, MATCH(TRIM($A107),'SLCA Raw'!$M$41:$M$100,0), MATCH(G$33,'SLCA Raw'!$B$38:$K$38,0) ),"") -> 75 | H107: =IFERROR( INDEX('SLCA Raw'!$B$41:$K$100, MATCH(TRIM($A107),'SLCA Raw'!$M$41:$M$100,0), MATCH(H$33,'SLCA Raw'!$B$38:$K$38,0) ),"") -> 76 | I107: =IFERROR( INDEX('SLCA Raw'!$B$41:$K$100, MATCH(TRIM($A107),'SLCA Raw'!$M$41:$M$100,0), MATCH(I$33,'SLCA Raw'!$B$38:$K$38,0) ),"") -> 77 | J107: =I107 -> 77 | K107: =J107 -> 77 | L107: =K107 -> 77 | M107: =L107 -> 77 | N107: =M107 -> 77
C109: Cash Flow Statement
J110: Forecast
C111: FYE December | D111: =$D$62 -> 43465 | E111: =EDATE(D111,12) -> 43830 | F111: =EDATE(E111,12) -> 44196 | G111: =EDATE(F111,12) -> 44561 | H111: =EDATE(G111,12) -> 44926 | I111: =EDATE(H111,12) -> 45291 | J111: =EDATE(I111,12) -> 45657 | K111: =EDATE(J111,12) -> 46022 | L111: =EDATE(K111,12) -> 46387 | ... N111: =EDATE(M111,12) -> 47118
D112: USD | E112: USD | F112: USD | G112: USD | H112: USD | I112: USD | J112: USD | K112: USD | L112: USD | M112: USD | N112: USD
A113: Net Income | C113: Net Income | D113: =IFERROR( INDEX('SLCA Raw'!$B$92:$K$111, MATCH(TRIM($A113),'SLCA Raw'!$M$92:$M$111,0), MATCH(D$33,'SLCA Raw'!$B$89:$K$89,0) ),"") -> -200.821 | E113: =IFERROR( INDEX('SLCA Raw'!$B$92:$K$111, MATCH(TRIM($A113),'SLCA Raw'!$M$92:$M$111,0), MATCH(E$33,'SLCA Raw'!$B$89:$K$89,0) ),"") -> -329.757 | F113: =IFERROR( INDEX('SLCA Raw'!$B$92:$K$111, MATCH(TRIM($A113),'SLCA Raw'!$M$92:$M$111,0), MATCH(F$33,'SLCA Raw'!$B$89:$K$89,0) ),"") -> -115.122 | G113: =IFERROR( INDEX('SLCA Raw'!$B$92:$K$111, MATCH(TRIM($A113),'SLCA Raw'!$M$92:$M$111,0), MATCH(G$33,'SLCA Raw'!$B$89:$K$89,0) ),"") -> -34.321 | H113: =IFERROR( INDEX('SLCA Raw'!$B$92:$K$111, MATCH(TRIM($A113),'SLCA Raw'!$M$92:$M$111,0), MATCH(H$33,'SLCA Raw'!$B$89:$K$89,0) ),"") -> 77.84 | I113: =IFERROR( INDEX('SLCA Raw'!$B$92:$K$111, MATCH(TRIM($A113),'SLCA Raw'!$M$92:$M$111,0), MATCH(I$33,'SLCA Raw'!$B$89:$K$89,0) ),"") -> 146.489 | J113: =J$52-J$53 -> 154.6291 | K113: =K$52-K$53 -> 172.52695 | L113: =L$52-L$53 -> 188.56351 | M113: =M$52-M$53 -> 189.60161 | N113: =N$52-N$53 -> 202.62993
C114: D&A | D114: =D140-D139 -> 148.8 | E114: =E140-E139 -> 179.5 | F114: =F140-F139 -> 155.6 | G114: =G140-G139 -> 161.2 | H114: =H140-H139 -> 140.1 | I114: =I140-I139 -> 137.2 | J114: =J41 -> 146.23333 | K114: =K41 -> 146.23333 | L114: =L41 -> 146.23333 | M114: =M41 -> 146.23333 | N114: =N41 -> 146.23333
A115: Operating Net Working Capital | C115: Operating Net Working Capital | D115: =D65+D66+D67+D68-D81-D82-D85 -> 149.769 | E115: =E65+E66+E67+E68-E81-E82-E85 -> 33.016 | F115: =F65+F66+F67+F68-F81-F82-F85 -> 187.282 | G115: =G65+G66+G67+G68-G81-G82-G85 -> 148.978 | H115: =H65+H66+H67+H68-H81-H82-H85 -> 124.102 | I115: =I65+I66+I67+I68-I81-I82-I85 -> 185.479 | J115: =J65+J66+J67+J68-J81-J82-J85 -> 159.33275 | K115: =K65+K66+K67+K68-K81-K82-K85 -> 166.59141 | ... N115: =N65+N66+N67+N68-N81-N82-N85 -> 181.75033 | O115: (see writeup)
A116: Changes in Working Capital | C116: Change in Working Capital | D116: =IFERROR( INDEX('SLCA Raw'!$B$92:$K$111, MATCH(TRIM($A116),'SLCA Raw'!$M$92:$M$111,0), MATCH(D$33,'SLCA Raw'!$B$89:$K$89,0) ),"") -> 135.156 | E116: =IFERROR( INDEX('SLCA Raw'!$B$92:$K$111, MATCH(TRIM($A116),'SLCA Raw'!$M$92:$M$111,0), MATCH(E$33,'SLCA Raw'!$B$89:$K$89,0) ),"") -> 83.298 | F116: =IFERROR( INDEX('SLCA Raw'!$B$92:$K$111, MATCH(TRIM($A116),'SLCA Raw'!$M$92:$M$111,0), MATCH(F$33,'SLCA Raw'!$B$89:$K$89,0) ),"") -> -75.171 | G116: =IFERROR( INDEX('SLCA Raw'!$B$92:$K$111, MATCH(TRIM($A116),'SLCA Raw'!$M$92:$M$111,0), MATCH(G$33,'SLCA Raw'!$B$89:$K$89,0) ),"") -> 30.387 | H116: =IFERROR( INDEX('SLCA Raw'!$B$92:$K$111, MATCH(TRIM($A116),'SLCA Raw'!$M$92:$M$111,0), MATCH(H$33,'SLCA Raw'!$B$89:$K$89,0) ),"") -> 5.981 | I116: =IFERROR( INDEX('SLCA Raw'!$B$92:$K$111, MATCH(TRIM($A116),'SLCA Raw'!$M$92:$M$111,0), MATCH(I$33,'SLCA Raw'!$B$89:$K$89,0) ),"") -> -64.144 | J116: =I115-J115 -> 26.146252 | K116: =J115-K115 -> -7.2586655 | L116: =K115-L115 -> -3.5781303 | M116: =L115-M115 -> -5.5229315 | N116: =M115-N115 -> -6.0578507
C117: Gain(Loss) On Asset sales | D117: =D$48 -> 0 | E117: =E$48 -> 0 | F117: =F$48 -> 0.3 | G117: =G$48 -> 0 | H117: =H$48 -> 0 | I117: =I$48 -> 16.8 | J117: =-J13 -> 0 | K117: =-K13 -> 0 | L117: =-L13 -> 0 | M117: =-M13 -> 0 | N117: =-N13 -> 0
...

Sheet Individual Cash Flow
A1: =HYPERLINK("#'Table of Contents'!A1", "<---------") -> <---------
B3: Individual Cash Flow Schedules($mm)
B4: O&G
C5: actual | I5: predicted
C6: 43465 | D6: =EDATE(C6,12) -> 43830 | E6: =EDATE(D6,12) -> 44196 | F6: =EDATE(E6,12) -> 44561 | G6: =EDATE(F6,12) -> 44926 | H6: =EDATE(G6,12) -> 45291 | I6: =EDATE(H6,12) -> 45657 | J6: =EDATE(I6,12) -> 46022 | K6: =EDATE(J6,12) -> 46387 | ... M6: =EDATE(L6,12) -> 47118
B7: Segment Contribution Margin | C7: ='Revenue Build'!C15/1000 -> 357.846 | D7: ='Revenue Build'!D15/1000 -> 248.594 | E7: ='Revenue Build'!E15/1000 -> 142.041 | F7: ='Revenue Build'!F15/1000 -> 160.052 | G7: ='Revenue Build'!G15/1000 -> 301.837 | H7: ='Revenue Build'!H15/1000 -> 361.998 | I7: ='Revenue Build'!I15/1000 -> 337.11791 | J7: ='Revenue Build'!J15/1000 -> 333.27954 | ... M7: ='Revenue Build'!M15/1000 -> 325.72169
B9: Allocated Operating Expense | C9: ='Revenue Build'!C20*(SUM('SLCA Financials (memo)'!D39:D40)+SUM('SLCA Financials (memo)'!D42:D43)) -> 321.65801 | D9: ='Revenue Build'!D20*(SUM('SLCA Financials (memo)'!E39:E40)+SUM('SLCA Financials (memo)'!E42:E43)) -> 352.70988 | E9: ='Revenue Build'!E20*(SUM('SLCA Financials (memo)'!F39:F40)+SUM('SLCA Financials (memo)'!F42:F43)) -> 128.22305 | F9: ='Revenue Build'!F20*(SUM('SLCA Financials (memo)'!G39:G40)+SUM('SLCA Financials (memo)'!G42:G43)) -> 85.309662 | G9: ='Revenue Build'!G20*(SUM('SLCA Financials (memo)'!H39:H40)+SUM('SLCA Financials (memo)'!H42:H43)) -> 115.01942 | H9: ='Revenue Build'!H20*(SUM('SLCA Financials (memo)'!I39:I40)+SUM('SLCA Financials (memo)'!I42:I43)) -> 105.66916 | I9: ='Revenue Build'!I20*(SUM('SLCA Financials (memo)'!J39:J40)+SUM('SLCA Financials (memo)'!J42:J43)) -> 122.52395 | J9: ='Revenue Build'!J20*(SUM('SLCA Financials (memo)'!K39:K40)+SUM('SLCA Financials (memo)'!K42:K43)) -> 126.22417 | ... M9: ='Revenue Build'!M20*(SUM('SLCA Financials (memo)'!N39:N40)+SUM('SLCA Financials (memo)'!N42:N43)) -> 139.10409 | N9: (read writeup)
B11: EBITDA | C11: =C7-C9 -> 36.187992 | D11: =D7-D9 -> -104.11588 | E11: =E7-E9 -> 13.817945 | F11: =F7-F9 -> 74.742338 | G11: =G7-G9 -> 186.81758 | H11: =H7-H9 -> 256.32884 | I11: =I7-I9 -> 214.59396 | J11: =J7-J9 -> 207.05537 | ... M11: =M7-M9 -> 186.6176
B13: D&A | C13: 102.7 | D13: 123.8 | E13: 107.3 | F13: 111.2 | G13: 96.7 | H13: 94.7 | I13: =AVERAGE($F$13:$H$13) -> 100.86667 | J13: =AVERAGE($F$13:$H$13) -> 100.86667 | K13: =AVERAGE($F$13:$H$13) -> 100.86667 | L13: =AVERAGE($F$13:$H$13) -> 100.86667 | M13: =AVERAGE($F$13:$H$13) -> 100.86667 | N13: (read writeup)
B15: EBIT | C15: =C11-C13 -> -66.512008 | D15: =D11-D13 -> -227.91588 | E15: =E11-E13 -> -93.482055 | F15: =F11-F13 -> -36.457662 | G15: =G11-G13 -> 90.117579 | H15: =H11-H13 -> 161.62884 | I15: =I11-I13 -> 113.7273 | J15: =J11-J13 -> 106.1887 | ... M15: =M11-M13 -> 85.750934
B17: Less: Run Rate Adjustments
B18: Less: Seperation Costs
B20: Less: Taxes | C20: =MAX(0,C15*'SLCA Financials (memo)'!D28) -> 0 | D20: =MAX(0,D15*'SLCA Financials (memo)'!E28) -> 0 | E20: =MAX(0,E15*'SLCA Financials (memo)'!F28) -> 0 | F20: =MAX(0,F15*'SLCA Financials (memo)'!G28) -> 0 | G20: =MAX(0,G15*'SLCA Financials (memo)'!H28) -> 23.881159 | H20: =MAX(0,H15*'SLCA Financials (memo)'!I28) -> 42.831644 | I20: =MAX(0,I15*'SLCA Financials (memo)'!J28) -> 30.137734 | J20: =MAX(0,J15*'SLCA Financials (memo)'!K28) -> 28.140007 | ... M20: =MAX(0,M15*'SLCA Financials (memo)'!N28) -> 22.723998
B21: Plus: D&A | C21: =C13 -> 102.7 | D21: =D13 -> 123.8 | E21: =E13 -> 107.3 | F21: =F13 -> 111.2 | G21: =G13 -> 96.7 | H21: =H13 -> 94.7 | I21: =I13 -> 100.86667 | J21: =J13 -> 100.86667 | ... M21: =M13 -> 100.86667
B22: Less: Capex | C22: 150.4 | D22: 52.4 | E22: 15.3 | F22: 13.4 | G22: 23.5 | H22: 28.8 | I22: =CHOOSE('Main Page & Assumptions'!$D$5,'Main Page & Assumptions'!E17,'Main Page & Assumptions'!J17,'Main Page & Assumptions'!O17)*'Revenue Build'!I7*('Main Page & Assumptions'!$D$22)/1000 -> 40.115602 | J22: =CHOOSE('Main Page & Assumptions'!$D$5,'Main Page & Assumptions'!F17,'Main Page & Assumptions'!K17,'Main Page & Assumptions'!P17)*'Revenue Build'!J7*('Main Page & Assumptions'!$D$22)/1000 -> 41.445471 | K22: =CHOOSE('Main Page & Assumptions'!$D$5,'Main Page & Assumptions'!G17,'Main Page & Assumptions'!L17,'Main Page & Assumptions'!Q17)*'Revenue Build'!K7*('Main Page & Assumptions'!$D$22)/1000 -> 42.773949 | L22: =CHOOSE('Main Page & Assumptions'!$D$5,'Main Page & Assumptions'!H17,'Main Page & Assumptions'!M17,'Main Page & Assumptions'!R17)*'Revenue Build'!L7*('Main Page & Assumptions'!$D$22)/1000 -> 44.196611 | M22: =CHOOSE('Main Page & Assumptions'!$D$5,'Main Page & Assumptions'!I17,'Main Page & Assumptions'!N17,'Main Page & Assumptions'!S17)*'Revenue Build'!M7*('Main Page & Assumptions'!$D$22)/1000 -> 45.707442 | N22: (read writeup)
B23: NWC | C23: 119.5 | D23: 34.9 | E23: 92.9 | F23: 82.5 | G23: 88.6 | H23: 120.3 | I23: =0.00012*'Revenue Build'!I12 -> 122.92081 | J23: =0.00012*'Revenue Build'!J12 -> 126.63302 | K23: =0.00012*'Revenue Build'!K12 -> 130.45733 | L23: =0.00012*'Revenue Build'!L12 -> 134.79634 | M23: =0.00012*'Revenue Build'!M12 -> 139.55465 | N23: (read writeup)
B24: Less: Change NWC | D24: =D23-C23 -> -84.6 | E24: =E23-D23 -> 58 | F24: =F23-E23 -> -10.4 | G24: =G23-F23 -> 6.1 | H24: =H23-G23 -> 31.7 | I24: =I23-H23 -> 2.6208069 | J24: =J23-I23 -> 3.7122084 | K24: =K23-J23 -> 3.8243171 | ... M24: =M23-L23 -> 4.7583109
B26: UFCF | D26: =D15-D20-D22-D24 -> -195.71588 | E26: =E15-E20-E22-E24 -> -166.78205 | F26: =F15-F20-F22-F24 -> -39.457662 | G26: =G15-G20-G22-G24 -> 36.636421 | H26: =H15-H20-H22-H24 -> 58.2972 | I26: =I15-I20-I22-I24+I21 -> 141.71982 | J26: =J15-J20-J22-J24+J21 -> 133.75768 | K26: =K15-K20-K22-K24+K21 -> 126.0875 | L26: =L15-L20-L22-L24+L21 -> 119.33728 | M26: =M15-M20-M22-M24+M21 -> 113.42785
B28: ISP
C29: actual | I29: predicted
C30: 43465 | D30: =EDATE(C30,12) -> 43830 | E30: =EDATE(D30,12) -> 44196 | F30: =EDATE(E30,12) -> 44561 | G30: =EDATE(F30,12) -> 44926 | H30: =EDATE(G30,12) -> 45291 | I30: =EDATE(H30,12) -> 45657 | J30: =EDATE(I30,12) -> 46022 | K30: =EDATE(J30,12) -> 46387 | ... M30: =EDATE(L30,12) -> 47118
B31: Segment Contribution Margin | C31: ='Revenue Build'!C37/1000 -> 155.084 | D31: ='Revenue Build'!D37/1000 -> 178.215 | E31: ='Revenue Build'!E37/1000 -> 159.176 | F31: ='Revenue Build'!F37/1000 -> 168.499 | G31: ='Revenue Build'!G37/1000 -> 170.28 | H31: ='Revenue Build'!H37/1000 -> 187.665 | I31: ='Revenue Build'!I37/1000 -> 217.97412 | J31: ='Revenue Build'!J37/1000 -> 222.64729 | ... M31: ='Revenue Build'!M37/1000 -> 233.39281
B33: Allocated Operating Expense | C33: =(1-'Revenue Build'!C20)*(SUM('SLCA Financials (memo)'!D39:D40)+SUM('SLCA Financials (memo)'!D42:D43)) -> 107.21299 | D33: =(1-'Revenue Build'!D20)*(SUM('SLCA Financials (memo)'!E39:E40)+SUM('SLCA Financials (memo)'!E42:E43)) -> 161.93812 | E33: =(1-'Revenue Build'!E20)*(SUM('SLCA Financials (memo)'!F39:F40)+SUM('SLCA Financials (memo)'!F42:F43)) -> 133.19595 | F33: =(1-'Revenue Build'!F20)*(SUM('SLCA Financials (memo)'!G39:G40)+SUM('SLCA Financials (memo)'!G42:G43)) -> 67.703338 | G33: =(1-'Revenue Build'!G20)*(SUM('SLCA Financials (memo)'!H39:H40)+SUM('SLCA Financials (memo)'!H42:H43)) -> 67.394579 | H33: =(1-'Revenue Build'!H20)*(SUM('SLCA Financials (memo)'!I39:I40)+SUM('SLCA Financials (memo)'!I42:I43)) -> 59.275844 | I33: =(1-'Revenue Build'!I20)*(SUM('SLCA Financials (memo)'!J39:J40)+SUM('SLCA Financials (memo)'!J42:J43)) -> 69.409266 | J33: =(1-'Revenue Build'!J20)*(SUM('SLCA Financials (memo)'!K39:K40)+SUM('SLCA Financials (memo)'!K42:K43)) -> 72.071805 | ... M33: =(1-'Revenue Build'!M20)*(SUM('SLCA Financials (memo)'!N39:N40)+SUM('SLCA Financials (memo)'!N42:N43)) -> 79.583295
B34: Less: Run Rate Adjustments | I34: ='ISP Carve Out Costs'!C12 -> 0.7 | J34: ='ISP Carve Out Costs'!D12 -> 0.7 | K34: ='ISP Carve Out Costs'!E12 -> 0.7 | L34: ='ISP Carve Out Costs'!F12 -> 0.7 | M34: ='ISP Carve Out Costs'!G12 -> 0.7
B35: Less: Seperation Costs | I35: ='ISP Carve Out Costs'!C25 -> 4 | J35: ='ISP Carve Out Costs'!D25 -> 1 | K35: ='ISP Carve Out Costs'!E25 -> 0 | L35: ='ISP Carve Out Costs'!F25 -> 0 | M35: ='ISP Carve Out Costs'!G25 -> 0
B37: EBITDA | C37: =C31-C33 -> 47.871008 | D37: =D31-D33 -> 16.276884 | E37: =E31-E33 -> 25.980055 | F37: =F31-F33 -> 100.79566 | G37: =G31-G33 -> 102.88542 | H37: =H31-H33 -> 128.38916 | I37: =I31-I33-SUM(I34:I35) -> 143.86485 | J37: =J31-J33-SUM(J34:J35) -> 148.87549 | K37: =K31-K33-SUM(K34:K35) -> 151.33485 | L37: =L31-L33-SUM(L34:L35) -> 152.36827 | M37: =M31-M33-SUM(M34:M35) -> 153.10951
B39: D&A | C39: 46.1 | D39: 55.6 | E39: 48.2 | F39: 50 | G39: 43.5 | H39: 42.6 | I39: =AVERAGE($F$39:$H$39) -> 45.366667 | J39: =AVERAGE($F$39:$H$39) -> 45.366667 | K39: =AVERAGE($F$39:$H$39) -> 45.366667 | L39: =AVERAGE($F$39:$H$39) -> 45.366667 | M39: =AVERAGE($F$39:$H$39) -> 45.366667
B41: EBIT | C41: =C37-C39 -> 1.7710083 | D41: =D37-D39 -> -39.323116 | E41: =E37-E39 -> -22.219945 | F41: =F37-F39 -> 50.795662 | G41: =G37-G39 -> 59.385421 | H41: =H37-H39 -> 85.789156 | I41: =I37-I39 -> 98.498188 | J41: =J37-J39 -> 103.50882 | ... M41: =M37-M39 -> 107.74284
B43: Less: Taxes | C43: =MAX(0,C41*'SLCA Financials (memo)'!D28) -> 0.4693172 | D43: =MAX(0,D41*'SLCA Financials (memo)'!E28) -> 0 | E43: =MAX(0,E41*'SLCA Financials (memo)'!F28) -> 0 | F43: =MAX(0,F41*'SLCA Financials (memo)'!G28) -> 13.460851 | G43: =MAX(0,G41*'SLCA Financials (memo)'!H28) -> 15.737136 | H43: =MAX(0,H41*'SLCA Financials (memo)'!I28) -> 22.734126 | I43: =MAX(0,I41*'SLCA Financials (memo)'!J28) -> 26.10202 | J43: =MAX(0,J41*'SLCA Financials (memo)'!K28) -> 27.429837 | ... M43: =MAX(0,M41*'SLCA Financials (memo)'!N28) -> 28.551854
B44: Plus D&A | C44: =C39 -> 46.1 | D44: =D39 -> 55.6 | E44: =E39 -> 48.2 | F44: =F39 -> 50 | G44: =G39 -> 43.5 | H44: =H39 -> 42.6 | I44: =I39 -> 45.366667 | J44: =J39 -> 45.366667 | ... M44: =M39 -> 45.366667
B45: Less: Capex | C45: 189.4 | D45: 66 | E45: 19.2 | F45: 16.9 | G45: 29.6 | H45: 36.3 | I45: =CHOOSE('Main Page & Assumptions'!$D$5,'Main Page & Assumptions'!E17,'Main Page & Assumptions'!J17,'Main Page & Assumptions'!O17)*'Revenue Build'!I7*(1-'Main Page & Assumptions'!$D$22)/1000 -> 40.115602 | J45: =CHOOSE('Main Page & Assumptions'!$D$5,'Main Page & Assumptions'!F17,'Main Page & Assumptions'!K17,'Main Page & Assumptions'!P17)*'Revenue Build'!J7*(1-'Main Page & Assumptions'!$D$22)/1000 -> 41.445471 | K45: =CHOOSE('Main Page & Assumptions'!$D$5,'Main Page & Assumptions'!G17,'Main Page & Assumptions'!L17,'Main Page & Assumptions'!Q17)*'Revenue Build'!K7*(1-'Main Page & Assumptions'!$D$22)/1000 -> 42.773949 | L45: =CHOOSE('Main Page & Assumptions'!$D$5,'Main Page & Assumptions'!H17,'Main Page & Assumptions'!M17,'Main Page & Assumptions'!R17)*'Revenue Build'!L7*(1-'Main Page & Assumptions'!$D$22)/1000 -> 44.196611 | M45: =CHOOSE('Main Page & Assumptions'!$D$5,'Main Page & Assumptions'!I17,'Main Page & Assumptions'!N17,'Main Page & Assumptions'!S17)*'Revenue Build'!M7*(1-'Main Page & Assumptions'!$D$22)/1000 -> 45.707442
B46: NWC | C46: 41.7 | D46: 23.6 | E46: 96.8 | F46: 68.3 | G46: 51.5 | H46: 67.5 | I46: =0.00012*'Revenue Build'!I34 -> 69.634084 | J46: =0.00012*'Revenue Build'!J34 -> 72.305248 | K46: =0.00012*'Revenue Build'!K34 -> 74.857623 | L46: =0.00012*'Revenue Build'!L34 -> 77.347388 | M46: =0.00012*'Revenue Build'!M34 -> 79.841067
B47: Less: Change NWC | D47: =D46-C46 -> -18.1 | E47: =E46-D46 -> 73.2 | F47: =F46-E46 -> -28.5 | G47: =G46-F46 -> -16.8 | H47: =H46-G46 -> 16 | I47: =I46-H46 -> 2.1340844 | J47: =J46-I46 -> 2.6711635 | K47: =K46-J46 -> 2.5523752 | ... M47: =M46-L46 -> 2.4936798
B49: UFCF | D49: =D41-D43-D45-D47 -> -87.223116 | E49: =E41-E43-E45-E47 -> -114.61995 | F49: =F41-F43-F45-F47 -> 48.934812 | G49: =G41-G43-G45-G47 -> 30.848284 | H49: =H41-H43-H45-H47 -> 10.75503 | I49: =I41-I43-I45-I47+I44 -> 75.513148 | J49: =J41-J43-J45-J47+J44 -> 77.329015 | K49: =K41-K43-K45-K47+K44 -> 77.926959 | L49: =L41-L43-L45-L47+L44 -> 77.326473 | M49: =M41-M43-M45-M47+M44 -> 76.356536
P57: Year | Q57: 2018 | R57: 2019 | S57: 2020 | T57: 2021 | U57: 2022 | V57: 2023
P58: O&G D&A | Q58: 102.7 | R58: 123.8 | S58: 107.3 | T58: 111.2 | U58: 96.7 | V58: 94.7
P59: ISP D&A | Q59: 46.1 | R59: 55.6 | S59: 48.2 | T59: 50 | U59: 43.5 | V59: 42.6
P61: Total D&A | Q61: ='SLCA Financials (memo)'!D41 -> 148.8 | R61: ='SLCA Financials (memo)'!E41 -> 179.4 | S61: ='SLCA Financials (memo)'!F41 -> 155.6 | T61: ='SLCA Financials (memo)'!G41 -> 161.1 | U61: ='SLCA Financials (memo)'!H41 -> 140.2 | V61: ='SLCA Financials (memo)'!I41 -> 137.3
P63: O&G Capex | Q63: 150.4 | R63: 52.4 | S63: 15.3 | T63: 13.4 | U63: 23.5 | V63: 28.8
P64: ISP Capex | Q64: 189.4 | R64: 66 | S64: 19.2 | T64: 16.9 | U64: 29.6 | V64: 36.3
P65: Total Capex | Q65: ='SLCA Financials (memo)'!D121*-1 -> 349.861 | R65: ='SLCA Financials (memo)'!E121*-1 -> 122.289 | S65: ='SLCA Financials (memo)'!F121*-1 -> 34.917 | T65: ='SLCA Financials (memo)'!G121*-1 -> 30.517 | U65: ='SLCA Financials (memo)'!H121*-1 -> 53.562 | V65: ='SLCA Financials (memo)'!I121*-1 -> 65.47
P66: O&G Op. NWC | Q66: 119.5 | R66: 34.9 | S66: 92.9 | T66: 82.5 | U66: 88.6 | V66: 120.3
P67: ISP Op. NWC | Q67: 41.7 | R67: 23.6 | S67: 96.8 | T67: 68.3 | U67: 51.5 | V67: 67.5
P69: Total Op. NWC | Q69: ='SLCA Financials (memo)'!D115 -> 149.769 | R69: 58.4 | S69: 189.7 | T69: 150.8 | U69: 140 | V69: 187.9
Q77: =V63/V65 -> 0.43989614

Sheet Carveout DCFs
A1: =HYPERLINK("#'Table of Contents'!A1", "<---------") -> <---------
B2: O&G
C3: 2024 | D3: 2025 | E3: 2026 | F3: 2027 | G3: 2028
B5: Discount Rate | C5: ='Main Page & Assumptions'!$D$26 -> 0.135 | D5: ='Main Page & Assumptions'!$D$26 -> 0.135 | E5: ='Main Page & Assumptions'!$D$26 -> 0.135 | F5: ='Main Page & Assumptions'!$D$26 -> 0.135 | G5: ='Main Page & Assumptions'!$D$26 -> 0.135
B7: UFCF | C7: ='Individual Cash Flow'!I26 -> 141.71982 | D7: ='Individual Cash Flow'!J26 -> 133.75768 | E7: ='Individual Cash Flow'!K26 -> 126.0875 | F7: ='Individual Cash Flow'!L26 -> 119.33728 | G7: ='Individual Cash Flow'!M26 -> 113.42785
B8: Discount Period | C8: 1 | D8: 2 | E8: 3 | F8: 4 | G8: 5
B10: Present Value of Free Cash Flow | C10: =C7/(1+C5)^C8 -> 124.86328 | D10: =D7/(1+D5)^D8 -> 103.831 | E10: =E7/(1+E5)^E8 -> 86.235178 | F10: =F7/(1+F5)^F8 -> 71.910562 | G10: =G7/(1+G5)^G8 -> 60.219951
B12: Combined Cash Flows | C12: =SUM(C10:G10) -> 447.05997
B13: Selected Exit Multiple | C13: =CHOOSE('Main Page & Assumptions'!D5,'Main Page & Assumptions'!D33,'Main Page & Assumptions'!D32,'Main Page & Assumptions'!D34) -> 3.3
B14: Terminal Value | C14: ='Individual Cash Flow'!H11*C13 -> 845.88519
B15: Present Value of Terminal Value | C15: =C14/(1+C5)^G8 -> 449.08868
B17: Warranted Enterprise Value | C17: =C15+C12 -> 896.14865
B18: Net Debt | C18: ='Main Page & Assumptions'!D44*('Individual Cash Flow'!H11/('Individual Cash Flow'!H11+'Individual Cash Flow'!H37)) -> 414.42444
B19: Equity Value | C19: =C17-C18 -> 481.72421
B22: ISP
C23: 2024 | D23: 2025 | E23: 2026 | F23: 2027 | G23: 2028
B25: Discount Rate | C25: ='Main Page & Assumptions'!$C$26 -> 0.11 | D25: ='Main Page & Assumptions'!$C$26 -> 0.11 | E25: ='Main Page & Assumptions'!$C$26 -> 0.11 | F25: ='Main Page & Assumptions'!$C$26 -> 0.11 | G25: ='Main Page & Assumptions'!$C$26 -> 0.11
B27: UFCF | C27: ='Individual Cash Flow'!I49 -> 75.513148 | D27: ='Individual Cash Flow'!J49 -> 77.329015 | E27: ='Individual Cash Flow'!K49 -> 77.926959 | F27: ='Individual Cash Flow'!L49 -> 77.326473 | G27: ='Individual Cash Flow'!M49 -> 76.356536
B28: Discount Period | C28: 1 | D28: 2 | E28: 3 | F28: 4 | G28: 5
B30: Present Value of Free Cash Flow | C30: =C27/(1+C25)^C28 -> 68.029863 | D30: =D27/(1+D25)^D28 -> 62.761963 | E30: =E27/(1+E25)^E28 -> 56.979521 | F30: =F27/(1+F25)^F28 -> 50.937343 | G30: =G27/(1+G25)^G28 -> 45.313888
B32: Combined Cash Flows | C32: =SUM(C30:G30) -> 284.02258
B33: Selected Exit Multiple | C33: =CHOOSE('Main Page & Assumptions'!D5,'Main Page & Assumptions'!C33,'Main Page & Assumptions'!C32,'Main Page & Assumptions'!C34) -> 7.7
B34: Terminal Value | C34: ='Individual Cash Flow'!I37*C33 -> 1107.7594
B35: Present Value of Terminal Value | C35: =C34/(1+C25)^G28 -> 657.40127
B37: Warranted Enterprise Value | C37: =C35+C32 -> 941.42385
B38: Net Debt | C38: ='Main Page & Assumptions'!D44*('Individual Cash Flow'!H37/('Individual Cash Flow'!H11+'Individual Cash Flow'!H37)) -> 207.57556
B39: Equity Value | C39: =C37-C38 -> 733.84829

Sheet Standalone DCF
A1: =HYPERLINK("#'Table of Contents'!A1", "<---------") -> <---------
B3: SLCA DCF
C4: Actual | I4: Forecast
C5: 43465 | D5: 43830 | E5: 44196 | F5: 44561 | G5: 44926 | H5: 45291 | I5: 45657 | J5: 46022 | K5: 46387 | L5: 46752 | M5: 47118
B7: Discount Rate | C7: ='Main Page & Assumptions'!D28 -> 0.125 | D7: =C7 -> 0.125 | E7: =D7 -> 0.125 | F7: =E7 -> 0.125 | G7: =F7 -> 0.125 | H7: =G7 -> 0.125 | I7: =H7 -> 0.125 | J7: =I7 -> 0.125 | K7: =J7 -> 0.125 | ... M7: =L7 -> 0.125
B9: EBITDA | C9: ='SLCA Financials (memo)'!D140 -> 369.7 | D9: ='SLCA Financials (memo)'!E140 -> 239.2 | E9: ='SLCA Financials (memo)'!F140 -> 161.7 | F9: ='SLCA Financials (memo)'!G140 -> 201 | G9: ='SLCA Financials (memo)'!H140 -> 327.7 | H9: ='SLCA Financials (memo)'!I140 -> 412.6 | I9: ='SLCA Financials (memo)'!J140 -> 343.01306 | J9: ='SLCA Financials (memo)'!K140 -> 367.36388 | ... M9: ='SLCA Financials (memo)'!N140 -> 408.32032
B11: D&A | C11: ='SLCA Financials (memo)'!D41 -> 148.8 | D11: ='SLCA Financials (memo)'!E41 -> 179.4 | E11: ='SLCA Financials (memo)'!F41 -> 155.6 | F11: ='SLCA Financials (memo)'!G41 -> 161.1 | G11: ='SLCA Financials (memo)'!H41 -> 140.2 | H11: ='SLCA Financials (memo)'!I41 -> 137.3 | I11: ='SLCA Financials (memo)'!J41 -> 146.23333 | J11: ='SLCA Financials (memo)'!K41 -> 146.23333 | ... M11: ='SLCA Financials (memo)'!N41 -> 146.23333
B13: EBIT | C13: =C9-C11 -> 220.9 | D13: =D9-D11 -> 59.8 | E13: =E9-E11 -> 6.1 | F13: =F9-F11 -> 39.9 | G13: =G9-G11 -> 187.5 | H13: =H9-H11 -> 275.3 | I13: =I9-I11 -> 196.77973 | J13: =J9-J11 -> 221.13054 | ... M13: =M9-M11 -> 262.08698
B15: Less: Taxes | C15: =C13*('SLCA Financials (memo)'!D28) -> 58.5385 | D15: =D13*('SLCA Financials (memo)'!E28) -> 15.847 | E15: =E13*('SLCA Financials (memo)'!F28) -> 1.6165 | F15: =F13*('SLCA Financials (memo)'!G28) -> 10.5735 | G15: =G13*('SLCA Financials (memo)'!H28) -> 49.6875 | H15: =H13*('SLCA Financials (memo)'!I28) -> 72.9545 | I15: =I13*('SLCA Financials (memo)'!J28) -> 52.146628 | J15: =J13*('SLCA Financials (memo)'!K28) -> 58.599594 | ... M15: =M13*('SLCA Financials (memo)'!N28) -> 69.453051
B16: Plus: D&A | C16: =C11 -> 148.8 | D16: =D11 -> 179.4 | E16: =E11 -> 155.6 | F16: =F11 -> 161.1 | G16: =G11 -> 140.2 | H16: =H11 -> 137.3 | I16: =I11 -> 146.23333 | J16: =J11 -> 146.23333 | ... M16: =M11 -> 146.23333
B17: Less: Capex | C17: ='SLCA Financials (memo)'!D121*-1 -> 349.861 | D17: ='SLCA Financials (memo)'!E121*-1 -> 122.289 | E17: ='SLCA Financials (memo)'!F121*-1 -> 34.917 | F17: ='SLCA Financials (memo)'!G121*-1 -> 30.517 | G17: ='SLCA Financials (memo)'!H121*-1 -> 53.562 | H17: ='SLCA Financials (memo)'!I121*-1 -> 65.47 | I17: ='SLCA Financials (memo)'!J121*-1 -> 80.231205 | J17: ='SLCA Financials (memo)'!K121*-1 -> 82.890943 | ... M17: ='SLCA Financials (memo)'!N121*-1 -> 91.414884
B18: NWC | C18: ='SLCA Financials (memo)'!D115 -> 149.769 | D18: ='SLCA Financials (memo)'!E115 -> 33.016 | E18: ='SLCA Financials (memo)'!F115 -> 187.282 | F18: ='SLCA Financials (memo)'!G115 -> 148.978 | G18: ='SLCA Financials (memo)'!H115 -> 124.102 | H18: ='SLCA Financials (memo)'!I115 -> 185.479 | I18: ='SLCA Financials (memo)'!J115 -> 159.33275 | J18: ='SLCA Financials (memo)'!K115 -> 166.59141 | ... M18: ='SLCA Financials (memo)'!N115 -> 181.75033
B19: Less: Change NWC | C19: ='SLCA Financials (memo)'!D116 -> 135.156 | D19: ='SLCA Financials (memo)'!E116 -> 83.298 | E19: ='SLCA Financials (memo)'!F116 -> -75.171 | F19: ='SLCA Financials (memo)'!G116 -> 30.387 | G19: ='SLCA Financials (memo)'!H116 -> 5.981 | H19: ='SLCA Financials (memo)'!I116 -> -64.144 | I19: ='SLCA Financials (memo)'!J116 -> 26.146252 | J19: ='SLCA Financials (memo)'!K116 -> -7.2586655 | ... M19: ='SLCA Financials (memo)'!N116 -> -6.0578507
B21: UFCF | D21: =D13-D15+D16-D17-D19 -> 17.766 | E21: =E13-E15+E16-E17-E19 -> 200.3375 | F21: =F13-F15+F16-F17-F19 -> 129.5225 | G21: =G13-G15+G16-G17-G19 -> 218.4695 | H21: =H13-H15+H16-H17-H19 -> 338.3195 | I21: =I13-I15+I16-I17-I19 -> 184.48898 | J21: =J13-J15+J16-J17-J19 -> 233.132 | K21: =K13-K15+K16-K17-K19 -> 242.83107 | ... M21: =M13-M15+M16-M17-M19 -> 253.51023
B23: Discount Period | I23: 1 | J23: 2 | K23: 3 | L23: 4 | M23: 5
B24: PV of Free Cash Flow | I24: =I21/(1+I7)^I23 -> 163.9902 | J24: =J21/(1+J7)^J23 -> 184.20307 | K24: =K21/(1+K7)^K23 -> 170.54802 | L24: =L21/(1+L7)^L23 -> 151.68413 | M24: =M21/(1+M7)^M23 -> 140.68017
B27: Combined Cash Flows | C27: =SUM(I24:M24) -> 811.10559
B28: Selected Exit Multiple | C28: =CHOOSE('Main Page & Assumptions'!$D$5,'Main Page & Assumptions'!$D$37,'Main Page & Assumptions'!$D$36,'Main Page & Assumptions'!$D$38) -> 4.5
B29: Terminal Value | C29: =C28*M9 -> 1837.4414
B30: Present Value of Terminal Value | C30: =C29/(1+M7)^M23 -> 1019.6495
B32: Warraned Enterprise Value | C32: =C30+C27 -> 1830.755
B33: Minus Net Debt | C33: ='Main Page & Assumptions'!D44 -> 622
B34: Equity Value | C34: =C32-C33 -> 1208.755
B35: Diluted Shares | C35: 79
B36: Implied Share Price | C36: =C34/C35 -> 15.300697

Sheet Public Comps
A1: =HYPERLINK("#'Table of Contents'!A1", "<---------") -> <---------
B3: ISP Comps
B4: Company | C4: Enterprise Value | D4: Ownership Status | E4: EV / EBITDA | F4: EBITDA | G4: Website | H4: Ticker | I4: Revenue
B5: United States Lime & Minerals | C5: 2622.61 | D5: Publicly Held | E5: =C5/F5 -> 13.231472 | F5: 198.21 | G5: www.uslm.com | H5: USLM | I5: 376.92
B6: Orion (Senningerberg) | C6: 1337.06 | D6: Publicly Held | E6: =C6/F6 -> 10.214362 | F6: 130.9 | G6: www.orioncarbons.com | H6: OEC | I6: 1823
B7: Oil Dri Corporation Of America | C7: 1064.77 | D7: Publicly Held | E7: =C7/F7 -> 11.765414 | F7: 90.5 | G7: www.oildri.com | H7: ODC | I7: 489.76
B8: Ecovyst | C8: 1636.25 | D8: Publicly Held | E8: =C8/F8 -> 10.308385 | F8: 158.73 | G8: www.ecovyst.com | H8: ECVT | I8: 869.25
B9: Compass Minerals International | C9: 1957.36 | D9: Publicly Held | E9: =C9/F9 -> 9.1124767 | F9: 214.8 | G9: www.compassminerals.com | H9: CMP | I9: 1292.1
B10: AdvanSix | C10: 944.73 | D10: Publicly Held | E10: =C10/F10 -> 13.048757 | F10: 72.4 | G10: www.advansix.com | H10: ASIX | I10: 1559.89
B15: Disregarded Pulled Comps:
B16: Kronos Worldwide | C16: 1324.09 | D16: Publicly Held | E16: =C16/F16 -> 49.222677 | F16: 26.9 | G16: www.kronosww.com | H16: KRO | I16: 1943.1
B17: Martin Marietta | C17: 40045.47 | D17: Publicly Held | E17: =C17/F17 -> 19.20646 | F17: 2085 | G17: www.martinmarietta.com | H17: MLM | I17: 6688
B18: Vulcan Materials | C18: 43248.99 | D18: Publicly Held | E18: =C18/F18 -> 18.412444 | F18: 2348.9 | G18: www.vulcanmaterials.com | H18: VMC | I18: 8115.8
B19: Ingevity | C19: 3745.7 | D19: Publicly Held | E19: =C19/F19 -> 18.506423 | F19: 202.4 | G19: www.ingevity.com | H19: NGVT | I19: 1160.3
B20: Hawkins | C20: 3228.34 | D20: Publicly Held | E20: =C20/F20 -> 18.461371 | F20: 174.87 | G20: www.hawkinsinc.com | H20: HWKN | I20: 1106.1
B22: O&G Comps
B23: Company | C23: Enterprise Value | D23: Ownership Status | E23: EV / EBITDA | F23: EBITDA | G23: Website | H23: Ticker | I23: Revenue
B24: Source Energy Services | C24: 333.72 | D24: Publicly Held | E24: =C24/F24 -> 5.7787013 | F24: 57.75 | G24: www.sourceenergyservices.com | H24: SHLE | I24: 424.82
B25: Smart Sand | C25: 234.77 | D25: Publicly Held | E25: =C25/F25 -> 5.9798777 | F25: 39.26 | G25: www.smartsand.com | H25: SND | I25: 386.99
B26: Select Water Solutions | C26: 2842.02 | D26: Publicly Held | E26: =C26/F26 -> 11.221305 | F26: 253.27 | G26: www.selectwater.com | H26: WTTR | I26: 1430.51
B27: Liberty Energy | C27: 5197.99 | D27: Publicly Held | E27: =C27/F27 -> 7.8824305 | F27: 659.44 | G27: www.libertyenergy.com | H27: LBRT | I27: 4195.91
B30: Disregarded Pulled Comps:
B31: ProFrac Holding | C31: 2395.85 | D31: Publicly Held | E31: =C31/F31 -> 18.054635 | F31: 132.7 | G31: www.profrac.com | H31: ACDC | I31: 1787.3
B32: Atlas Energy Solutions | C32: 2727.46 | D32: Publicly Held | E32: =C32/F32 -> 24.585001 | F32: 110.94 | G32: www.atlas.energy | H32: AESI | I32: 1067.8

Sheet Site By Site Assignments
B2: SLCA Site Split
B3: Site | C3: Type | D3: Verdict | E3: Reason
B4: Crane, TX | C4: Proppant sand | D4: O&G | E4: Frac sand asset
B5: Lamesa, TX | C5: Proppant sand | D5: O&G | E5: Frac sand asset
B6: Ottawa, IL | C6: Silica sand | D6: ISP | E6: Broader industrial silica
B7: Lovelock/Colado, NV | C7: Diatomaceous earth | D7: ISP | E7: Specialty industrial mineral
B8: Dubberly, LA | C8: Silica for glass/foundry/building | D8: ISP | E8: Industrial end markets
B9: Pacific, MO | C9: Silica, some proppant | D9: Mixed / ISP | E9: Mostly industrial, some O&G
B10: Mapleton Depot, PA | C10: Silica, some proppant | D10: Mixed / ISP | E10: Mostly industrial, some O&G
B11: Mill Creek, OK | C11: Ground/fine ground silica | D11: ISP | E11: Industrial silica
B12: Columbia, SC | C12: Glass/building/fillers/filtration | D12: ISP | E12: Industrial end markets
B13: Hurtsboro, AL | C13: Foundry/building/recreation | D13: ISP | E13: Industrial end markets
B14: Mauricetown, NJ | C14: Foundry/filtration/building/recreation | D14: ISP | E14: Industrial end markets
... B29: Siskiyou, CA | C29: DE exploration | D29: ISP | E29: Future DE resource

Sheet SLCA Raw
A1: US Silica Holdings Inc (90346E10)
A2: Income Statement - Annual (As Originally Reported) | M2: Income Statement - Annual (As Originally Reported)
A3: FYE December | B3: 43465 | C3: 43830 | D3: 44196 | E3: 44561 | F3: 44926 | G3: 45291 | M3: FYE December
A4: Currency | B4: USD | C4: USD | D4: USD | E4: USD | F4: USD | G4: USD | M4: Currency
A5: Scale | B5: Million | C5: Million | D5: Million | E5: Million | F5: Million | G5: Million | M5: Scale
A6: Total Revenue | B6: 1577.298 | C6: 1474.477 | D6: 845.885 | E6: 1103.879 | F6: 1525.147 | G6: 1552.022 | M6: Total Revenue
A7: Cost of Revenue, Total | B7: 1163.129 | C7: 1133.293 | D7: 548.522 | E7: 761.798 | F7: 1031.613 | G7: 982.979 | M7: Cost of Revenue, Total
A8: Gross Profit | B8: 414.169 | C8: 341.184 | D8: 297.363 | E8: 342.081 | F8: 493.534 | G8: 569.043 | M8: Gross Profit
A9: Selling/General/Admin. Expenses, Total | B9: 146.971 | C9: 150.848 | D9: 150.719 | E9: 152.813 | F9: 182.414 | G9: 156.445 | M9: Selling/General/Admin. Expenses, Total
A10: Research & Development | M10: Research & Development
A11: Depreciation/Amortization | B11: 148.8 | C11: 179.4 | D11: 155.6 | E11: 161.1 | F11: 140.2 | G11: 137.3 | M11: Depreciation/Amortization
A12: Interest Exp.(Inc.), Net-Operating, Total | M12: Interest Exp.(Inc.), Net-Operating, Total
A13: Unusual Expense (Income) | B13: 281.9 | C13: 363.8 | D13: 110.7 | E13: 0.2 | F13: 0 | G13: 8.5 | M13: Unusual Expense (Income)
A14: Other Operating Expenses, Total | M14: Other Operating Expenses, Total
A15: Total Operating Expense | B15: 1740.8 | C15: 1827.4 | D15: 965.5 | E15: 1075.9 | F15: 1354.2 | G15: 1285.2 | M15: Total Operating Expense
A16: Operating Income | B16: -163.533 | C16: -352.955 | D16: -119.612 | E16: 27.935 | F16: 170.954 | G16: 266.839 | M16: Operating Income
A17: Interest Inc.(Exp.),Net-Non-Op., Total | B17: -70.6 | C17: -95.5 | D17: -79.9 | E17: -71.2 | F17: -77.6 | G17: -101.7 | M17: Interest Inc.(Exp.),Net-Non-Op., Total
A18: Gain (Loss) on Sale of Assets | D18: 0.3 | G18: 16.8 | M18: Gain (Loss) on Sale of Assets
A19: Other, Net | B19: 4.1 | C19: 19.5 | D19: 24 | E19: 6.1 | F19: 10.6 | G19: 13.6 | M19: Other, Net
A20: Net Income Before Taxes | B20: -229.953 | C20: -428.908 | D20: -175.147 | E20: -37.076 | F20: 103.999 | G20: 195.569 | M20: Net Income Before Taxes
A21: Provision for Income Taxes | B21: -29.132 | C21: -99.151 | D21: -37.707 | E21: -2.755 | F21: 26.159 | G21: 49.08 | M21: Provision for Income Taxes
A22: Net Income | B22: -200.808 | C22: -329.082 | D22: -114.094 | E22: -33.761 | F22: 78.176 | G22: 146.925 | M22: Net Income
A23: Preferred Dividends | M23: Preferred Dividends
A24: Basic EPS Excluding Extraordinary Items | B24: -2.63 | C24: -4.49 | D24: -1.85 | E24: -0.45 | F24: 1.04 | G24: 1.91 | M24: Basic EPS Excluding Extraordinary Items
A25: Basic EPS Including Extraordinary Items | B25: -2.63 | C25: -4.49 | D25: -1.55 | E25: -0.45 | F25: 1.04 | G25: 1.91 | M25: Basic EPS Including Extraordinary Items
A26: Normalized Basic EPS | B26: 0.64 | C26: -0.83 | D26: -0.75 | E26: -0.35 | F26: 1.2 | G26: 1.83 | M26: Normalized Basic EPS
A27: Basic Weighted Average Shares | B27: 76 | C27: 73 | D27: 74 | E27: 74 | F27: 76 | G27: 77 | M27: Basic Weighted Average Shares
A28: Diluted EPS Excluding ExtraOrd Items | B28: -2.63 | C28: -4.49 | D28: -1.85 | E28: -0.45 | F28: 1.01 | G28: 1.87 | M28: Diluted EPS Excluding ExtraOrd Items
A29: Diluted EPS Including ExtraOrd Items | B29: -2.63 | C29: -4.49 | D29: -1.55 | E29: -0.45 | F29: 1.01 | G29: 1.87 | M29: Diluted EPS Including ExtraOrd Items
A30: Normalized Diluted EPS | B30: 0.64 | C30: -0.83 | D30: -0.75 | E30: -0.35 | F30: 1.17 | G30: 1.79 | M30: Normalized Diluted EPS
A31: Diluted Weighted Average Shares | B31: 76 | C31: 73 | D31: 74 | E31: 74 | F31: 78 | G31: 79 | M31: Diluted Weighted Average Shares
A32: Dividends Per Share | B32: 0.25 | C32: 0.25 | M32: Dividends Per Share
A33: Number of Employees | B33: 2812 | C33: 2177 | D33: 1613 | E33: 1863 | F33: 2013 | G33: 1873 | M33: Number of Employees
A36: US Silica Holdings Inc (90346E10) | M36: Olin Corp (OLN)
A37: Balance Sheet - Annual (As Originally Reported) | M37: Balance Sheet - Annual (As Originally Reported)
A38: FYE December | B38: 43465 | C38: 43830 | D38: 44196 | E38: 44561 | F38: 44926 | G38: 45291 | M38: FYE December
A39: Currency | B39: USD | C39: USD | D39: USD | E39: USD | F39: USD | G39: USD | M39: Currency
A40: Scale | B40: Million | C40: Million | D40: Million | E40: Million | F40: Million | G40: Million | M40: Scale
A41: Cash & Equivalents | B41: 202.498 | C41: 185.74 | D41: 150.92 | E41: 239.425 | F41: 280.845 | G41: 245.716 | M41: Cash & Equivalents
A42: Cash, Cash Equiv. & Short Term Inv. | B42: 202.498 | C42: 185.74 | D42: 150.92 | E42: 239.425 | F42: 280.845 | G42: 245.716 | M42: Cash, Cash Equiv. & Short Term Inv.
A43: Total Receivables, Net | B43: 217.686 | C43: 182.713 | D43: 207.562 | E43: 202.759 | F43: 208.631 | G43: 185.917 | M43: Total Receivables, Net
A44: Total Inventory | B44: 162.087 | C44: 124.432 | D44: 104.684 | E44: 115.713 | F44: 147.626 | G44: 149.429 | M44: Total Inventory
A45: Prepaid Expenses | B45: 18 | C45: 16.2 | D45: 23.1 | E45: 18 | F45: 20.2 | G45: 19.7 | M45: Prepaid Expenses
A46: Other Current Assets, Total | M46: Other Current Assets, Total
A47: Total Current Assets | B47: 600.237 | C47: 509.04 | D47: 486.313 | E47: 575.915 | F47: 657.284 | G47: 600.744 | M47: Total Current Assets
A48: Property/Plant/Equipment, Total - Gross | B48: 2326.1 | C48: 2277.3 | D48: 2245 | E48: 2286.2 | F48: 2321.1 | G48: 2377.6 | M48: Property/Plant/Equipment, Total - Gross
A49: Accumulated Depreciation, Total | B49: -499.823 | C49: -706.61 | D49: -839.402 | E49: -985.295 | F49: -1099.922 | G49: -1211.26 | M49: Accumulated Depreciation, Total
A50: Property/Plant/Equipment, Total - Net | B50: 1826.3 | C50: 1570.7 | D50: 1405.6 | E50: 1300.9 | F50: 1221.2 | G50: 1166.3 | M50: Property/Plant/Equipment, Total - Net
A51: Goodwill, Net | B51: 261.34 | C51: 273.524 | D51: 185.649 | E51: 185.649 | F51: 185.649 | G51: 185.649 | M51: Goodwill, Net
A52: Intangibles, Net | B52: 194.626 | C52: 183.815 | D52: 159.582 | E52: 150.054 | F52: 140.809 | G52: 131.384 | M52: Intangibles, Net
A53: Long Term Investments | M53: Long Term Investments
A54: Note Receivable - Long Term | M54: Note Receivable - Long Term
A55: Other Long Term Assets, Total | B55: 18.3 | C55: 16.2 | D55: 9.8 | E55: 7.1 | F55: 9.6 | G55: 12.5 | M55: Other Long Term Assets, Total
A56: Other Assets, Total | M56: Other Assets, Total
A57: Total Assets | B57: 2900.84 | C57: 2553.234 | D57: 2246.947 | E57: 2219.6 | F57: 2214.58 | G57: 2096.593 | M57: Total Assets
A58: Accounts Payable | B58: 178.804 | C58: 181.029 | D58: 90.564 | E58: 134.494 | F58: 182.555 | G58: 123.667 | M58: Accounts Payable
A59: Payable/Accrued | C59: 26.6 | D59: 4.8 | M59: Payable/Accrued
A60: Accrued Expenses | B60: 37.6 | C60: 94.2 | D60: 44 | E60: 47.6 | F60: 51.1 | G60: 40.6 | M60: Accrued Expenses
A61: Current Port. of LT Debt/Capital Leases | B61: 13.3 | C61: 18.5 | D61: 42 | E61: 18.3 | F61: 19.5 | G61: 16.4 | M61: Current Port. of LT Debt/Capital Leases
A62: Notes Payable/Short Term Debt | B62: 0 | C62: 0 | D62: 0 | E62: 0 | F62: 0 | G62: 0 | M62: Notes Payable/Short Term Debt
A63: Other Current Liabilities, Total | B63: 31.6 | C63: 15.1 | D63: 13.5 | E63: 5.4 | F63: 18.7 | G63: 5.3 | M63: Other Current Liabilities, Total
A64: Total Current Liabilities | B64: 261.339 | C64: 335.398 | D64: 194.895 | E64: 205.871 | F64: 271.95 | G64: 185.85 | M64: Total Current Liabilities
A65: Long Term Debt | B65: 1246.4 | C65: 1214 | D65: 1197.4 | E65: 1190.6 | F65: 1035.3 | G65: 821.7 | M65: Long Term Debt
A66: Capital Lease Obligations | C66: 0 | D66: 0.3 | E66: 2.5 | F66: 2.2 | G66: 2 | M66: Capital Lease Obligations
A67: Total Long Term Debt | B67: 1246.428 | C67: 1213.985 | D67: 1197.66 | E67: 1193.135 | F67: 1037.458 | G67: 823.67 | M67: Total Long Term Debt
A68: Deferred Income Tax | B68: 137.239 | C68: 38.585 | D68: 49.386 | E68: 44.774 | F68: 64.636 | G68: 100.458 | M68: Deferred Income Tax
A69: Other Liabilities, Total | B69: 203.5 | C69: 248.7 | D69: 178.2 | E69: 161.7 | F69: 135.8 | G69: 131.1 | M69: Other Liabilities, Total
A70: Minority Interest | B70: 7.484 | C70: 11.363 | D70: 11.531 | E70: 9.868 | F70: 8.009 | G70: 6.219 | M70: Minority Interest
A71: Total Liabilities | B71: 1856.02 | C71: 1848.017 | D71: 1631.687 | E71: 1615.385 | F71: 1517.895 | G71: 1247.285 | M71: Total Liabilities
A72: Redeemable Preferred Stock, Total | M72: Redeemable Preferred Stock, Total
A73: Preferred Stock - Non Redeemable, Net | B73: 0 | C73: 0 | D73: 0 | E73: 0 | F73: 0 | M73: Preferred Stock - Non Redeemable, Net
A74: Limited Partner | M74: Limited Partner
A75: Common Stock | B75: 0.8 | C75: 0.8 | D75: 0.8 | E75: 0.8 | F75: 0.9 | G75: 0.9 | M75: Common Stock
A76: Additional Paid-In Capital | B76: 1169.383 | C76: 1185.116 | D76: 1200.023 | E76: 1218.575 | F76: 1234.834 | G76: 1249.46 | M76: Additional Paid-In Capital
A77: Retained Earnings (Accumulated Deficit) | B77: 67.854 | C77: -279.956 | D77: -395.496 | E77: -429.26 | F77: -351.084 | G77: -204.159 | M77: Retained Earnings (Accumulated Deficit)
A78: Treasury Stock - Common | B78: -178.215 | C78: -180.912 | D78: -181.615 | E78: -186.294 | F78: -186.196 | G78: -196.745 | M78: Treasury Stock - Common
A79: ESOP Debt Guarantee | M79: ESOP Debt Guarantee
A80: Unrealized Gain (Loss) | M80: Unrealized Gain (Loss)
A81: Other Equity, Total | B81: -15.02 | C81: -19.854 | D81: -8.479 | E81: 0.349 | F81: -1.723 | G81: -0.125 | M81: Other Equity, Total
A82: Total Equity | B82: 1044.82 | C82: 705.217 | D82: 615.26 | E82: 604.215 | F82: 696.685 | G82: 849.308 | M82: Total Equity
A83: Total Liabilities & Shareholders' Equity | B83: 2900.84 | C83: 2553.234 | D83: 2246.947 | E83: 2219.6 | F83: 2214.58 | G83: 2096.593 | M83: Total Liabilities & Shareholders' Equity
A84: Total Common Shares Outstanding | B84: 73 | C84: 74 | D84: 74 | E84: 75 | F84: 76 | G84: 77 | M84: Total Common Shares Outstanding
A87: US Silica Holdings Inc (90346E10) | M87: Olin Corp (OLN)
A88: Cash Flow - Annual (As Originally Reported) | M88: Cash Flow - Annual (As Originally Reported)
A89: FYE December | B89: 43465 | C89: 43830 | D89: 44196 | E89: 44561 | F89: 44926 | G89: 45291 | M89: FYE December
A90: Currency | B90: USD | C90: USD | D90: USD | E90: USD | F90: USD | G90: USD | M90: Currency
A91: Scale | B91: Million | C91: Million | D91: Million | E91: Million | F91: Million | G91: Million | M91: Scale
A92: Net Income | B92: -200.821 | C92: -329.757 | D92: -115.122 | E92: -34.321 | F92: 77.84 | G92: 146.489 | M92: Net Income
A93: Changes in Working Capital | B93: 135.156 | C93: 83.298 | D93: -75.171 | E93: 30.387 | F93: 5.981 | G93: -64.144 | M93: Changes in Working Capital
A94: Cash from Operating Activities | B94: 310.706 | C94: 144.046 | D94: -10.534 | E94: 169.347 | F94: 262.716 | G94: 263.868 | M94: Cash from Operating Activities
A95: Capital Expenditures | B95: -349.861 | C95: -122.289 | D95: -34.917 | E95: -30.517 | F95: -53.562 | G95: -65.47 | M95: Capital Expenditures
A96: Investment, Net | M96: Investment, Net
A97: Software Development Costs | M97: Software Development Costs
A98: Sale of Fixed Assets | B98: 26.231 | C98: 1.896 | D98: 7.353 | E98: 0.661 | F98: 2.609 | G98: 20.749 | M98: Sale of Fixed Assets
A99: Acquisition of Business | B99: -743.249 | C99: 0 | D99: 0 | M99: Acquisition of Business
A100: Sale/Maturity of Investment | B100: 0 | M100: Sale/Maturity of Investment
A101: Other Investing Cash Flow Items, Total | B101: -717.018 | C101: 1.896 | D101: 7.353 | E101: 0.661 | F101: 2.609 | G101: 20.749 | M101: Other Investing Cash Flow Items, Total
A102: Cash from Investing Activities | B102: -1066.879 | C102: -120.393 | D102: -27.564 | E102: -29.856 | F102: -50.953 | G102: -44.721 | M102: Cash from Investing Activities
A103: Short Term Debt, Net | E103: -6.398 | F103: -7.237 | G103: -8.863 | M103: Short Term Debt, Net
A104: Issuance (Retirement) of Debt, Net | B104: 778.011 | C104: -23.508 | D104: 8.97 | E104: -44.939 | F104: -166.658 | G104: -200.701 | M104: Issuance (Retirement) of Debt, Net
...
