Workbook

Sheet Inputs
A1: Inputs ($mm except per-share, percentages, multiples)
A3: Input | B3: Value | D3: Notes | E3: Source / Comment
A4: Purchase price / EV | B4: 225 | D4: All cash | E4: https://ir.cleanharbors.com/news-releases/news-release-details/clean-harbors-announces-acquisition-terra-nova-solutions
A5: Revenue - low | B5: 45 | D5: Disclosed | E5: https://ir.cleanharbors.com/news-releases/news-release-details/clean-harbors-announces-acquisition-terra-nova-solutions
A6: Revenue - high | B6: 50 | D6: Disclosed | E6: https://ir.cleanharbors.com/news-releases/news-release-details/clean-harbors-announces-acquisition-terra-nova-solutions
A7: Standalone Adjusted EBITDA | B7: 15 | D7: Approximate EBITDA disclosed | E7: https://ir.cleanharbors.com/news-releases/news-release-details/clean-harbors-announces-acquisition-terra-nova-solutions
A8: Run-rate synergies | B8: 4 | D8: expected synergies via press release | E8: https://ir.cleanharbors.com/news-releases/news-release-details/clean-harbors-announces-acquisition-terra-nova-solutions
A9: Disclosed post-synergy multiple | B9: 11.8 | D9: Disclosed post-synergy EV / EBITDA multiple. | E9: https://ir.cleanharbors.com/news-releases/news-release-details/clean-harbors-announces-acquisition-terra-nova-solutions
A10: Revenue midpoint | B10: =AVERAGE(B5:B6) -> 47.5 | D10: Formula: average of revenue range.
A11: Post-synergy EBITDA | B11: =B7+B8 -> 19 | D11: Formula: EBITDA + synergies.
A12: Implied standalone EV / EBITDA | B12: =B4/B7 -> 15 | D12: Formula: purchase price / standalone EBITDA.
A13: Implied post-synergy EV / EBITDA | B13: =B4/B11 -> 11.842105 | D13: Formula: purchase price / post-synergy EBITDA.
A14: D&A as % of EBITDA | B14: 0.15 | D14: assumption | E14: Assumption - waste companies tend to lean high
A15: Tax rate | B15: 0.25 | D15: Assumption | E15: assumption - from past 10-k
A16: Cash Opportunity Cost | B16: 0.04 | D16: Lost cash interest/debt financing or revolver | E16: assumption
A17: Clean Harbors 2025 net income | B17: 391 | D17: FY2025 net income | E17: https://ir.cleanharbors.com/news-releases/news-release-details/clean-harbors-announces-fourth-quarter-and-full-year-2025
A18: Clean Harbors 2025 diluted EPS | B18: 7.28 | D18: FY2025 diluted EPS | E18: https://ir.cleanharbors.com/news-release-details/2026/Clean-Harbors-Announces-Fourth-Quarter-and-Full-Year-2025-Financial-Results/default.aspx
A19: Clean Harbors diluted shares | B19: 53.716 | D19: Weighted-average diluted shares from 2025 10-K. | E19: https://ir.cleanharbors.com/static-files/6b594bf5-0d42-431a-ad55-00d59200cb4c

Sheet MnA Comps
E1: MnA Comps Tab
A3: Downloaded on: | C3: 46203
A4: Created for: | C4: Evan Hassan, University of Utah Marriott Library- Students
A5: Search Criteria: | C5: Valuation / Revenue: Min: 0.00; Valuation / EBITDA: Min: 0.00; Max: 40.00; Deal Date: From: 01-Jan-2021; To: 21-Aug-2026; Deal Size: Min: 100M; Max: 400M; Deal Option: Search on a full transaction; Deal Status: Completed; Deal Type: M&A/Control Transactions > M&A; Location: Americas;
A10: Transaction | B10: Role | C10: Deal Size | D10: Post Valuation | E10: Post Valuation Status | F10: Investors | G10: Sellers | H10: Acquired Company | I10: Implied EV | J10: Revenue | K10: EBITDA | L10: EBIT | M10: Fiscal Year | N10: Deal Size/EBITDA | O10: Deal Size/Revenue | P10: Implied EV/EBITDA | Q10: Implied EV/Revenue | R10: EBITDA Margin % | S10: Current Employees | T10: Deal Date
A11: Clean Harbors / Terra Nova Solutions | B11: subject transaction | C11: 225 | D11: 225 | E11: Estimated | F11: Clean Harbors (NYS: CLH)(Michael Battles) | G11: Crescentia Capital | H11: Terra Nova Solutions | I11: 225 | S11: 120 | T11: 46147
A12: Ambipar / Disal Chile | B12: selected precedent comp | C12: 157.98 | D12: 157.98 | E12: Estimated | F12: Ambipar Participacoes e Empreendimentos (BVMF: AMBP3)(Fábio Castro) | G12: Australis Partners | H12: Disal Chile | I12: 157.98 | J12: 97.63 | K12: 17.57 | M12: 2020 | N12: 8.99 | O12: 1.62 | P12: 8.99 | Q12: 1.62 | R12: 18 | S12: 454 | T12: 44374
A13: Clean Harbors / HEPACO | B13: selected precedent comp | C13: 392.12 | D13: 392.12 | E13: Estimated | F13: Clean Harbors (NYS: CLH)(Eric Gerstenberg) | G13: Gryphon Investors | H13: HEPACO | I13: 392.12 | J13: 270 | K13: 36 | M13: 2023 | N13: 10.89 | O13: 1.45 | P13: 10.89 | Q13: 1.45 | R13: 13.33 | S13: 518 | T13: 45373
A14: Kemira/ Water Engineering | B14: selected precedent comp | C14: 147.52 | D14: 152.08 | E14: Estimated | F14: Kemira (HEL: KEMIRA)(Antti Salminen) | G14: Nolan Capital | H14: Water Engineering (Mead) | I14: 152.09 | J14: 2753.5 | L14: 271.6 | M14: 2025 | O14: 0.05 | Q14: 0.06 | S14: 54 | T14: 45947
A15: Secure Energy Services / Tervia | B15: selected precedent cmp | C15: 390.25 | D15: 390.25 | E15: Estimated | F15: Secure Energy Services (TSE: SES)(Rene Amirault) | G15: AllianceBernstein, British Columbia Investment Management, Goldman Sachs Asset Management, International Technologies (Canada), Newalta, OSS Capital Management, Solus Alternative Asset Management, Vestar Capital Partners | H15: Tervita | I15: 373.11 | J15: 1031.43 | K15: 132.24 | L15: 55.16 | M15: 2021 | N15: 2.95 | O15: 0.38 | P15: 2.82 | Q15: 0.36 | R15: 12.82 | S15: 1213 | T15: 44379
A16: D.R Horton / Vidler Water Company | B16: excluded | C16: 271.5 | D16: 271.5 | E16: Estimated | F16: D.R. Horton (NYS: DHI)(Jessica Hansen) | G16: BlackRock Fund Advisors, Dimensional Fund Advisors, Physicians Insurance Company of Ohio | H16: Vidler Water Company | I16: 245.97 | J16: 26.28 | K16: 12.75 | L16: 12.56 | M16: 2022 | N16: 21.29 | O16: 10.33 | P16: 19.29 | Q16: 9.36 | R16: 48.51 | S16: 14 | T16: 44705
A17: Korea Zinc / Igloo | B17: excluded | C17: 332 | D17: 453.49 | E17: Estimated | F17: Korea Zinc (KRX: 010130) | G17: Tarsadia Capital | H17: Igneo | I17: 453.49 | J17: 49.3 | M17: 2022 | O17: 6.73 | Q17: 9.2 | S17: 170 | T17: 44753
A18: Hawkins / Water Surplus | B18: selected precedent comp | C18: 203.7 | D18: 203.7 | E18: Estimated | F18: Hawkins (NAS: HWKN)(Patrick Hawkins) | G18: The Water Council | H18: WaterSurplus | I18: 203.7 | K18: 10 | M18: 2024 | N18: 20.37 | P18: 20.37 | S18: 60 | T18: 45772
A19: Vivakor / Equipment Transport | B19: selected precedent cmp | C19: 116.3 | D19: 116.3 | E19: Estimated | F19: Vivakor (NAS: VIVK)(James Ballengee) | G19: Gas Field Services | H19: Equipment Transport | I19: 116.3 | J19: 94.6 | K19: 18.67 | M19: 2024 | N19: 6.23 | O19: 1.23 | P19: 6.23 | Q19: 1.23 | R19: 19.73 | S19: 500 | T19: 45566
A26: © PitchBook Data, Inc. 2026

Sheet Valuation
A1: Model 1: Precedent Transaction and Implied Valuation
A3: Terra Nova quick math
A4: Purchase price / EV | B4: =Inputs!B4 -> 225
A5: Standalone EBITDA | B5: =Inputs!B7 -> 15
A6: Run-rate synergies | B6: =Inputs!B8 -> 4
A7: Post-synergy EBITDA | B7: =B5+B6 -> 19
A8: Implied standalone EV / EBITDA | B8: =B4/B5 -> 15
A9: Implied post-synergy EV / EBITDA | B9: =B4/B7 -> 11.842105
A12: Date | B12: Acquirer | C12: Target | D12: Sector | E12: EV ($mm) | F12: Standalone EBITDA ($mm) | G12: Synergies ($mm) | H12: Post-Synergy EBITDA ($mm) | I12: Standalone EV/EBITDA | J12: Post-Synergy EV/EBITDA | K12: Source URL | L12: Comment
A13: 46168 | B13: ='MnA Comps'!F11 -> Clean Harbors (NYS: CLH)(Michael Battles) | C13: ='MnA Comps'!H11 -> Terra Nova Solutions | D13: Environmental Services | E13: ='MnA Comps'!C11 -> 225 | F13: =Inputs!B7 -> 15 | G13: =Inputs!B8 -> 4 | H13: =F13+G13 -> 19 | I13: =E13/F13 -> 15 | J13: =E13/H13 -> 11.842105 | K13: https://ir.cleanharbors.com/news-releases/news-release-details/clean-harbors-announces-acquisition-terra-nova-solutions
A14: ='MnA Comps'!T12 -> 44374 | B14: ='MnA Comps'!F12 -> Ambipar Participacoes e Empreendimentos (BVMF: AMBP3)(Fábio Castro) | C14: ='MnA Comps'!H12 -> Disal Chile | D14: Environmental Services | E14: ='MnA Comps'!C12 -> 157.98 | F14: ='MnA Comps'!K12 -> 17.57 | G14: =F14*0.1 -> 1.757 | H14: =F14+G14 -> 19.327 | I14: =E14/F14 -> 8.9914627 | J14: =E14/H14 -> 8.174057 | K14: https://ambipar.com/latam/noticias/ambipar-anuncia-la-adquisicion-del-100-de-la-empresa-de-gestion-ambiental-disal/ | L14: estimated synergy 10% ebitda
A15: ='MnA Comps'!T13 -> 45373 | B15: ='MnA Comps'!F13 -> Clean Harbors (NYS: CLH)(Eric Gerstenberg) | C15: ='MnA Comps'!H13 -> HEPACO | D15: Environmental Services | E15: ='MnA Comps'!C13 -> 392.12 | F15: ='MnA Comps'!K13 -> 36 | G15: 20 | H15: =F15+G15 -> 56 | I15: =E15/F15 -> 10.892222 | J15: =E15/H15 -> 7.0021429 | K15: https://www.veolia.com/en/our-media/press-releases/hazardous-waste-us-acquisition-clean-earth | L15: synergy states in press release
A16: ='MnA Comps'!T19 -> 45566 | B16: ='MnA Comps'!F19 -> Vivakor (NAS: VIVK)(James Ballengee) | C16: ='MnA Comps'!H19 -> Equipment Transport | D16: Environmental Services | E16: ='MnA Comps'!C19 -> 116.3 | F16: ='MnA Comps'!K19 -> 18.67 | G16: =F16*0.1 -> 1.867 | H16: =G16+F16 -> 20.537 | I16: =E16/F16 -> 6.2292448 | J16: =E16/H16 -> 5.6629498 | K16: https://www.sec.gov/Archives/edgar/data/1450704/000182912624001850/vivakorinc_ex99-1.htm | L16: estimated synergy 10% ebitda
A17: ='MnA Comps'!T15 -> 44379 | B17: ='MnA Comps'!F15 -> Secure Energy Services (TSE: SES)(Rene Amirault) | C17: ='MnA Comps'!H15 -> Tervita | D17: Environmental Services | E17: ='MnA Comps'!C15 -> 390.25 | F17: =E17*0.12 -> 46.83 | G17: 75 | H17: =SUM(F17:G17) -> 121.83 | I17: =E17/F17 -> 8.3333333 | J17: =E17/H17 -> 3.203234 | K17: https://s28.q4cdn.com/276182264/files/doc_downloads/res_library/SECURE-IR-Presentation-July-27-2021-Final.pdf | L17: synergies: cost savings of "at least $75M"
A22: Multiple summary | B22: Standalone EV/EBITDA | C22: Post-Synergy EV/EBITDA
A23: Low | B23: =MIN(I14:I17) -> 6.2292448 | C23: =MIN(J14:J17) -> 3.203234
A24: Median | B24: =MEDIAN(I14:I17) -> 8.662398 | C24: =MEDIAN(J14:J17) -> 6.3325463
A25: High | B25: =MAX(I14:I17) -> 10.892222 | C25: =MAX(J14:J17) -> 8.174057
A26: Terra Nova | B26: =I13 -> 15 | C26: =J13 -> 11.842105

Sheet Accretion-Dilution 
A1: Model 2: Accretion / Dilution | E1: EPS Accretion / Dilution Sensitivity
G2: Cash Opportunity Cost
A3: Assumption / Output | B3: Value | C3: Formula / Notes | E3: Synergies(mm) | F3: =B25 -> 0.014729532 | G3: 0.03 | H3: 0.035 | I3: 0.04 | J3: 0.045 | K3: 0.05
A4: Purchase price / EV | B4: =Inputs!B4 -> 225 | C4: Linked from Inputs | E4: 0 | F4: =E4 -> 0 | G4: 0.011373205 | H4: 0.0092155662 | I4: 0.0070579274 | J4: 0.0049002886 | K4: 0.0027426498
A5: Target standalone EBITDA | B5: =Inputs!B7 -> 15 | C5: Linked from Inputs | E5: 2 | F5: =E5 -> 2 | G5: 0.015209007 | H5: 0.013051368 | I5: 0.01089373 | J5: 0.0087360909 | K5: 0.0065784521
A6: Run-rate synergies | B6: =Inputs!B8 -> 4 | C6: Linked from Inputs | E6: 4 | F6: =E6 -> 4 | G6: 0.01904481 | H6: 0.016887171 | I6: 0.014729532 | J6: 0.012571893 | K6: 0.010414254
A7: D&A as % of EBITDA | B7: =Inputs!B14 -> 0.15 | C7: Linked from Inputs | E7: 6 | F7: =E7 -> 6 | G7: 0.022880612 | H7: 0.020722973 | I7: 0.018565334 | J7: 0.016407695 | K7: 0.014250057
A8: Target D&A | B8: =B5*B7 -> 2.25 | C8: EBITDA x D&A % | E8: 8 | F8: =E8 -> 8 | G8: 0.026716414 | H8: 0.024558775 | I8: 0.022401137 | J8: 0.020243498 | K8: 0.018085859
A9: Target EBITDA + synergies | B9: =B5+B6 -> 19 | C9: Standalone EBITDA + synergies
A10: Target EBIT after D&A | B10: =B9-B8 -> 16.75 | C10: EBITDA + synergies - D&A
A11: Cost of debt | B11: =Inputs!B16 -> 0.04 | C11: Linked from Inputs
A12: Foregone interest income | B12: =B4*B11 -> 9 | C12: Purchase price x financing cost
A13: Pre-tax earnings contribution | B13: =B10-B12 -> 7.75 | C13: Target EBIT - Incremental interest expense
A14: Tax rate | B14: =Inputs!B15 -> 0.25 | C14: Linked from Inputs
A15: After-tax earnings contribution | B15: =B13*(1-B14) -> 5.8125 | C15: Pre-tax x (1-tax rate)
A16: Clean Harbors standalone net income | B16: =Inputs!B17 -> 391 | C16: Linked from Inputs
A17: Pro forma net income | B17: =B16+B15 -> 396.8125 | C17: Standalone NI + after-tax contribution
A18: Diluted shares | B18: =Inputs!B19 -> 53.716 | C18: Linked from Inputs
A19: Pro forma EPS | B19: =B17/B18 -> 7.387231 | C19: Pro forma NI / diluted shares
A20: Standalone EPS | B20: =Inputs!B18 -> 7.28 | C20: Standalone EPS
A23: Key output | B23: Value | C23: Meaning
A24: EPS accretion / dilution ($) | B24: =B19-B20 -> 0.10723099 | C24: Pro forma EPS - standalone EPS
A25: EPS accretion / dilution (%) | B25: =B24/B20 -> 0.014729532 | C25: Accretion / standalone EPS
A26: Standalone deal multiple | B26: =B4/B5 -> 15 | C26: Purchase price / standalone EBITDA
A27: Post-synergy deal multiple | B27: =B4/B9 -> 11.842105 | C27: Purchase price / EBITDA incl. synergies
