Workbook

Sheet Sheet3
B1: Michael Scott's Paper Company
B2: Standalone Financials
C3: Actual | D3: Forecast
B4: FYE December | C4: 2009A Annuaized | D4: 2010E | E4: 2011E | F4: 2012E | G4: 2013E | H4: 2014E
B5: Currency | C5: USD | D5: USD | E5: USD | F5: USD | G5: USD | H5: USD
B6: Scale | C6: k | D6: k | E6: k | F6: k | G6: k | H6: k
B7: Total Revenue | C7: =C22*C23*C24*C25 / 1000 -> 144 | D7: =D22*D23*D24*D25 / 1000 -> 275.184 | E7: =E22*E23*E24*E25 / 1000 -> 405 | F7: =F22*F23*F24*F25 / 1000 -> 514.08 | G7: =G22*G23*G24*G25 / 1000 -> 615.264 | H7: =H22*H23*H24*H25 / 1000 -> 686.88
B8: Year-over-year growth | D8: =D7/C7 -1 -> 0.911 | E8: =E7/D7 -1 -> 0.47174254 | F8: =F7/E7 -1 -> 0.26933333 | G8: =G7/F7 -1 -> 0.1968254 | H8: =H7/G7 -1 -> 0.11639881
B10: Cost of Revenue | C10: =C7*C26 -> 144 | D10: =D7*D26 -> 266.92848 | E10: =E7*E26 -> 380.7 | F10: =F7*F26 -> 472.9536 | G10: =G7*G26 -> 553.7376 | H10: =H7*H26 -> 604.4544
B11: Gross Profit | C11: =C7-C10 -> 0 | D11: =D7-D10 -> 8.25552 | E11: =E7-E10 -> 24.3 | F11: =F7-F10 -> 41.1264 | G11: =G7-G10 -> 61.5264 | H11: =H7-H10 -> 82.4256
B12: Cash Compensation & Benefits | C12: =C29 -> 0 | D12: =D29 -> 20 | E12: =E29 -> 40 | F12: =F29 -> 60 | G12: =G29 -> 75 | H12: =H29 -> 90
B13: Rent and Occupancy | C13: =C30 -> 3 | D13: =D30 -> 3 | E13: =E30 -> 3.1 | F13: =F30 -> 3.1 | G13: =G30 -> 3.2 | H13: =H30 -> 3.2
B14: Delivery and Vehicle Expense | C14: =C31 -> 2 | D14: =D31 -> 2.4 | E14: =E31 -> 2.7 | F14: =F31 -> 2.8 | G14: =G31 -> 2.9 | H14: =H31 -> 3
B15: EBITDA | C15: =C11-SUM(C12:C14) -> -5 | D15: =D11-SUM(D12:D14) -> -17.14448 | E15: =E11-SUM(E12:E14) -> -21.5 | F15: =F11-SUM(F12:F14) -> -24.7736 | G15: =G11-SUM(G12:G14) -> -19.5736 | H15: =H11-SUM(H12:H14) -> -13.7744
B16: EBITDA Margin | C16: =C15/C7 -> -0.034722222 | D16: =D15/D7 -> -0.062301878 | E16: =E15/E7 -> -0.05308642 | F16: =F15/F7 -> -0.048190165 | G16: =G15/G7 -> -0.031813335 | H16: =H15/H7 -> -0.020053576
B17: D&A(van) | C17: =C32 -> 0.6 | D17: =D32 -> 0.6 | E17: =E32 -> 0.6 | F17: =F32 -> 0.6 | G17: =G32 -> 0.6 | H17: =H32 -> 0
B18: Operating Income | C18: =C15-C17 -> -5.6 | D18: =D15-D17 -> -17.74448 | E18: =E15-E17 -> -22.1 | F18: =F15-F17 -> -25.3736 | G18: =G15-G17 -> -20.1736 | H18: =H15-H17 -> -13.7744
B19: Operating Margin | C19: =C18/C7 -> -0.038888889 | D19: =D18/D7 -> -0.064482237 | E19: =E18/E7 -> -0.054567901 | F19: =F18/F7 -> -0.049357298 | G19: =G18/G7 -> -0.032788527 | H19: =H18/H7 -> -0.020053576
B20: Key Model Drivers
B21: Revenue Drivers(k)
B22: Major Clients | C22: 10 | D22: 18 | E22: 25 | F22: 30 | G22: 34 | H22: 36
B23: Average Boxes per Order | C23: 25 | D23: 26 | E23: 27 | F23: 28 | G23: 29 | H23: 30
B24: Orders per Client per year | C24: 12 | D24: 12 | E24: 12 | F24: 12 | G24: 12 | H24: 12
B25: Price Per Box | C25: 48 | D25: 49 | E25: 50 | F25: 51 | G25: 52 | H25: 53
B26: Cost of Revenue (% revenue) | C26: 1 | D26: 0.97 | E26: 0.94 | F26: 0.92 | G26: 0.9 | H26: 0.88
B28: Operating Drivers(k)
B29: Cash Compensation & benefits | C29: 0 | D29: 20 | E29: 40 | F29: 60 | G29: 75 | H29: 90
B30: Rent and occupancy | C30: 3 | D30: 3 | E30: 3.1 | F30: 3.1 | G30: 3.2 | H30: 3.2
B31: Delivery and Vehicle Expense | C31: 2 | D31: 2.4 | E31: 2.7 | F31: 2.8 | G31: 2.9 | H31: 3
B32: D&A (for a $3,000 van) | C32: 0.6 | D32: 0.6 | E32: 0.6 | F32: 0.6 | G32: 0.6 | H32: 0
B35: Dunder Miffin's Gross Margin | C35: 0.45
B36: Discount Rate | C36: 0.15

Sheet Sheet1
B2: PV of Future Client Retention
C3: 2010E | D3: 2011E | E3: 2012E | F3: 2013E | G3: 2014E
B4: New Clients Retained | C4: =Sheet3!D22-Sheet3!C22 -> 8 | D4: =Sheet3!E22-Sheet3!D22 -> 7 | E4: =Sheet3!F22-Sheet3!E22 -> 5 | F4: =Sheet3!G22-Sheet3!F22 -> 4 | G4: =Sheet3!H22-Sheet3!G22 -> 2
B5: Revenue per Client($k) | C5: =Sheet3!C7/Sheet3!C22 -> 14.4 | D5: =Sheet3!D7/Sheet3!D22 -> 15.288 | E5: =Sheet3!E7/Sheet3!E22 -> 16.2 | F5: =Sheet3!F7/Sheet3!F22 -> 17.136 | G5: =Sheet3!G7/Sheet3!G22 -> 18.096
B6: Revenue Retained | C6: =C5*C4 -> 115.2 | D6: =D5*D4 -> 107.016 | E6: =E5*E4 -> 81 | F6: =F5*F4 -> 68.544 | G6: =G5*G4 -> 36.192
B8: Gross Margin | C8: =$C$25 -> 0.45 | D8: =$C$25 -> 0.45 | E8: =$C$25 -> 0.45 | F8: =$C$25 -> 0.45 | G8: =$C$25 -> 0.45
B9: Gross Profit Retained | C9: =C8*C6 -> 51.84 | D9: =D8*D6 -> 48.1572 | E9: =E8*E6 -> 36.45 | F9: =F8*F6 -> 30.8448 | G9: =G8*G6 -> 16.2864
B10: Discount Rate | C10: =Sheet3!C36 -> 0.15 | D10: =Sheet3!D36 -> 0 | E10: =Sheet3!E36 -> 0 | F10: =Sheet3!F36 -> 0 | G10: =Sheet3!G36 -> 0
B11: PV of Retained Gross Profit | C11: =C9/(1+C10) -> 45.078261 | D11: =D9/(1+D10)^2 -> 48.1572 | E11: =E9/(1+E10)^3 -> 36.45 | F11: =F9/(1+F10)^4 -> 30.8448 | G11: =G9/(1+G10)^5 -> 16.2864
B13: Total PV off Future Client Retention | G13: =SUM(C11:G11) -> 176.81666
B19: Strategic Value Build
C20: ($k) | D20: Notes
B21: Existing Clients Recovered | C21: 10 | D21: linked
B22: Annual Revenue Per Client | C22: =Sheet3!C7/10 -> 14.4 | D22: linked
B23: Annual Revenue Recovered | C23: =C22*C21 -> 144
B25: Dunder Mifflin Gross Margin | C25: =Sheet3!C35 -> 0.45 | D25: csi paper company market data 2025
B26: Annual Gross Profit Recovered | C26: =C25*C23 -> 64.8
B28: PV of Recovered Gross Profit | C28: =PV(Sheet3!C36, 5, -C26) -> 217.21965
B29: PV of Future Client Retention | C29: =G13 -> 176.81666
B31: Total Strategic Benefit | C31: =C29+C28 -> 394.03631
B32: Less: Proposed Cash Consideration | C32: 60
B34: Net Value to Dunder Mifflin | C34: =C31-C32 -> 334.03631

Sheet Sheet2
A1: Revenue Build
B2: Actual | C2: Forecast
A3: FYE December | C3: 45657 | D3: 46022 | E3: 46387 | F3: 46752 | G3: 47118 | H3: 47483 | I3: 11323 | J3: 11688 | K3: 12054 | L3: 12419
A4: Currency | B4: USD | C4: USD | D4: USD | E4: USD | F4: USD | G4: USD | H4: USD | I4: USD | J4: USD | K4: USD | L4: USD
A5: Scale | B5: Million | C5: Million | D5: Million | E5: Million | F5: Million | G5: Million | H5: Million | I5: Million | J5: Million | K5: Million | L5: Million
A6: Clients | B6: 10
A7: Orders Per Clients | B7: 10
A8: Boxes Per Order | B8: 20 | C8: 439.2 | D8: 474.4 | E8: 512.3 | F8: 548.2 | G8: 583.8 | H8: 618.8 | I8: 643.6 | J8: 667.4 | K8: 690.8 | L8: 708.7
A9: Price Per Box | B9: 43 | C9: 36.4 | D9: 37.1 | E9: 38.2 | F9: 39.4 | G9: 40.6 | H9: 41.8 | I9: 43 | J9: 44.3 | K9: 45.6 | L9: 47
A10: Year-over-year growth(%) | B10: -0.19 | C10: -0.05 | D10: 0.02 | E10: 0.03 | F10: 0.03 | G10: 0.03 | H10: 0.03 | I10: 0.03 | J10: 0.03 | K10: 0.03 | L10: 0.03
A11: Total Revenue | B11: 448.8 | C11: 475.6 | D11: 511.5 | E11: 550.5 | F11: 587.6 | G11: 624.4 | H11: 660.6 | I11: 686.6 | J11: 711.7 | K11: 736.4 | L11: 755.7
A12: Year-over-year Growth | B12: 0.0391 | C12: 0.0598 | D12: 0.0754 | E12: 0.0764 | F12: 0.0672 | G12: 0.0627 | H12: 0.0581 | I12: 0.0394 | J12: 0.0366 | K12: 0.0347 | L12: 0.0262
