Workbook

Sheet Assumptions
B1: Assumptions
C2: ($mm except %s) | D2: notes
B3: Tax Rate | C3: 0.25
B4: Benchmark Rate | C4: 0.0058 | D4: 3-month average LIBOR from June 2021-2022
B5: 3-year credit spread | C5: 0.00875 | D5: via sec filing
B6: LIBOR | C6: 0.0055 | D6: for benchmark debt
B8: Purchase Price | C8: 2604.1
B9: % financed with equity | C9: 0
B10: % financed with debt | C10: 1
B11: % financed with cash | C11: 0
B13: Itiviti Earnings Growth | C13: 0.0973 | D13: privco
B14: Integration Costs | C14: 0
B15: Cross-Sell Penetration | C15: 0.03
B17: Itiviti 2020A Net Revenue | C17: =210*1.1064 -> 232.344 | D17: 2021 8-k Broadridge
B18: Itiviti 2020A Net Income | C18: =12.774*1.1064 -> 14.133154 | D18: 2021 8-k Broadridge
B19: Itivity 2020A Financial Expense | C19: =29.611*1.1064 -> 32.76161 | D19: 2021 8-k Broadridge
B21: Itiviti 2020 Debt Free Net Income | C21: =C18+(C19*(1-C3)) -> 38.704361
B22: Iitiviti Projected 2022 Revenue | C22: =C17*(1+C13)^2 -> 279.75781 | D22: limited financials - read analysis
B23: Itibiti FY2022E Debt-Free Net Income | C23: =C21*(1+C13)^2 -> 46.602656 | D23: limited financials - read analysis

Sheet Broadridge Consolidated Financi
B1: Broadridge Financial Solutions Inc.
B2: Income Statement - Annual
C3: Actuals | H3: Forecast
B4: FYE June | C4: 42551 | D4: 42916 | E4: 43281 | F4: 43646 | G4: 44012 | H4: 44377 | I4: 44742
B5: Currency | C5: USD | D5: USD | E5: USD | F5: USD | G5: USD | H5: USD | I5: USD
B6: Scale | C6: Million | D6: Million | E6: Million | F6: Million | G6: Million | H6: Million | I6: Million
B7: Total Revenue | C7: 2897 | D7: 4142.6 | E7: 4329.9 | F7: 4362.2 | G7: 4529 | H7: =G7*(1+H32) -> 4664.87 | I7: =H7*(1+I32) -> 4804.8161
B8: Year-over-year growth | D8: =D7/C7-1 -> 0.42996203 | E8: =E7/D7-1 -> 0.045213151 | F8: =F7/E7-1 -> 0.0074597566 | G8: =G7/F7-1 -> 0.038237587 | H8: =H7/G7-1 -> 0.03 | I8: =I7/H7-1 -> 0.03
B10: Cost of Revenue, Total | C10: 1975.9 | D10: 3109.6 | E10: 3169.6 | F10: 3131.9 | G10: 3265.1 | H10: =H7*H34 -> 3358.7064 | I10: =I7*I34 -> 3459.4676
B11: Gross Profit | C11: 921.1 | D11: 1033 | E11: 1160.3 | F11: 1230.3 | G11: 1263.9 | H11: =H7-H10 -> 1306.1636 | I11: =I7-I10 -> 1345.3485
B12: Selling/General/Admin. Expenses, Total | C12: 420.9 | D12: 501.4 | E12: 565.4 | F12: 577.5 | G12: 639 | H12: =H7*H35 -> 653.0818 | I12: =I7*I35 -> 672.67425
B13: Research & Development
B14: Depreciation/Amortization
B15: Interest Exp.(Inc.), Net-Operating, Total
B16: Unusual Expense (Income)
B17: Other Operating Expenses, Total
B18: Total Operating Expense | C18: 2396.8 | D18: 3611 | E18: 3735 | F18: 3709.5 | G18: 3904.1 | H18: =SUM(H10,H12:H17) -> 4011.7882 | I18: =SUM(I10,I12:I17) -> 4132.1418
B19: Operating Income | C19: 500.2 | D19: 531.6 | E19: 594.9 | F19: 652.7 | G19: 624.9 | H19: =H7-H18 -> 653.0818 | I19: =I7-I18 -> 672.67425
B20: Operating Margin | C20: =C19/C7 -> 0.17266137 | D20: =D19/D7 -> 0.12832521 | E20: =E19/E7 -> 0.13739347 | F20: =F19/F7 -> 0.14962634 | G20: =G19/G7 -> 0.13797748 | H20: =H19/H7 -> 0.14 | I20: =I19/I7 -> 0.14
B21: EBITDA | C21: =C19 -> 500.2 | D21: =D19 -> 531.6 | E21: =E19 -> 594.9 | F21: =F19 -> 652.7 | G21: =G19 -> 624.9 | H21: =H19 -> 653.0818 | I21: =I19 -> 672.67425
B22: EBITDA Margin | C22: =C21/C7 -> 0.17266137 | D22: =D21/D7 -> 0.12832521 | E22: =E21/E7 -> 0.13739347 | F22: =F21/F7 -> 0.14962634 | G22: =G21/G7 -> 0.13797748 | H22: =H21/H7 -> 0.14 | I22: =I21/I7 -> 0.14
B24: Interest Expense, Net | C24: -31.4 | D24: -43.4 | E24: -33.8 | F24: -41.8 | G24: -58.8 | H24: =G24*(1+H36) -> -70.62398 | I24: =H24*(1+I36) -> -84.825622
B25: Net Income | C25: 307.5 | D25: 326.7 | E25: 427.9 | F25: 482.1 | G25: 462.5 | H25: =(H19+H24)*(1-H37) -> 462.47151 | I25: =(I19+I24)*(1-I37) -> 466.75181
B27: Adjusted - GAAP net adjustments | C27: 51.5 | D27: 76.2 | E27: 71.5 | F27: 126 | G27: 119 | H27: =H7*(H38) -> 100.61561 | I27: =I7*(I38) -> 103.63408
B29: Key Model Drivers
B31: Revenue Drivers
B32: Year-over-year growth | H32: 0.03 | I32: 0.03
B33: Cost Drivers
B34: Cost of revenue (% Revenue) | C34: =C10/C7 -> 0.6820504 | D34: =D10/D7 -> 0.75063969 | E34: =E10/E7 -> 0.73202614 | F34: =F10/F7 -> 0.71796341 | G34: =G10/G7 -> 0.72093177 | H34: 0.72 | I34: 0.72
B35: SG&A (% of Revenue) | C35: =C12/C7 -> 0.14528823 | D35: =D12/D7 -> 0.1210351 | E35: =E12/E7 -> 0.13058038 | F35: =F12/F7 -> 0.13238733 | G35: =G12/G7 -> 0.14109075 | H35: 0.14 | I35: 0.14
B36: Change in Interest Expense(%) | D36: =(D24-C24)/C24 -> 0.38216561 | E36: =(E24-D24)/D24 -> -0.22119816 | F36: =(F24-E24)/E24 -> 0.23668639 | G36: =(G24-F24)/F24 -> 0.40669856 | H36: =AVERAGE(D36:G36) -> 0.2010881 | I36: =AVERAGE(D36:G36) -> 0.2010881
B37: Effecive Tax Rate | C37: 0.34420985 | D37: 0.33066994 | E37: 0.20962567 | F37: 0.20533509 | G37: 0.20189819 | H37: 0.206 | I37: 0.206
B38: GAAP add backs(% Revenue) | C38: =C27/C7 -> 0.017777011 | D38: =D27/D7 -> 0.018394245 | E38: =E27/E7 -> 0.016513083 | F38: =F27/F7 -> 0.028884508 | G38: =G27/G7 -> 0.026275116 | H38: =AVERAGE($C$38:$G$38) -> 0.021568793 | I38: =AVERAGE($C$38:$G$38) -> 0.021568793

Sheet Transaction Adjustments
B1: Interest Expense Calculation | F1: Cross-Selling Synergy Build(FY 2022)
B2: Debt | C2: Debt Balance(mm) | D2: Rate | F2: Itiviti Customers | G2: 2000
B3: Senior Notes | C3: 1000 | D3: 0.026 | F3: Itiviti 2022E Revenue ($mm) | G3: =Assumptions!C22 -> 279.75781
B4: Term Loan | C4: 1550 | D4: =Assumptions!$C$6+Assumptions!$C$5 -> 0.01425 | F4: Average Revenue per Customer ($000) | G4: =G3*1000/G2 -> 139.87891
F6: Cross-Sell Penetration | G6: 0.02
B7: Total Pre-tax annual interest expense | C7: =(C3*D3)+C4*D4 -> 48.0875 | F7: Converted Customers | G7: =G2*G6 -> 40
B8: Total After-tax annual interest expense | C8: =C7*(1-Assumptions!$C$3) -> 36.065625
F9: Revenue per Converted Customer ($000) | G9: =G4 -> 139.87891
F10: Revenue Synergies ($mm) | G10: =G9*G7 / 1000 -> 5.5951562
F12: Incremental Operating Margin | G12: 0.3
F13: Pre-Tax Earnings Synergies ($mm) | G13: =G12*G10 -> 1.6785469
F15: Tax Rate | G15: 0.25
F16: After-Tax Synergies ($mm) | G16: =G13*(1-G15) -> 1.2589101
B28: Acquisition-Related Amoritization
B29: New Acquired Intangible | C29: Value | D29: Life | E29: Amoritization($mm)
B30: Software technology | C30: 181.1 | D30: 5 | E30: =C30/D30 -> 36.22
B31: Customer relationships and trade names | C31: 677.3 | D31: 7 | E31: =C31/D31 -> 96.757143
B33: Amoritization Adjustment
B34: Old Amoritization | C34: 48.4
B35: Pre-tax incremental acquisiton amoritization | C35: =SUM(E30:E31) -C34 -> 84.577143
B36: After-tax incremental acquisiton amoritization | C36: =C35*(1-Assumptions!C3) -> 63.432857

Sheet Accretion-Dilution
B3: Accretion - Dilution (GAAP) | E3: Accretion - Dilution (Adjusted)
C4: (mm besides EPS and %) | F4: (mm besides EPS and %)
B5: Broadridge 2022E Net Income | C5: ='Broadridge Consolidated Financi'!I25 -> 466.75181 | E5: Broadridge 2022E Net Income | F5: ='Broadridge Consolidated Financi'!I25 -> 466.75181
B6: Broadridge 2022 Diluted Shares | C6: 118 | E6: Broadridge 2022 Diluted Shares | F6: 118
B7: Broadridge 2022E EPS | C7: =C5/C6 -> 3.9555238 | E7: Broadridge 2022E Adjusted Diluted EPS | F7: =('Broadridge Consolidated Financi'!I25+'Broadridge Consolidated Financi'!I27)/F6 -> 4.8337788
B9: Itiviti 2022E Net Income | C9: =Assumptions!C23 -> 46.602656 | E9: Itiviti 2022E Net Income | F9: =Assumptions!$C$23 -> 46.602656
B11: Purchase Price | C11: =Assumptions!C8 -> 2604.1 | E11: Purchase Price | F11: =Assumptions!$C$8 -> 2604.1
B12: % financed with equity | C12: =Assumptions!$C9 -> 0 | E12: % financed with equity | F12: =Assumptions!$C9 -> 0
B13: % financed with debt | C13: =Assumptions!$C10 -> 1 | E13: % financed with debt | F13: =Assumptions!$C10 -> 1
B14: % financed with cash | C14: =Assumptions!$C11 -> 0 | E14: % financed with cash | F14: =Assumptions!$C11 -> 0
B16: Combined Net Income before Adjustment | C16: =C5+C9 -> 513.35447 | E16: Combined Net Income before Adjustment | F16: =F5+F9 -> 513.35447
B17: Adjustments to Net Income | E17: Adjustments to Net Income
B18: Less: After-Tax Annual Interest Expense from Debt | C18: ='Transaction Adjustments'!C8 -> 36.065625 | E18: Less: After-Tax Annual Interest Expense from Debt | F18: ='Transaction Adjustments'!$C$8 -> 36.065625
B19: Less: After-Tax Annual Interest Income (Lost) from Cash | C19: 0 | E19: Less: After-Tax Annual Interest Income (Lost) from Cash | F19: 0
B20: Add: 2022E After-Tax Synergies | C20: ='Transaction Adjustments'!$G$16 -> 1.2589101 | E20: Add: 2022E After-Tax Synergies | F20: ='Transaction Adjustments'!$G$16 -> 1.2589101
B21: Less: Acquisiton-related amoritization | C21: ='Transaction Adjustments'!C36 -> 63.432857 | E21: Less: Acquisiton-related amoritization | F21: ='Transaction Adjustments'!$C$36 -> 63.432857
B22: Less: Integration costs | C22: 0 | E22: Less: Integration costs | F22: 0
B24: GAAP Net Income | C24: =C16-C18-C19+C20-C21-C22 -> 415.1149 | E24: GAAP Net Income | F24: =F16-F18-F19+F20-F21-F22 -> 415.1149
E26: Adjusted EPS Bridge
E27: Add Back: broad ridge stand alone non-gaap adjustments | F27: ='Broadridge Consolidated Financi'!I27 -> 103.63408
E28: Add Back: after-tax acquisition-related amoritization | F28: =F21 -> 63.432857
E29: Add Back: Integration costs
E30: Adjusted Income | F30: =F24+F28+F27 -> 582.18184
B32: Broadridge FDSO | C32: 118 | E32: Broadridge FDSO | F32: 118
B33: Adjustment to Broadridge FDSO | C33: 0 | E33: Adjustment to Broadridge FDSO | F33: 0
B34: Pro Forma FDSO | C34: =SUM(C32:C33) -> 118 | F34: =SUM(F32:F33) -> 118
B36: Combined EPS | C36: =C24/C34 -> 3.5179229 | E36: Adjusted Combined EPS | F36: =F30/F34 -> 4.9337444
B37: Accretin/Dilution % | C37: =(C36-C7)/C7 -> -0.11063035 | E37: Adjusted Accretion/Dilution % | F37: =(F36-F7)/F7 -> 0.020680632
B38: Decision | C38: =IF(C37<0,"Dilutive","Accretive") -> Dilutive | E38: Decision | F38: =IF(F37<0,"Dilutive","Accretive") -> Accretive
